Workbook
Name ATC: ATC!$A$2:$A$593
Name CIRUGIA: 'CUPS CIRUGÍA'!$A$9
Name CUPSCX: 'CUPS CIRUGÍA'!$A$2:$A$2557
Name IPS: CÓD_HABILITACIÓN!$A$2:$A$111

Sheet PACIENTES
A1: No. VARIABLE | B1: 1 | C1: 2 | D1: 3 | E1: 4 | F1: 5 | G1: 6 | H1: 7 | I1: 8 | J1: 9 | K1: 10 | L1: 11 | M1: 12 | N1: 13 | O1: 14 | P1: 15 | Q1: 16 | R1: 17 | S1: 18 | T1: 19 | U1: 20 | V1: 21 | W1: 22 | X1: 23 | Y1: 24 | Z1: 25 | AA1: 26 | AB1: 27 | AC1: 28 | AD1: 29 | AE1: 30 | AF1: 31 | AG1: 32 | AH1: 33 | AI1: 34 | AJ1: 35 | AK1: 36 | AL1: 37 | AM1: 38 | AN1: 39 | AO1: 40 | AP1: 41 | AQ1: 42 | AR1: 43 | AS1: 44 | AT1: 45 | AU1: 46 | AV1: 46.1 | AW1: 46.2 | AX1: 46.3 | AY1: 46.4 | AZ1: 46.5 | BA1: 46.6 | BB1: 46.7 | BC1: 46.8 | BD1: 47 | BE1: 48 | BF1: 49 | BG1: 50 | BH1: 51 | BI1: 52 | BJ1: 53 | BK1: 53.1 | BL1: 53.2 | BM1: 53.3 | BN1: 53.4 | BO1: 53.5 | BP1: 53.6 | BQ1: 53.7 | BR1: 53.8 | BS1: 53.9 | BT1: 54 | BU1: 55 | BV1: 56 | BW1: 57 | BX1: 58 | BY1: 59 | BZ1: 60 | CA1: 61 | CB1: 62 | CC1: 63 | CD1: 64 | CE1: 65 | CF1: 66 | CG1: 66.1 | CH1: 66.2 | CI1: 66.3 | CJ1: 66.4 | CK1: 66.5 | CL1: 66.6 | CM1: 66.7 | CN1: 66.8 | CO1: 66.9 | CP1: 67 | CQ1: 68 | CR1: 69 | CS1: 70 | CT1: 71 | CU1: 72 | CV1: 73 | CW1: 74 | CX1: 75 | CY1: 76 | CZ1: 77 | DA1: 78 | DB1: 79 | DC1: 80 | DD1: 81 | DE1: 82 | DF1: 83 | DG1: 84 | DH1: 85 | DI1: 86 | DJ1: 87 | DK1: 88 | DL1: 89 | DM1: 90 | DN1: 91 | DO1: 92 | DP1: 93 | DQ1: 94 | DR1: 95 | DS1: 96 | DT1: 97 | DU1: 98 | DV1: 99 | DW1: 100 | DX1: 101 | DY1: 102 | DZ1: 103 | EA1: 104 | EB1: 105 | EC1: 106 | ED1: 107 | EE1: 108 | EF1: 109 | EG1: 110 | EH1: 111 | EI1: 112 | EJ1: 113 | EK1: 114 | EL1: 114.1 | EM1: 114.2 | EN1: 114.3 | EO1: 114.4 | EP1: 114.5 | EQ1: 114.6 | ER1: 115 | ES1: 116 | ET1: 117 | EU1: 118 | EV1: 119 | EW1: 120 | EX1: 121 | EY1: 122 | EZ1: 123 | FA1: 124 | FB1: 125 | FC1: 126 | FD1: 127 | FE1: 128 | FF1: 129 | FG1: 130 | FH1: 131 | FI1: 132 | FJ1: 133 | FK1: 134
A2: Nombre del campo | B2: Primer nombre del usuario | C2: Segundo nombre del usuario | D2: Primer apellido del usuario | E2: Segundo apellido del usuario | F2: Tipo de Identificación del usuario | G2: Número de Identificación del usuario | H2: Fecha de nacimiento | I2: Sexo | J2: Ocupación | K2: Régimen de afiliación AL SGSSS | L2: Código de la EPS o de la entidad territorial | M2: Código pertenencia étnica | N2: Grupo poblacional | O2: Municipio de residencia | P2: Númerotelefónicodelpaciente(incluyendoafamiliaresycuidadores) | Q2: Fecha de afiliación a la EAPB que reporta | R2: Codigo CIE -10 de la neoplasia (cáncer o tumor) maligna reportada(Primario) | S2: Fecha de Diagnóstico del Cáncer reportado | T2: Fecha de la nota de remisión del médico o institución general hacia la institución o médico que hizo el diagnóstico | U2: Fecha de ingreso a la institución que realizó el diagnóstico luego de la remisión intenconsulta | V2: Tipo de estudio con el que se realizó el diagnóstico de cáncer | W2: Motivo por el cual el usuario no tuvo diagnóstico por histopatología (aplica para registros con respuesta igual a 7 en la variable anterior) | X2: Fecha de recolección de muestra para estudio histopatológico de diagnóstico | Y2: Fecha de Primero o único informe histopatológico válido de diagnóstico | Z2: Código válido de habilitación de la IPS donde se realiza la confirmación diagnóstica | AA2: Fecha de primera consulta con médico tratante de la enfermedad maligna(médico especialista que define la primera conducta terapéutica-terapia sistémica, cirugía , radioterapia o cuidado paliativos- manejo expectante) | AB2: Histología del tumor en muestra de biopsia o quirúrgica | AC2: Grado de diferenciación del tumor sólido maligno según la biopsia o informe de primera cirugía | AD2: Si es tumor sólido, cuál fue la primera estadificación basada en TNM, FIGO, u otras compatibles con esta numeración según tumor. | AE2: Fecha en que se realizó esta estadificación | AF2: Para cáncer de mama, ¿se le realizó a este usuario la prueba HER2 (llamado también receptor 2 del factor de crecimiento epidérmico humano, también llamado erb-B2) antes del inicio del tratamiento? | AG2: Para cáncer de mama, fecha de realización de la última prueba HER2 | AH2: Para cáncer de mama, resultado de la ultima prueba HER2 | AI2: Para cáncer colorrectal, estadificación de Dukes | AJ2: Fecha en que se realizó la estadificación de Dukes | AK2: Estadificación clínica en linfoma no Hodgkin, linfoma Hodgkin adulto y pediátrico (Ann Arbor - Lugano) y mieloma múltiple | AL2: Para cáncer de próstata, valor de clasificación de la escala Gleason en el momento del diagnóstico | AM2: Clasificación de riesgo leucemias o linfomas, y sólidos pediátricos | AN2: Fecha de clasificación de riesgo | AO2: Objetivo (o intención) del tratamiento médico inicial (al diagnóstico) | AP2: Objetivo de la intervención médica durante el periodo de reporte. | AQ2: Tiene antecedente de otro cáncer primario (es decir, tiene o tuvo otro tumor maligno diferente al que está notificando) | AR2: Fecha de diagnóstico del otro cáncer primario | AS2: Tipo (CIE-10) de ese cáncer antecedente | AT2: ¿Recibió el usuario quimioterapia u otra terapia sistémica (incluye quimioterapia, hormonoterapia, inmunoterapia) dentro del periodo de corte actual? (Aclaración: en esta sección solo incluya ciclos iniciados en este corte. Por favor, no incluya el último ciclo informado como "actual" en el corte anterior, así se haya terminado en el periodo actual de reporte). | AU2: ¿Cuántas fases de quimioterapia recibió el usuario en este corte? (aplica para hematolinfáticos) | AV2: El usuario recibió en este corte la fase de quimioterapia denominada Prefase o Citorreducción inicial (aplica solo para leucemia linfoide aguda y linfoma linfoblástico, puede haber recibido más de una fase): | AW2: El usuario recibió en este corte la fase de quimioterapia denominada Inducción (aplica solo para leucemia linfoide o mieloide aguda y linfoma linfoblástico, puede haber recibido más de una fase) | AX2: El usuario recibió en este corte la fase de quimioterapia denominada Intensificación (aplica solo para leucemia linfoide aguda y o mieloide linfoma linfoblástico, puede haber recibido más de una fase) | AY2: El usuario recibió en este corte la fase de quimioterapia denominada Consolidación (aplica solo para leucemia linfoide aguda y o mieloide linfoma linfoblástico, puede haber recibido más de una fase) | AZ2: El usuario recibió en este corte la fase de quimioterapia denominada Reinducción (aplica solo para leucemia linfoide aguda y linfoma linfoblástico, puede haber recibido más de una fase | BA2: El usuario recibió en este corte la fase de quimioterapia denominada Mantenimiento (aplica solo para leucemia linfoide o mieloide aguda y linfoma linfoblástico, puede haber recibido más de una fase) | BB2: El usuario recibió en este corte la fase de quimioterapia denominada Mantenimiento largo o final (aplica solo para leucemia linfoide o mieloide aguda y linfoma linfoblástico, puede haber recibido más de una fase) | BC2: El usuario recibió en este corte Otra fase de quimioterapia denominada diferente a las anteriores (aplica solo para leucemia linfoide o mieloide aguda y linfoma linfoblástico, puede haber recibido más de una fase) | BD2: Número de ciclos iniciados y administrados en el periodo de reporte, incluyendo el que aún recibe en la fecha de corte. | BE2: Ubicación temporal del primer ciclo en el periodo en relación al manejo oncológico | BF2: Fecha de inicio del primer ESQUEMA de quimioterapia de este periodo de reporte. Si es hormonoterapia reporte la fecha de inicio del tratamiento actual, así haya sido iniciada previo al reporte actual | BG2: Número de IPS que suministran el primer ciclo de este corte | BH2: Código de la IPS1 que suministra el primer ciclo de este corte | BI2: Código de la IPS2 que suministra el primer ciclo de este corte | BJ2: Cuantos medicamentos antineoplásicos, el (los) especialista(s) tratante(s) del cáncer propusieron como manejo en el primer ciclo de este corte | BK2: Medicamento antineoplasico administrado al usuario - PRIMER O UNICO esquema en el periodo del reporte | BL2: Medicamento antineoplasico administrado al usuario - PRIMER O UNICO esquema en el periodo del reporte | BM2: Medicamento antineoplasico administrado al usuario - PRIMER O UNICO esquema en el periodo del reporte | BN2: Medicamento antineoplasico administrado al usuario - PRIMER O UNICO esquema en el periodo del reporte | BO2: Medicamento antineoplasico administrado al usuario - PRIMER O UNICO esquema en el periodo del reporte | BP2: Medicamento antineoplasico administrado al usuario - PRIMER O UNICO esquema en el periodo del reporte | BQ2: Medicamento antineoplasico administrado al usuario - PRIMER O UNICO esquema en el periodo del reporte | BR2: Medicamento antineoplasico administrado al usuario - PRIMER O UNICO esquema en el periodo del reporte | BS2: Medicamento antineoplasico administrado al usuario - PRIMER O UNICO esquema en el periodo del reporte | BT2: Medicamento ANTINEOPLASICO - o terapia hormonal para cancer, adicional a los reportados en las variables 53.1 a 53.9, administrados al usuario en el primer o unico esquema. | BU2: Medicamento ANTINEOPLASICO - o terapia hormonal para cancer, adicional a los reportados en las variables 53.1 a 53.9, administrados al usuario en el primer o unico esquema. | BV2: Medicamento ANTINEOPLASICO - o terapia hormonal para cancer, adicional a los reportados en las variables 53.1 a 53.9, administrados al usuario en el primer o unico esquema. | BW2: ¿Recibió quimioterapia intratecal en el primer ciclo de este corte? | BX2: Fecha de finalización del primer ESQUEMA de este periodo de reporte. Si es hormonoterapia reporte la fecha de finalización del tratamiento actual | BY2: Características actuales del primer ESQUEMA de este corte | BZ2: Motivo de la finalización (prematura) de este primer ESQUEMA (Aplica si registró la opción 2 de la pregunta anterior) Selecciona un sólo número (lo que primero ocurrió). | CA2: Ubicación temporal del último ESQUEMA de este corte en relación al manejo oncológico | CB2: Fecha de inicio del últimoESQUEMA de quimioterapia de este periodo de reporte. Si es hormonoterapia reporte la fecha de inicio del tratamiento actual, así haya sido iniciada previo al reporte actual | CC2: Número de IPS que suministran el último ESQUEMA de este corte | CD2: Código de la IPS1 que suministra el último ESQUEMA en este reporte | CE2: Código de la IPS2 que suministra el último ESQUEMA en este reporte | CF2: Cuantos medicamentos antineoplásicos, el (los) especialista(s) tratante(s) del cáncer propusieron como manejo en este último ciclo de este corte | CG2: Medicamento antineoplasico administrado al usuario - ULTIMO esquema en el periodo del reporte | CH2: Medicamento antineoplasico administrado al usuario - ULTIMO esquema en el periodo del reporte | CI2: Medicamento antineoplasico administrado al usuario - ULTIMO esquema en el periodo del reporte | CJ2: Medicamento antineoplasico administrado al usuario - ULTIMO esquema en el periodo del reporte | CK2: Medicamento antineoplasico administrado al usuario - ULTIMO esquema en el periodo del reporte | CL2: Medicamento antineoplasico administrado al usuario - ULTIMO esquema en el periodo del reporte | CM2: Medicamento antineoplasico administrado al usuario - ULTIMO esquema en el periodo del reporte | CN2: Medicamento antineoplasico administrado al usuario - ULTIMO esquema en el periodo del reporte | CO2: Medicamento antineoplasico administrado al usuario - ULTIMO esquema en el periodo del reporte | CP2: Medicamento ANTINEOPLASICO - o terapia hormonal para cancer, adicional a los reportados en las variables 66.1 a 66.9, administrados al usuario en el ultimo esquema | CQ2: Medicamento ANTINEOPLASICO - o terapia hormonal para cancer, adicional a los reportados en las variables 66.1 a 66.9, administrados al usuario en el ultimo esquema | CR2: Medicamento ANTINEOPLASICO - o terapia hormonal para cancer, adicional a los reportados en las variables 66.1 a 66.9, administrados al usuario en el ultimo esquema | CS2: ¿Recibió quimioterapia intratecal en el último ciclo de este corte? | CT2: Fecha de finalización del último ESQUEMA de este periodo de reporte. Si es hormonoterapia reporte la fecha de finalización del tratamiento actual | CU2: Características actuales del último ESQUEMA de este corte | CV2: Motivo de la finalización (prematura) de este último ciclo (Aplica si registró la opción 2 de la pregunta anterior) Selecciona un sólo número (lo que primero ocurrió). | CW2: ¿Fue sometido el usuario a una o más cirugías curativas o paliativas como parte del manejo del cáncer durante este reporte? | CX2: Número de cirugías a las que fue sometido el usuario durante el periodo de reporte actual | CY2: Fecha de realización de la primera cirugía en este reporte | CZ2: Código de la IPS que realizó la primera cirugía de este corte | DA2: Código de primera cirugía | DB2: Ubicación temporal de esta primera cirugía en relación al manejo oncológico | DC2: Fecha de realización del último procedimiento quirúrgico o de reintervención en este corte. | DD2: Motivo de haber realizado la última intervención quirúrgica de este este periodo de reporte | DE2: Código de la IPS que realiza el último de los procedimientos quirúrgicos en este corte | DF2: Código de última cirugía | DG2: Ubicación temporal de esta última cirugía en relación al manejo oncológico, en este periodo de reporte | DH2: Estado vital al finalizar la única o última cirugía de este periodo de reporte | DI2: ¿Recibió el usuario algún tipo de radioterapia en el corte actual? | DJ2: Número de sesiones de radioterapia suministrados en el periodo de reporte actual | DK2: Fecha de inicio de primer o único esquema de radioterapia suministrado en el corte actual | DL2: Ubicación temporal del primer o único esquema de radioterapia en este corte | DM2: Tipo de radioterapia aplicada en este primer o único esquema | DN2: Número de IPS que suministran este primer o único esquema de radioterapia | DO2: Código de la IPS1 que suministra la radioterapia | DP2: Código de la IPS2 que suministra la radioterapia | DQ2: Fecha de finalización de primer o único esquema de radioterapia | DR2: Características actuales de este primer o único esquema de radioterapia | DS2: Motivo de la finalización de este primer o único esquema de radioterapia (Aplica si registró la opción 2 de la pregunta anterior) Selecciona un sólo número (lo que primero ocurrió). | DT2: Fecha de inicio del último esquema de radioterapia suministrado en el corte actual | DU2: Ubicación temporal/Intención del último esquema de radioterapia suministrado en el corte actual | DV2: Tipo de radioterapia aplicada en el último esquema de radioterapia suministrado en el corte actual | DW2: Número de IPS que suministran este último esquema de radioterapia suministrado en el corte actual | DX2: Código de la IPS1 que suministra la radioterapia | DY2: Código de la IPS2 que suministra la radioterapia | DZ2: Fecha de finalización del último esquema de radioterapia suministrado en el corte actual | EA2: Características actuales de este último esquema de radioterapia suministrado en el corte actual | EB2: Motivo de la finalización de este último esquema de radioterapia suministrado en el corte actual (Aplica si registró la opción 2 de la pregunta anterior) Selecciona un sólo número (lo que primero ocurrió). | EC2: ¿Recibió el usuario trasplante de células progenitoras hematopoyética dentro del periodo de corte actual? | ED2: Tipo de trasplante recibido | EE2: Ubicación temporal de este trasplante en relación al manejo oncológico | EF2: Fecha de trasplante | EG2: Código de la IPS que realizó este trasplante | EH2: El usuario, ¿recibió cirugía reconstructiva? | EI2: Fecha de la cirugía | EJ2: Código de la IPS que realizó cirugía reconstructiva | EK2: ¿El usuario fue valorado en consulta o procedimiento de cuidado paliativo durante este corte? (pueden haber sido múltiples) | EL2: El usuario recibió consulta o procedimiento de cuidado paliativo en este corte, por médico especialista en cuidado paliativo | EM2: El usuario recibió consulta o procedimiento de cuidado paliativo en este corte, por profesional de la salud (no médico, incluye psicólogo) especialista en cuidado paliativo | EN2: El usuario recibió consulta o procedimiento de cuidado paliativo en este corte, por médico especialista, otra especialidad | EO2: El usuario recibió consulta o procedimiento de cuidado paliativo en este corte, por médico general | EP2: El usuario recibió consulta o procedimiento de cuidado paliativo en este corte, por trabajo social | EQ2: El usuario recibió consulta o procedimiento de cuidado paliativo en este corte, por otro profesional de salud (no médico, incluye psicólogo) no especializado | ER2: Fecha de primera consulta o procedimiento de cuidado paliativo en este corte | ES2: Código de la IPS donde recibió la ATENCIÓN de cuidado Paliativo | ET2: ¿Ha sido valorado el usuario por el servicio de psiquiatría durante este corte? | EU2: Fecha de primera consulta con el servicio de psiquiatría (para todos los usuarios) en este corte | EV2: Código de la IPS donde recibió la primera valoración de psiquiatría en este corte | EW2: ¿Fue valorado el usuario por profesional en nutrición durante este corte? | EX2: Fecha de consulta inicial con nutrición en este corte | EY2: Código de la IPS donde recibió la valoración por nutrición, en este corte | EZ2: ¿El usuario recibió soporte nutricional? | FA2: ¿El usuario ha recibido terapias complementarias para su rehabilitación? | FB2: Tipo de tratamiento que está recibiendo el usuario a la fecha de corte | FC2: Resultado final del manejo oncológico en este corte | FD2: Estado vital al finalizar este corte | FE2: Novedad ADMINISTRATIVA del usuario respecto al reporte anterior | FF2: Novedad clínica del usuario a la fecha de corte | FG2: Fecha de desafiliación de la EPS | FH2: Fecha de muerte | FI2: Causa de muerte | FJ2: Código único de identificación BDUA | FK2: Diligencie esta variable con la fecha 2021-01-01
A3: Valores permitidos | B3: Escriba el primer nombre del usuario. | C3: Escriba el segundo nombre del usuario. En caso de un tercer nombre, escríbalo separado por un espacio. Registre "NONE", en mayúscula sostenida, cuando el usuario no tiene segundo nombre (NONE="Ningún Otro Nombre Escrito"). | D3: Escriba el primer apellido del usuario. | E3: Escriba el segundo apellido del usuario. Registre "NOAP", en mayúscula sostenida, cuando el usuario no tiene segundo apellido (NOAP=Ningún Otro Apellido") | F3: RC=Registro Civil TI=Tarjeta Identidad CC=Cédula de Ciudadanía CE=Cédula Extranjería PA=Pasaporte MS=Menor sin Identificación (solo para el Régimen Subsidiado) AS=Adulto sin Identificación (solo para el Régimen Subsidiado) CD=Carnet Diplomático SD= Salvoconducto de Permanencia PE=Permiso Especial | G3: Número de identificación del afiliado según el tipo de identificación.Para MS y AS registre el consecutivo interno del afiliado según lo dispuesto en la Resolución 4622/2016. | H3: Fecha de nacimiento del usuario en el formato AAAA-MM-DD. | I3: M= masculino F= femenino | J3: Código según la Clasificación Internacional Uniforme de Ocupaciones. 9999= No existe información 5555= Persona con aseguramiento (régimen subsidiado o contributivo y que no son PPNA)que recibió servicios de salud por parte del ente territorial durante el periodo de reporte. 9998= No Aplica | K3: C=Régimen Contributivo S=Régimen Subsidiado P=Regímenes de excepción E=Régimen especial N=No asegurado | L3: Cuando el usuario tenga EPS u otra EOC escriba el código de la empresa aseguradora que registra al usuario . Cuando el usuario sea notificado por entidad territorial escriba el código de departamento yseguido de tres ceros | M3: Registre el grupo étnico del usuario: 1=Indígena 2=ROM (gitano) 3=Raizal del archipiélago de San Andrés y Providencia 4=Palenquero de San Basilio 5=Negro(a), mulato(a), afro colombiano(a) o afro descendiente 6=Ninguna de las anteriores 55= Persona con aseguramiento (régimen subsidiado o contributivo y que no son PPNA)que recibió servicios de salud por parte del ente territorial durante el periodo de reporte. | N3: 1=Indigentes 2=Población infantil a cargo del ICBF 3=Madres comunitarias 4=Artistas, autores, compositores 5=Otro grupo poblacional 6=Recién Nacidos 7=Discapacitados 8=Desmovilizados 9=Desplazados 10=Población ROM 11=Población raizal 12=Población en centros psiquiátricos 13=Migratorio 14=Población en centros carcelarios 15=Población rural no migratoria 16=Afrocolombiano 31=Adulto mayor 32=Cabeza de familia 33=Mujer embarazada 34=Mujer lactante 35=Trabajador urbano 36=Trabajador rural 37=Víctima de violencia armada 38=Jóvenes vulnerables rurales 39=Jóvenes vulnerables urbanos 50=Discapacitado - el sistema nervioso 51=Discapacitado - los ojos 52=Discapacitado - los oídos 53=Discapacitado - los demás órganos de los sentidos (olfato, tacto y gusto) 54=Discapacitado - la voz y el habla 55=Discapacitado - el sistema cardiorrespiratorio y las defensas 56=Discapacitado - la digestión, el metabolismo, las hormonas 57=Discapacitado - el sistema genital y reproductivo 58=Discapacitado - el movimiento del cuerpo, manos, brazos, piernas 59=Discapacitado - la piel 60=Discapacitado - otra 61=No definido 62=Comunidad Indígena 63=Población Migrante de la República Bolivariana de Venezuela 555= Persona con aseguramiento (régimen subsidiado o contributivo y que no son PPNA)que recibió servicios de salud por parte del ente territorial durante el periodo de reporte. | O3: Registre el Código del municipio en donde reside el afiliado según la división político administrativa DIVIPOLA – DANE. Este código debe ser reportado en 5 dígitos, donde los dos primeros dígitos corresponden al departamento donde se localiza el municipio. | P3: Registresólodosnúmerosdeteléfono(s)fijosy/omóvilescompletosparacontactaralpacienteysepareporcomas.Sinosetieneelnúmerotelefónicodelpaciente(incluyendofamiliaresycuidadores)diligencie0 | Q3: Fecha en la que el usuario se afilió a la EPS en el formato AAAA-MM-DD. | R3: Registre el código de la enfermedad maligna que fue inicialmente diagnosticada al usuario según código CIE -10. Si el paciente tuvo inicialmente diagnóstico Clínico que posteriormente fue confirmado con histopatología, en esta variable debe registrar el CIE -10 de la confirmación histopatológica. | S3: Escriba la fecha de diagnóstico en formato AAAA-MM-DD (con guion “-“ como separador). Si conoce sólo el año y el mes, registre el día 15. Registre 1800-01-01= Desconocido, el dato de esta variable no se encuentra descrito en los soportes clínicos Registre 1846-01-01= Persona con aseguramiento (régimen subsidiado o contributivo y que no son PPNA) que recibió servicios de salud por parte del ente territorial durante el periodo de reporte. | T3: Revisar en la historia clínica la remisión más antigua disponible previa al diagnóstico y que pudiese estar asociada a la enfermedad maligna actual (debe ser menor o igual a la fecha de ingreso a la institución que realizó el diagnóstico, solicitada en la variable 20). Escriba la fecha de esa remisión en formato AAAA-MM-DD (con guion “-” como separador). Si conoce sólo el año y el mes, registre el día 15. Registre 1800-01-01= Desconocido, el dato de esta variable no se encuentra descrito en los soportes clínicos Registre 1846-01-01= Persona con aseguramiento (régimen subsidiado o contributivo y que no son PPNA) que recibió servicios de salud por parte del ente territorial durante el periodo de reporte. | U3: Registre la fecha en formato AAAA-MM-DD (si no hay remisión o interconsulta registre la fecha de primera consulta relacionada al cáncer en la institución que realizó el diagnóstico). Si conoce sólo el año y el mes, registre el día 15. Registre 1800-01-01= desconocida.(opción válida solo en caso de diagnóstico antes de 2015-01-01, se aclara que, si el diagnóstico fue previo a la fecha mencionada, pero se tiene el dato solicitado entonces se debe reportar). Registre 1846-01-01= Persona con aseguramiento (régimen subsidiado o contributivo y que no son PPNA)que recibió servicios de salud por parte del ente territorial durante el periodo de reporte. | V3: Tipo de prueba registre: 5= Inmunohistoquímica 6= Citometría de flujo 7= Clínica exclusivamente (incluye estudios imagenológicos y/o de laboratorio en aquellos casos clínicamente justificados en donde fue imposible tomar muestra de estudio histopatológico) 8=Otro 9= Genética 10= Patología básica 99= Desconocido, el dato de esta variable no se encuentra descrito en los soportes clínicos. 55= Persona con aseguramiento (régimen subsidiado o contributivo y que no son PPNA) que recibió servicios de salud por parte del ente territorial durante el periodo de reporte. | W3: 1= Clínica, usuario con coagulopatía 2= Clínica, debido a localización del tumor 3= Clínica, debido al estado funcional del usuario (deterioro) 4= Negativa del usuario o su acudiente para realizar el estudio histopatológico, con documentación de soporte 5= Administrativa 6= Clínica por reporte de imágenes o laboratorios. 55= Persona con aseguramiento (régimen subsidiado o contributivo y que no son PPNA) que recibió servicios de salud por parte del ente territorial durante el periodo de reporte. 98= Tiene confirmación por histopatología. 99= Desconocido, el dato de esta variable no se encuentra descrito en los soportes clínicos. | X3: Registre la fecha en el formato AAAA-MM-DD. Si conoce sólo el año y el mes, registre el día 15. Registre 1800-01-01= Desconocido, el dato de esta variable no se encuentra descrito en los soportes clínicos. Registre 1845-01-01= No se realizó estudio histopatológico (en la variable 21 registro la opción 7). Registre 1846-01-01= Persona con aseguramiento (régimen subsidiado o contributivo y que no son PPNA) que recibió servicios de salud por parte del ente territorial durante el periodo de reporte. | Y3: Registre la fecha en el formato AAAA-MM-DD. (Registre la fecha de la primera prueba que confirmó diagnóstico de cáncer y dio inicio a un manejo, así haya requerido pruebas adicionales posteriormente para el diagnóstico definitivo). Si conoce sólo el año y el mes, registre el día 15. Registre 1800-01-01= Desconocido, el dato de esta variable no se encuentra descrito en los soportes clínicos. Registre 1845-01-01=No se realizó estudio histopatológico(en la variable 21 registro la opción 7). Registre 1846-01-01= Persona con aseguramiento (régimen subsidiado o contributivo y que no son PPNA)que recibió servicios de salud por parte del ente territorial durante el periodo de reporte. | Z3: Registre el código de habilitación de IPS que proceso la muestra de patología.Verifique el código reportado como a una IPS con habilitación para procesamiento de muestra de patología. 55= Persona con aseguramiento (régimen subsidiado o contributivo y que no son PPNA)que recibió servicios de salud por parte del ente territorial durante el periodo de reporte. 96= Diagnóstico fuera del país 98= No se realizó confirmación por estudio histopatológico(en la variable 21 registro la opción 7) 99= Desconocido (opción válida solo en caso de diagnóstico antes de 2015-01-01 , se aclara que, si el diagnóstico fue previo a la fecha mencionada pero se tiene el dato solicitado entonces se debe reportar) | AA3: Registre la fecha en el formato AAAA-MM-DD. Si conoce sólo el año y el mes, registre el día 15. Registre 1800-01-01= Desconocido, el dato de esta variable no se encuentra descrito en los soportes clínicos.Registre 1846-01-01= Persona con aseguramiento (régimen subsidiado o contributivo y que no son PPNA)que recibió servicios de salud por parte del ente territorial durante el periodo de reporte. | AB3: Registre el número que corresponde al subtipo histológico de la biopsia diagnóstica del cáncer (como primera opción), si no hay información en ese reporte use la quirúrgica: 1= Adenocarcinoma, con o sin otra especificación 2= Carcinoma escamocelular (epidermoide), con o sin otra especificación 3= Carcinoma de células basales (basocelular) 4= Carcinoma, con o sin otra especificación diferentes a las anteriores 5= Oligodendroglioma, con o sin otra especificación 6= Astrocitoma, con o sin otra especificación 7= Ependimoma, con o sin otra especificación 8= Neuroblastoma, con o sin otra especificación 9= Meduloblastoma, con o sin otra especificación 10= Hepatoblastoma, con o sin otra especificación 11= Rabdomiosarcoma, con o sin otra especificación 12= Leiomiosarcoma, con o sin otra especificación 13= Osteosarcoma, con o sin otra especificación 14= Fibrosarcoma, con o sin otra especificación 15= Angiosarcoma, con o sin otra especificación 16= Condrosarcoma, con o sin otra especificación 17= Otros sarcomas, con o sin otra especificación 18= Pancreatoblastoma, con o sin otra especificación 19= Blastoma pleuropulmonar, con o sin otra especificación 20= Otros tipos histológicos no mencionados 23= Melanoma 24= Carcinoma papilar de tiroides 55= Persona con aseguramiento (régimen subsidiado o contributivo y que no son PPNA) que recibió servicios de salud por parte del ente territorial durante el periodo de reporte. 98= No se realizó estudio histopatológico (en la variable 21 registró la opción 7). 99= Desconocido, el dato de esta variable no se encuentra descrito en los soportes clínicos. | AC3: Apunte el número que corresponde al grado de diferenciación de la biopsia diagnóstica del cáncer (como primera opción), si no hay información en ese informe, use la quirúrgica. 1= Bien diferenciado (grado 1) 2= Moderadamente diferenciado (grado 2) 3= Mal diferenciado (grado 3) 4= Anaplásico o indiferenciado (grado 4) 55= Persona con aseguramiento (régimen subsidiado o contributivo y que no son PPNA) que recibió servicios de salud por parte del ente territorial durante el periodo de reporte. 94= Es un cáncer sólido cuyo reporte de patología no incluye la descripción de la diferenciación celular. (ejemplo: cáncer de tiroides, carcinoma basocelular, tumores in situ, melanoma, próstata, entre otros). 95= No es sólido (cáncer hematolinfático) 98= No se realizó estudio histopatológico (en la variable 21 registró la opción 7). 99= No hay información en la historia clínica | AD3: CÁNCER DE MAMA Y CÁNCER GÁSTRICO 0= estadio clínico (ec) 0 (tumor in situ) 2= ec IA o 1A 5= ec IB o 1b 11= ec IIA o 2a 14= ec IIB 17= ec IIIA o 3a 18= ec IIIB o 3b 19= ec IIIC o 3c 20= ec IV o 4 CANCER DE PRÓSTATA 0= estadio clínico (ec) o (tumor in situ) 1= ec I o 1 11= ec IIA o 2a 14= ec IIB 15= ec IIC o 2c 17= ec IIIA o 3a 18= ec IIIB o 3b 19= ec IIIC o 3c 21= ec IVA o 4a 22= ec IVB o 4b CANCER DE PULMÓN 8ª Edición TNM 0= estadio clínico (ec) o (tumor in situ) 3= ec IA1 4= ec IA2 36= ec IA3 11= ec IIA o 2a 14= ec IIB o 2b 17= ec IIIA o 3a 18= ec IIIB o 3b 19= ec IIIC o 3c 21= ec IVA o 4a 22= ec IVB o 4b MELANOMA 0= estadio clínico (ec) o (tumor in situ) 2= ec IA o 1A 5= ec IB o 1b 11= ec IIA o 2a 14= ec IIB o 2b 15= ec IIC o 2c 17= ec IIIA o 3a 18= ec IIIB o 3b 19= ec IIIC o 3c 29= ec IIID o 3d 20= ec IV o 4 CÁNCER DE COLON Y RECTO 0= estadio clínico (ec) o (tumor in situ) 1= ec I o 1 11= ec IIA o 2a 14= ec IIB o 2b 15= ec IIC o 2c 17= ec IIIA o 3a 18= ec IIIB o 3b 19= ec IIIC o 3c 21= ec IVA o 4a 22= ec IVB o 4b 23= ec IVC o 4c CÁNCER ANAL (Agrupador Colon y recto) 8ª Edición TNM 0= estadio clínico (ec) o (tumor in situ) 1= ec I o 1 11= ec IIA o 2a 14= ec IIB o 2b 17= ec IIIA o 3a 18= ec IIIB o 3b 19= ec IIIC o 3c 20= ec IV o 4 CÁNCER DE CÉRVIX (FIGO) 0= estadio clínico (ec) o (tumor in situ) 1= ec I o 1 2= ec IA o 1A 3= ec IA1 4= ec IA2 5= ec IB o 1b 6= ec IB1 7= ec IB2 30= ec IB3 10= ec II o 2 11= ec IIA o 2a 12= ec IIA1 13= ec IIA2 14= ec IIB o 2b 16= ec III o 3 17= ec IIIA o 3a 18= ec IIIB o 3b 19= ec IIIC o 3c 27= ec IIIC1 28= ec IIIC2 21= ec IVA o 4a 22= ec IVB o 4b OTRAS OPCIONES 8= ec IC o 1c 9= ec IS o 1s 24= ec 4S (para neuroblastoma) 25= ec V o 5 31= ec IC1 32= ec IC2 33= ec IC3 34= ec IIIA1 35= ec IIIA2 55= Persona con aseguramiento (régimen subsidiado o contributivo y que no son PPNA) que recibió servicios de salud por parte del ente territorial durante el periodo de reporte. 98= No Aplica (Es cáncer de piel basocelular, es cáncer hematológico o es cáncer en SNC, excepto neuroblastoma). 99= Desconocido, el dato de esta variable no se encuentra descrito en los soportes clínicos. | AE3: Registre la fecha en el formato AAAA-MM-DD. Si conoce sólo el año y el mes, registre el día 15. Registre 1800-01-01= Desconocido, el dato de esta variable no se encuentra descrito en los soportes clínicos. Registre 1845-01-01=No Aplica (no es sólido o SNC -execpto neuroblastoma). Registre 1846-01-01 = persona con aseguramiento (régimen subsidiado o contributivo y que no son PPNA)que recibió servicios de salud por parte del ente territorial durante el periodo de reporte. | AF3: Registre 1=sí se le realizó 2= no se le realizó 55=persona con aseguramiento (régimen subsidiado o contributivo y que no son PPNA)que recibió servicios de salud por parte del ente territorial durante el periodo de reporte. 97= No aplica porque es cancer de mama in situ 98=No Aplica (no es cáncer de mama) 99=Desconocido, el dato de esta variable no se encuentra descrito en los soportes clínicos. | AG3: Registre la fecha en el formato AAAA-MM-DD. Si conoce sólo el año y el mes, registre el día 15. Registre 1800-01-01= Desconocida (opción válida solo en caso de diagnóstico antes de 2015-01-01, se aclara que si el diagnóstico fue previo a la fecha mencionada pero se tiene el dato solicitado entonces se debe reportar) Registre 1840-01-01= No Aplica porque es cáncer de mama in situ. Registre 1845-01-01=No Aplica (no es cáncer de mama) o marco la variable 31 opcion 2. Registre 1846-01-01 = persona con aseguramiento (régimen subsidiado o contributivo y que no son PPNA)que recibió servicios de salud por parte del ente territorial durante el periodo de reporte. | AH3: 1= +++ (positivo) 2= ++ (equivoco o indeterminado) 3= + (negativo) 4= cero ó (negativo) 97= No Aplica porque es cáncer de mama in situ. 98= No Aplica (no es cáncer de mama) o marcó la variable 31 con la opción 2. 99= Desconocido, el dato de esta variable no se encuentra descrito en los soportes clínicos. 55=Persona con aseguramiento (régimen subsidiado o contributivo y que no son PPNA) que recibió servicios de salud por parte del ente territorial durante el periodo de reporte. | AI3: 1= A 2= B 3= C 4= D 55= Persona con aseguramiento (régimen subsidiado o contributivo y que no son PPNA) que recibió servicios de salud por parte del ente territorial durante el periodo de reporte. 98= No Aplica (no es cáncer colorrectal) 99= Es cáncer colorrectal pero no hay información en la historia clínica acerca de esta estadificación | AJ3: Registre la fecha en el formato AAAA-MM-DD. Si conoce sólo el año y el mes, registre el día 15. Registre 1845-01-01=No Aplica. (no es cáncer colo-rectal o respuesta 99 en la variable anterior) Registre 1846-01-01 = persona con aseguramiento (régimen subsidiado o contributivo y que no son PPNA)que recibió servicios de salud por parte del ente territorial durante el periodo de reporte. | AK3: Registre: 1= Estadio I 2= Estadio II 3= Estadio III 4= Estadio IV 5= Estadio IA 6= Estadio IB 7= Estadio IIA 8= Estadio IIB 9= Estadio IIIA 10= Estadio IIIB 11= Estadio IVA 12= Estadio IVB 13= Extranodal cualquier estadio 14= Primario SNC 15= Primario Mediastinal 16= Primario de otros órganos 55= Persona con aseguramiento (régimen subsidiado o contributivo y que no son PPNA) que recibió servicios de salud por parte del ente territorial durante el periodo de reporte. 98= No Aplica (porque es un tumor diferente a los enunciados) 99= Desconocido, el dato de esta variable no se encuentra descrito en los soportes clínicos. | AL3: 11= Gleason ≤ 6: ≤ 3+3 12= Gleason 7: 3+4 13= Gleason 7: 4+3 14= Gleason 8: 4+4 o 3+5 o 5+3 15= Gleason 9 o 10: 4+5 o 5+4 o 5+5 97= Es cáncer de próstata, pero no hay información acerca de esta estadificación porque el diagnóstico fue clínico. 98= No es cáncer de próstata. 99= Es cáncer de próstata, pero no hay información en la historia clínica acerca de esta clasificación a pesar de que fue diagnóstico histopatológico. 55= Persona con aseguramiento (régimen subsidiado o contributivo y que no son PPNA) que recibió servicios de salud por parte del ente territorial durante el periodo de reporte. | AM3: Clasificación de riesgo en linfoma no Hodgkin Registre: 1= Bajo Riesgo 2= Riesgo intermedio bajo 3= Intermedio 4= Riesgo intermedio alto 5= Riesgo alto Clasificación de riesgo en linfoma de Hodgkin Registre: 1= Bajo Riesgo 5= Riesgo alto Clasificación del riesgo en adultos (LLA, LMA y MM) Registre: 1= Riesgo estándar, bajo 3= Riesgo intermedio 5= Riesgo alto Clasificación del riesgo en Pediatría (LLA y LMA) Registre: 1= Riesgo estándar, favorable 3= Riesgo intermedio 5= Riesgo alto, desfavorable 55= Persona con aseguramiento (régimen subsidiado o contributivo y que no son PPNA) que recibió servicios de salud por parte del ente territorial durante el periodo de reporte. 98= No Aplica (no es leucemia ni linfoma) 99= Desconocido, el dato de esta variable no se encuentra descrito en los soportes clínicos. | AN3: Registre la fecha en el formato AAAA-MM-DD. Si conoce sólo el año y el mes, registre el día 15. Registre 1800-01-01=Desconocido, el dato de esta variable no se encuentra descrito en los soportes clínicos. Registre 1845-01-01=No Aplica no es leucemia, linfoma o sólido pediátrico; respuesta 99 en variable anterior) Registre 1846-01-01 = persona con aseguramiento (régimen subsidiado o contributivo y que no son PPNA)que recibió servicios de salud por parte del ente territorial durante el periodo de reporte. | AO3: 1= Curación 2= Paliación (intención paliativa) exclusivamente. 55= Persona con aseguramiento (régimen subsidiado o contributivo y que no son PPNA) que recibió servicios de salud por parte del ente territorial durante el periodo de reporte. 99= Desconocido, el dato de esta variable no se encuentra descrito en los soportes clínicos. | AP3: Registre: 1=observación previa a tratamiento únicamente (manejo expectante todo el periodo) 2=ofrecer tratamiento curativo o paliativo dirigido al cáncer (quimioterapia, hormonoterapia, radioterapia, cirugía, terapia biológica) inicial o por recaída únicamente 3= observación o seguimiento oncológico luego de tratamiento inicial únicamente (incluye tratamientos médicos para enfermedad general (no oncológica) y métodos diagnósticos de seguimiento) 4=1 y 2 únicamente 5=2 y 3 únicamente 6= 1, 2 y 3 55=Persona con aseguramiento (régimen subsidiado o contributivo y que no son PPNA)que recibió servicios de salud por parte del ente territorial durante el periodo de reporte 99= No hay intervención en el periodo (abandono de terapia, alta oncológica ó alta voluntaria) | AQ3: Registre: 1=Sí 2=No 55=Persona con aseguramiento (régimen subsidiado o contributivo y que no son PPNA)que recibió servicios de salud por parte del ente territorial durante el periodo de reporte 99=Desconocido, el dato de esta variable no se encuentra descrito en los soportes clínicos. | AR3: Fecha en que se diagnosticó el otro cáncer primario que afecta al usuario en el formato AAAA-MM-DD. Si conoce sólo el año y el mes, registre el día 15. Registre 1800-01-01= Desconocido, el dato de esta variable no se encuentra descrito en los soportes clínicos. Registre 1845-01-01= No Aplica. (no ha tenido otro cáncer primario) Registre 1846-01-01 = persona con aseguramiento (régimen subsidiado o contributivo y que no son PPNA)que recibió servicios de salud por parte del ente territorial durante el periodo de reporte. | AS3: Registre la enfermedad maligna antecedente o concurrente. Tenga en cuenta que antes de definir, por ejemplo, un linfoma, el usuario pudo tener un diagnóstico de cáncer a estudio o tumor de células pequeñas, redondas y azules, debe notificarse el linfoma. Registre el código de la enfermedad maligna ANTECEDENTE diagnosticada al usuario según código CIE -10. Registre 55 = persona con aseguramiento (régimen subsidiado o contributivo y que no son PPNA)que recibió servicios de salud por parte del ente territorial durante el periodo de reporte. Registre 99= No Aplica (no hay antecedente de otro cáncer primario). | AT3: Registre: 1= Sí recibió terapia sistémica 55= Persona con aseguramiento (régimen subsidiado o contributivo y que no son PPNA) que recibió servicios de salud por parte del ente territorial durante el periodo de reporte. 98= No Aplica (Nunca fue propuesta la terapia sistémica dentro del plan de terapéutico, verifique que en las variables 46 a 73 se registra No Aplica) | AU3: Escriba el número de fases de quimioterapia propuestas para este periodo. 0= Es cáncer hematolinfático con los siguientes códigos de clasificación diagnóstica CIE 10 (C835, C910, C920, C924 y C925) y en la variable 45 respondió la opción 2 o 98 55= Persona con aseguramiento (régimen subsidiado o contributivo y que no son PPNA) que recibió servicios de salud por parte del ente territorial durante el periodo de reporte. 98= No Aplica (es sólido o es cáncer diferente a los enunciados en las fases) | AV3: 1= Sí recibió 2= No recibió (en la variable 46 selecciono la opción 0) 55= Persona con aseguramiento (régimen subsidiado o contributivo y que no son PPNA) que recibió servicios de salud por parte del ente territorial durante el periodo de reporte. 97= No Aplica (no es leucemia linfoide o mieloide aguda ni linfoma linfoblástico) 99=Desconocido (es leucemia linfoide aguda ó linfoma linfoblástico, recibió quimioterapia, pero no hay información del nombre de la fase) | AW3: 1= Sí recibió 2= No recibió (en la variable 46 selecciono la opción 0) 55= Persona con aseguramiento (régimen subsidiado o contributivo y que no son PPNA) que recibió servicios de salud por parte del ente territorial durante el periodo de reporte. 97= No Aplica (no es leucemia linfoide o mieloide aguda ni linfoma linfoblástico) 99=Desconocido (es leucemia linfoide aguda ó linfoma linfoblástico, recibió quimioterapia, pero no hay información del nombre de la fase) | AX3: 1= Sí recibió 2= No recibió (en la variable 46 selecciono la opción 0) 55= Persona con aseguramiento (régimen subsidiado o contributivo y que no son PPNA) que recibió servicios de salud por parte del ente territorial durante el periodo de reporte. 97= No Aplica (no es leucemia linfoide o mieloide aguda ni linfoma linfoblástico) 99=Desconocido (es leucemia linfoide aguda ó linfoma linfoblástico, recibió quimioterapia, pero no hay información del nombre de la fase) | AY3: 1= Sí recibió 2= No recibió (en la variable 46 selecciono la opción 0) 55= Persona con aseguramiento (régimen subsidiado o contributivo y que no son PPNA) que recibió servicios de salud por parte del ente territorial durante el periodo de reporte. 97= No Aplica (no es leucemia linfoide o mieloide aguda ni linfoma linfoblástico) 99=Desconocido (es leucemia linfoide aguda ó linfoma linfoblástico, recibió quimioterapia, pero no hay información del nombre de la fase) | AZ3: 1= Sí recibió 2= No recibió (en la variable 46 selecciono la opción 0) 55= Persona con aseguramiento (régimen subsidiado o contributivo y que no son PPNA) que recibió servicios de salud por parte del ente territorial durante el periodo de reporte. 97= No Aplica (no es leucemia linfoide o mieloide aguda ni linfoma linfoblástico) 99=Desconocido (es leucemia linfoide aguda ó linfoma linfoblástico, recibió quimioterapia, pero no hay información del nombre de la fase) | BA3: 1= Sí recibió 2= No recibió (en la variable 46 selecciono la opción 0) 55= Persona con aseguramiento (régimen subsidiado o contributivo y que no son PPNA) que recibió servicios de salud por parte del ente territorial durante el periodo de reporte. 97= No Aplica (no es leucemia linfoide o mieloide aguda ni linfoma linfoblástico) 99=Desconocido (es leucemia linfoide aguda ó linfoma linfoblástico, recibió quimioterapia, pero no hay información del nombre de la fase) | BB3: 1= Sí recibió 2= No recibió (en la variable 46 selecciono la opción 0) 55= Persona con aseguramiento (régimen subsidiado o contributivo y que no son PPNA) que recibió servicios de salud por parte del ente territorial durante el periodo de reporte. 97= No Aplica (no es leucemia linfoide o mieloide aguda ni linfoma linfoblástico) 99=Desconocido (es leucemia linfoide aguda ó linfoma linfoblástico, recibió quimioterapia, pero no hay información del nombre de la fase) | BC3: 1= Sí recibió 2= No recibió (en la variable 46 selecciono la opción 0) 55= Persona con aseguramiento (régimen subsidiado o contributivo y que no son PPNA) que recibió servicios de salud por parte del ente territorial durante el periodo de reporte. 97= No Aplica (no es leucemia linfoide o mieloide aguda ni linfoma linfoblástico) 99=Desconocido (es leucemia linfoide aguda ó linfoma linfoblástico, recibió quimioterapia, pero no hay información del nombre de la fase) | BD3: Escriba el número de ciclos iniciados en el periodo de reporte actual (pueden ser ciclos en diferentes esquemas de manejo) 55= Persona con aseguramiento (régimen subsidiado o contributivo y que no son PPNA) que recibió servicios de salud por parte del ente territorial durante el periodo de reporte. 98= No Aplica o no la recibió, aunque fue formulada (en la variable 45 seleccionó 2 o 98) Para las hormonoterapias el dato en esta variable es 1 (un ciclo) en tratamientos orales sin periodos de descanso; para las terapias hormonales inyectables se cuenta el número de aplicaciones del periodo. | BE3: 1= Neoadyuvancia (manejo inicial prequirúrgico) 2= Tratamiento inicial curativo sin cirugía sugerida (por ejemplo, sería una opción frecuente en caso de leucemias o linfomas, u otros cánceres a quienes no se les hizo cirugía) 3= Adyuvancia (manejo inicial postquirúrgico) 11= Manejo de recaída 12= Manejo de enfermedad metastásica 13= Manejo paliativo (sin manejo de recaída ni enfermedad metastásica) 55= Persona con aseguramiento (régimen subsidiado o contributivo y que no son PPNA) que recibió servicios de salud por parte del ente territorial durante el periodo de reporte. 98= No Aplica (en la variable 45 seleccionó la opción 98) Aclaraciones servicios de salud por parte del ente territorial durante el periodo de reporte. 98= No Aplica (en la variable 45 seleccionó la opción 98)2 | BF3: Fecha en que se inició este esquema de quimioterapia en el formato AAAA-MM-DD. Si conoce sólo el año y el mes, registre el día 15. Registre 1845-01-01= No Aplica (en la variable 45 seleccionó la opción 2 ó 98). Registre 1846-01-01= Persona con aseguramiento (régimen subsidiado o contributivo y que no son PPNA) que recibió servicios de salud por parte del ente territorial durante el periodo de reporte. | BG3: Registre el número de Instituciones Prestadoras de Servicios de Salud que suministran el primer esquema de quimioterapia del periodo de reporte. 55= Persona con aseguramiento (régimen subsidiado o contributivo y que no son PPNA) que recibió servicios de salud por parte del ente territorial durante el periodo de reporte. 98= No aplica (en la variable 45 seleccionó la opción 2 y 98) | BH3: Código de Habilitación de IPS (disponible en la página web REPS) Para todos los tratamientos orales, se debe consignar el código de habilitación de la IPS que le prescribió el tratamiento no el código del operador logístico que realiza la entrega. 55= Persona con aseguramiento (régimen subsidiado o contributivo y que no son PPNA) que recibió servicios de salud por parte del ente territorial durante el periodo de reporte. 98= No Aplica (en la variable 45 seleccionó la opción 2 ó 98) | BI3: Código de Habilitación de IPS (disponible en la página web REPS) Para todos los tratamientos orales, se debe consignar el código de habilitación de la IPS que le prescribió el tratamiento no el código del operador logístico que realiza la entrega. 98= No Aplica 55= Persona con aseguramiento (régimen subsidiado o contributivo y que no son PPNA) que recibióservicios de salud por parte del ente territorial durante el periodo de reporte. | BJ3: Escriba el número de medicamentos antineoplásicos propuestos en el primer esquema de este periodo. Recuerde descontar el número de medicamento adyuvantes o de premedicación de la terapia que no son antineoplásicos. 98= No Aplica (en la variable 45 seleccionó la opción 98) 99= Persona con aseguramiento (régimen subsidiado o contributivo y que no son PPNA) que recibió servicios de salud por parte del ente territorial durante el periodo de reporte. | BK3: REGISTRE EL CODIGO ATC 98= No Aplica (en la variable 45 seleccionó la opción 98) 55= Persona con aseguramiento (régimen subsidiado o contributivo y que no son PPNA) que recibió | BL3: REGISTRE EL CODIGO ATC 97. SI, recibio quimioterapia ya registrada en las variables anteriores ( en la variable 45 selecciono 1 ) 98= No Aplica (en la variable 45 seleccionó la opción 98) 55= Persona con aseguramiento (régimen subsidiado o contributivo y que no son PPNA) que recibió | BM3: REGISTRE EL CODIGO ATC 97. SI, recibio quimioterapia ya registrada en las variables anteriores ( en la variable 45 selecciono 1 ) 98= No Aplica (en la variable 45 seleccionó la opción 98) 55= Persona con aseguramiento (régimen subsidiado o contributivo y que no son PPNA) que recibió | BN3: REGISTRE EL CODIGO ATC 97. SI, recibio quimioterapia ya registrada en las variables anteriores ( en la variable 45 selecciono 1 ) 98= No Aplica (en la variable 45 seleccionó la opción 98) 55= Persona con aseguramiento (régimen subsidiado o contributivo y que no son PPNA) que recibió | BO3: REGISTRE EL CODIGO ATC 97. SI, recibio quimioterapia ya registrada en las variables anteriores ( en la variable 45 selecciono 1 ) 98= No Aplica (en la variable 45 seleccionó la opción 98) 55= Persona con aseguramiento (régimen subsidiado o contributivo y que no son PPNA) que recibió | BP3: REGISTRE EL CODIGO ATC 97. SI, recibio quimioterapia ya registrada en las variables anteriores ( en la variable 45 selecciono 1 ) 98= No Aplica (en la variable 45 seleccionó la opción 98) 55= Persona con aseguramiento (régimen subsidiado o contributivo y que no son PPNA) que recibió | BQ3: REGISTRE EL CODIGO ATC 97. SI, recibio quimioterapia ya registrada en las variables anteriores ( en la variable 45 selecciono 1 ) 98= No Aplica (en la variable 45 seleccionó la opción 98) 55= Persona con aseguramiento (régimen subsidiado o contributivo y que no son PPNA) que recibió | BR3: REGISTRE EL CODIGO ATC 97. SI, recibio quimioterapia ya registrada en las variables anteriores ( en la variable 45 selecciono 1 ) 98= No Aplica (en la variable 45 seleccionó la opción 98) 55= Persona con aseguramiento (régimen subsidiado o contributivo y que no son PPNA) que recibió | BS3: REGISTRE EL CODIGO ATC 97. SI, recibio quimioterapia ya registrada en las variables anteriores ( en la variable 45 selecciono 1 ) 98= No Aplica (en la variable 45 seleccionó la opción 98) 55= Persona con aseguramiento (régimen subsidiado o contributivo y que no son PPNA) que recibió | BT3: Registre el código ATC del medicamento del listado usado en este caso (disponible en la página web CAC) 97= No Aplica (No recibió medicamentos diferente a los enunciados en las variables 53.1 a la 53.9 y en la variable 45 seleccionó la opción 1 ó 2) 98= No Aplica (no tuvo este esquema y en la variable 45 seleccionó la opción 98) 55= Persona con aseguramiento (régimen subsidiado o contributivo y que no son PPNA) que recibió servicios de salud por parte del ente territorial durante el periodo de reporte. | BU3: Registre el código ATC del medicamento del listado usado en este caso (disponible en la página web CAC) 97= No Aplica (No recibió medicamentos diferente a los enunciados en las variables 53.1 a la 53.9 y en la variable 45 seleccionó la opción 1 ó 2) 98= No Aplica (no tuvo este esquema y en la variable 45 seleccionó la opción 98) 55= Persona con aseguramiento (régimen subsidiado o contributivo y que no son PPNA) que recibió servicios de salud por parte del ente territorial durante el periodo de reporte. | BV3: Registre el código ATC del medicamento del listado usado en este caso (disponible en la página web CAC) 97= No Aplica (No recibió medicamentos diferente a los enunciados en las variables 53.1 a la 53.9 y en la variable 45 seleccionó la opción 1 ó 2) 98= No Aplica (no tuvo este esquema y en la variable 45 seleccionó la opción 98) 55= Persona con aseguramiento (régimen subsidiado o contributivo y que no son PPNA) que recibió servicios de salud por parte del ente territorial durante el periodo de reporte. | BW3: Registre: 1= Sí recibió 2= No recibió 98= No Aplica (no tuvo ningún esquema de quimioterapia) | BX3: Fecha en que terminó la administración del primer o único esquema de quimioterapia en el formato AAAA-MM-DD. Si conoce sólo el año y el mes, registre el día 15. Registre 1845-01-01= No Aplica (en la variable 45 seleccionó la opción 2 ó 98). Registre 1800-01-01= para casos de hormonoterapia o de esquema que aún no finalizan. Registre 1846-01-01=Persona con aseguramiento (régimen subsidiado o contributivo y que no son PPNA) que recibió servicios de salud por parte del ente territorial durante el periodo de reporte. | BY3: 1= Finalizado, esquema completo según medicamentos programados 2= Finalizado, esquema incompleto pero finalizado por algún motivo 3= No finalizado, esquema incompleto, pero aún bajo tratamiento (ejemplo: hormonoterapia o esquema no finalizado) 98= No Aplica (no tuvo ningún esquema de terapia sistémica y en la variable 45 seleccionó la opción 2 ó 98) 55= Persona con aseguramiento (régimen subsidiado o contributivo y que no son PPNA) que recibió servicios de salud por parte del ente territorial durante el periodo de reporte | BZ3: 1= Toxicidad de uno o más medicamentos 2= Otros motivos médicos 3= Muerte 4= Cambio de EAPB 5= Decisión del usuario: ABANDONO DE TERAPIA 6= No hay disponibilidad de medicamentos 7= Otros motivos administrativos 8= Otras causas no contempladas 98= No Aplica 55= Persona con aseguramiento (régimen subsidiado o contributivo y que no son PPNA) que recibió servicios de salud por parte del ente territorial durante el periodo de reporte. | CA3: (Si en el periodo recibió únicamente hormonoterapia no reportar nuevamente en esquema final), Registre: 1= Neoadyuvancia (manejo inicial prequirúrgico) 2= Tratamiento inicial curativo sin cirugía sugerida (por ejemplo, sería una opción frecuente en caso de leucemias o linfomas, u otros cánceres a quienes no se les hizo cirugía) 3= Adyuvancia (manejo inicial postquirúrgico) 11= Manejo de progresión o recaída 12= Manejo de enfermedad metastásica 13= Cambio por toxicidad 14= Manejo paliativo (sin manejo de recaída ni enfermedad metastásica) 97=Solo recibió un esquema de quimioterapia en este periodo y en la variable 45 seleccionó la opción 1. (verifique que las variables 62 a 73 registren No Aplica) 98= No Aplica (en la variable 45 seleccionó la opción 98) 55= Persona con aseguramiento (régimen subsidiado o contributivo y que no son PPNA) que recibió servicios de salud por parte del ente territorial durante el periodo de reporte. | CB3: Fecha en que se inició este esquema de quimioterapia en el formato AAAA-MM-DD. Si conoce sólo el año y el mes, registre el día 15. Registre 1845-01-01= No Aplica. Registre 1846-01-01= Persona con aseguramiento (régimen subsidiado o contributivo y que no son PPNA) que recibió servicios de salud por parte del ente territorial durante el periodo de reporte. | CC3: Registre el número de Instituciones Prestadoras de Servicios de Salud que suministran el último esquema de quimioterapia 98= No aplica 55= Persona con aseguramiento (régimen subsidiado o contributivo y que no son PPNA) que recibió servicios de salud por parte del ente territorial durante el periodo de reporte. | CD3: Código de Habilitación de IPS (disponible en la página web REPS). Para todos los tratamientos orales, se debe consignar el código de habilitación de la IPS que le prescribió el tratamiento, no el código del operador logístico que realiza la entrega. 98= No Aplica 55= Persona con aseguramiento (régimen subsidiado o contributivo y que no son PPNA) que recibió servicios de salud por parte del ente territorial durante el periodo de reporte. | CE3: Código de Habilitación de IPS (disponible en la página web REPS). Para todos los tratamientos orales, se debe consignar el código de habilitación de la IPS que le prescribió el tratamiento no el código del operador logístico que realiza la entrega. 98= No Aplica 55= Persona con aseguramiento (régimen subsidiado o contributivo y que no son PPNA) que recibió servicios de salud por parte del ente territorial durante el periodo de reporte. | CF3: Escriba el número de medicamentos antineoplásicos propuestos en este último esquema del periodo de reporte actual. Recuerde descontar el número de medicamento adyuvantes o de premedicación de la terapia que no son antineoplásicos. 98= No Aplica ( NO RECIBIO SEGUNDO ESQUEMA O marco 98 en la variable 45 ) 99= Persona con aseguramiento (régimen subsidiado o contributivo y que no son PPNA) que recibió servicios de salud por parte del ente territorial durante el periodo de reporte. | CG3: REGISTRE EL CODIGO ATC 98= No Aplica (en la variable 45 seleccionó la opción 98) 55= Persona con aseguramiento (régimen subsidiado o contributivo y que no son PPNA) que recibió | CH3: REGISTRE EL CODIGO ATC 97. SI, recibio quimioterapia ya registrada en las variables anteriores ( en la variable 45 selecciono 1 ) 98= No Aplica (en la variable 45 seleccionó la opción 98) 55= Persona con aseguramiento (régimen subsidiado o contributivo y que no son PPNA) que recibió | CI3: REGISTRE EL CODIGO ATC 97. SI, recibio quimioterapia ya registrada en las variables anteriores ( en la variable 45 selecciono 1 ) 98= No Aplica (en la variable 45 seleccionó la opción 98) 55= Persona con aseguramiento (régimen subsidiado o contributivo y que no son PPNA) que recibió | CJ3: REGISTRE EL CODIGO ATC 97. SI, recibio quimioterapia ya registrada en las variables anteriores ( en la variable 45 selecciono 1 ) 98= No Aplica (en la variable 45 seleccionó la opción 98) 55= Persona con aseguramiento (régimen subsidiado o contributivo y que no son PPNA) que recibió | CK3: REGISTRE EL CODIGO ATC 97. SI, recibio quimioterapia ya registrada en las variables anteriores ( en la variable 45 selecciono 1 ) 98= No Aplica (en la variable 45 seleccionó la opción 98) 55= Persona con aseguramiento (régimen subsidiado o contributivo y que no son PPNA) que recibió | CL3: REGISTRE EL CODIGO ATC 97. SI, recibio quimioterapia ya registrada en las variables anteriores ( en la variable 45 selecciono 1 ) 98= No Aplica (en la variable 45 seleccionó la opción 98) 55= Persona con aseguramiento (régimen subsidiado o contributivo y que no son PPNA) que recibió | CM3: REGISTRE EL CODIGO ATC 97. SI, recibio quimioterapia ya registrada en las variables anteriores ( en la variable 45 selecciono 1 ) 98= No Aplica (en la variable 45 seleccionó la opción 98) 55= Persona con aseguramiento (régimen subsidiado o contributivo y que no son PPNA) que recibió | CN3: REGISTRE EL CODIGO ATC 97. SI, recibio quimioterapia ya registrada en las variables anteriores ( en la variable 45 selecciono 1 ) 98= No Aplica (en la variable 45 seleccionó la opción 98) 55= Persona con aseguramiento (régimen subsidiado o contributivo y que no son PPNA) que recibió | CO3: REGISTRE EL CODIGO ATC 97. SI, recibio quimioterapia ya registrada en las variables anteriores ( en la variable 45 selecciono 1 ) 98= No Aplica (en la variable 45 seleccionó la opción 98) 55= Persona con aseguramiento (régimen subsidiado o contributivo y que no son PPNA) que recibió | CP3: Registre el código ATC del medicamento del listado usado en este caso (disponible en la página web CAC) 97= No Aplica (No recibió medicamentos diferente a los enunciados en las variables 53.1 a la 53.9 y en la variable 45 seleccionó la opción 1 ó 2) 98= No Aplica (no tuvo este esquema y en la variable 45 seleccionó la opción 98) 55= Persona con aseguramiento (régimen subsidiado o contributivo y que no son PPNA) que recibió servicios de salud por parte del ente territorial durante el periodo de reporte. | CQ3: Registre el código ATC del medicamento del listado usado en este caso (disponible en la página web CAC) 97= No Aplica (No recibió medicamentos diferente a los enunciados en las variables 53.1 a la 53.9 y en la variable 45 seleccionó la opción 1 ó 2) 98= No Aplica (no tuvo este esquema y en la variable 45 seleccionó la opción 98) 55= Persona con aseguramiento (régimen subsidiado o contributivo y que no son PPNA) que recibió servicios de salud por parte del ente territorial durante el periodo de reporte. | CR3: Registre el código ATC del medicamento del listado usado en este caso (disponible en la página web CAC) 97= No Aplica (No recibió medicamentos diferente a los enunciados en las variables 53.1 a la 53.9 y en la variable 45 seleccionó la opción 1 ó 2) 98= No Aplica (no tuvo este esquema y en la variable 45 seleccionó la opción 98) 55= Persona con aseguramiento (régimen subsidiado o contributivo y que no son PPNA) que recibió servicios de salud por parte del ente territorial durante el periodo de reporte. | CS3: Registre: 1= Si recibió 2= No recibió 98= No Aplica (no tuvo ningún esquema de quimioterapia) | CT3: Fecha en que terminó la administración del último esquema de quimioterapia en el formato AAAA-MM-DD. Si conoce sólo el año y el mes, registre el día 15. Registre 1845-01-01= No Aplica. Registre 1800-01-01= para casos de hormonoterapia o de esquema que aún no finalizan. Registre 1846-01-01= Persona con aseguramiento (régimen subsidiado o contributivo y que no son PPNA) que recibió servicios de salud por parte del ente territorial durante el periodo de reporte. | CU3: 1= Finalizado, esquema completo según medicamentos programados 2= Finalizado, esquema incompleto pero finalizado por algún motivo 3= No finalizado, esquema incompleto, pero aún bajo tratamiento (ejemplo: hormonoterapia o esquema no finalizado) 98= No Aplica (no tuvo ningún esquema de quimioterapia) 55= Persona con aseguramiento (régimen subsidiado o contributivo y que no son PPNA) que recibió servicios de salud por parte del ente territorial durante el periodo de reporte. | CV3: 1= Toxicidad de uno o más medicamentos 2= Otros motivos médicos 3= Muerte 4= Cambio de EPS 5= Decisión del usuario: ABANDONO DE TERAPIA 6= No hay disponibilidad de medicamentos 7= Otros motivos administrativos 8= Otras causas no contempladas 98= No Aplica 55= Persona con aseguramiento (régimen subsidiado o contributivo y que no son PPNA) que recibió servicios de salud por parte del ente territorial durante el periodo de reporte. | CW3: 1= Si fue sometido al menos a una cirugía durante este periodo 2= No recibió cirugía durante este periodo y no fue propuesta dentro del plan terapéutico. 55= Persona con aseguramiento (régimen subsidiado o contributivo y que no son PPNA) que recibió servicios de salud por parte del ente territorial durante el periodo de reporte. | CX3: Registre el número de cirugías a las que el usuario fue sometido durante el periodo de reporte actual, incluya aquellas por complicaciones relacionadas a la cirugía inicial. Valide que se esté reportando la cantidad de cirugías (tiempos quirúrgicos) y no la cantidad de procedimientos CUPS realizados dentro de una o varias cirugías. 98= No Aplica (si respondió 2 o 3 en la pregunta anterior) 55= Persona con aseguramiento (régimen subsidiado o contributivo y que no son PPNA) que recibió servicios de salud por parte del ente territorial durante el periodo de reporte. | CY3: Registre la fecha en el formato AAAA-MM-DD. Si conoce sólo el año y el mes, registre el día 15. Registre 1845-01-01= No Aplica. Registre 1846-01-01= Persona con aseguramiento (régimen subsidiado o contributivo y que no son PPNA) que recibió servicios de salud por parte del ente territorial durante el periodo de reporte. | CZ3: Registre el código de habilitación de la IPS (disponible en la página web REPS). 98= No Aplica 55= Persona con aseguramiento (régimen subsidiado o contributivo y que no son PPNA) que recibió servicios de salud por parte del ente territorial durante el periodo de reporte. | DA3: Registre el código de procedimiento CUPS (disponible en la página web CAC se recomienda utilizar el CUPS que tenga mayor relación con el manejo del cáncer o el que mayor complejidad represente dentro de la cirugía). 98= No Aplica 55= Persona con aseguramiento (régimen subsidiado o contributivo y que no son PPNA) que recibió servicios de salud por parte del ente territorial durante el periodo de reporte. | DB3: 1= Parte del manejo inicial para el cáncer ( Tratamiento inicial curativo) 5. Manejo de recaida 6. Manejo de enfermedad mestastica. 98= No Aplica 55= Persona con aseguramiento (régimen subsidiado o contributivo y que no son PPNA) que recibió servicios de salud por parte del ente territorial durante el periodo de reporte. | DC3: Registre la Fecha de realización de la última cirugía en el formato AAAA-MM-DD. Si conoce sólo el año y el mes, registre el día 15. Valide que no se estén reportando datos del evento quirúrgico denominado como primera cirugía de este periodo Registre 1845-01-01= No Aplica (sólo hubo una intervención en este periodo o no hubo cirugías en este periodo). Registre 1846-01-01= Persona con aseguramiento (régimen subsidiado o contributivo y que no son PPNA) que recibió servicios de salud por parte del ente territorial durante el periodo de reporte. | DD3: 1= Complementar tratamiento quirúrgico del cáncer no asociado a complicaciones de la primera cirugía 2= Complicaciones debida a la primera cirugía o siguientes 3= Complicaciones por otras condiciones médicas no relacionadas a la cirugía (por ejemplo, comorbilidad) 5= 1 y 3 6= 2 y 3 98= No Aplica (sólo hubo una intervención en este periodo o no hubo cirugías en este periodo) 55= Persona con aseguramiento (régimen subsidiado o contributivo y que no son PPNA) que recibió servicios de salud por parte del ente territorial durante el periodo de reporte. | DE3: Registre el código de Habilitación de IPS (disponible en la página web REPS). 98= No Aplica (sólo hubo una intervención en este periodo o no hubo cirugías en este periodo) 55= Persona con aseguramiento (régimen subsidiado o contributivo y que no son PPNA) que recibió servicios de salud por parte del ente territorial durante el periodo de reporte. | DF3: Registre el código de procedimiento CUPS (disponible en la página web CAC). Se recomienda utilizar el CUPS que tenga mayor relación con el manejo del cáncer o el que mayor complejidad represente dentro de la cirugía). 98= No Aplica (sólo hubo una intervención en este periodo o no hubo cirugías en este periodo) 55= Persona con aseguramiento (régimen subsidiado o contributivo y que no son PPNA) que recibió servicios de salud por parte del ente territorial durante el periodo de reporte. | DG3: 1= Parte del manejo inicial para el cáncer ( Tratamiento inicial curativo) 5. Manejo de recaida 6. Manejo de enfermedad mestastica. 98= No Aplica 55= Persona con aseguramiento (régimen subsidiado o contributivo y que no son PPNA) que recibió servicios de salud por parte del ente territorial durante el periodo de reporte. | DH3: 1= Vivo 2= Fallece 98= No Aplica (No cirugías en este periodo) 55= Persona con aseguramiento (régimen subsidiado o contributivo y que no son PPNA) que recibió servicios de salud por parte del ente territorial durante el periodo de reporte. | DI3: Registre: 1= Si recibió algún tipo de radioterapia 98= No Aplica - No fue propuesta dentro del plan terapéutico. (verifique que en las variables 87 a 105 se registra No Aplica) 55= Persona con aseguramiento (régimen subsidiado o contributivo y que no son PPNA) que recibió servicios de salud por parte del ente territorial durante el periodo de reporte. | DJ3: Registre el número de sesiones de radioterapia suministrados durante el periodo de reporte actual (valide que en los soportes exista la cantidad de sesiones ordenadas que serán capturadas en el momento de la auditoría en variable adicional). Registre el valor de INTERNAS Y EXTERNAS 0= si las sesiones suministradas son de otro tipo diferente a la externa o cuando no se recibieron, aunque fueron propuestas en el plan terapéutico. 98= No Aplica (No fue propuesta dentro del plan terapéutico) 55= Persona con aseguramiento (régimen subsidiado o contributivo y que no son PPNA) que recibió servicios de salud por parte del ente territorial durante el periodo de reporte. | DK3: Registre la fecha en que se inició cualquiera de los tipos de radioterapia en el formato AAAA-MM-DD. Si conoce sólo el año y el mes, registre el día 15. Registre 1845-01-01= No Aplica. Registre 1846-01-01= Persona con aseguramiento (régimen subsidiado o contributivo y que no son PPNA) que recibió servicios de salud por parte del ente territorial durante el periodo de reporte. | DL3: 1= Neoadyuvancia (manejo inicial prequirúrgico) 2= Tratamiento inicial curativo sin cirugía sugerida (por ejemplo, solo algunos cánceres que se curan con radioterapia exclusiva) 3= Adyuvancia (manejo inicial postquirúrgico) 11= Manejo de recaída 12= Manejo de enfermedad metastásica 13= Manejo paliativo (sin manejo de recaída ni enfermedad metastásica) 98= No Aplica 55= Persona con aseguramiento (régimen subsidiado o contributivo y que no son PPNA) que recibió servicios de salud por parte del ente territorial durante el periodo de reporte | DM3: Registre el codigo de procedimiento CUPS. 98= No aplica. 55= Persona con aseguramiento | DN3: Registre el número de IPS que intervinieron en la administración de la dosis de radioterapia. 98= No Aplica 55= Persona con aseguramiento (régimen subsidiado o contributivo y que no son PPNA) que recibió servicios de salud por parte del ente territorial durante el periodo de reporte. | DO3: Registre el código de Habilitación de IPS (disponible en la página web REPS). 98= No Aplica 55= Persona con aseguramiento (régimen subsidiado o contributivo y que no son PPNA) que recibió servicios de salud por parte del ente territorial durante el periodo de reporte. | DP3: Registre el código de Habilitación de IPS (disponible en la página web REPS). 98= No Aplica 55= Persona con aseguramiento (régimen subsidiado o contributivo y que no son PPNA) que recibió servicios de salud por parte del ente territorial durante el periodo de reporte. | DQ3: Registre la fecha de finalización de cualquiera de los tipos de radioterapia en el formato AAAA-MM-DD. Si conoce sólo el año y el mes, registre el día 15. Registre 1800-01-01= esquema de radioterapia que aún no finalizan. Registre 1845-01-01= No Aplica. Registre 1846-01-01= Persona con aseguramiento (régimen subsidiado o contributivo y que no son PPNA) que recibió servicios de salud por parte del ente territorial durante el periodo de reporte. | DR3: 1= Finalizado, dosis completa de radioterapia administrada PRESCRITA 2= Finalizado, dosis incompleta pero finalizada por algún motivo 3= No finalizado, esquema incompleto, pero aún bajo tratamiento 98= No Aplica 55= Persona con aseguramiento (régimen subsidiado o contributivo y que no son PPNA) que recibió servicios de salud por parte del ente territorial durante el periodo de reporte. | DS3: Registre: 1= Toxicidad 2= Otros motivos médicos 3= Muerte 4= Cambio de EPS 5= Decisión del usuario: ABANDONO DE TERAPIA 6= Otros motivos administrativos 7= Otras causas no contempladas 98= No Aplica 55= Persona con aseguramiento (régimen subsidiado o contributivo y que no son PPNA) que recibió servicios de salud por parte del ente territorial durante el periodo de reporte. | DT3: Registre la fecha en que se inició el último esquema, de cualquiera de los tipos de radioterapia en el formato AAAA-MM-DD. Si conoce sólo el año y el mes, registre el día 15. Registre 1845-01-01= No Aplica. Registre 1846-01-01= Persona con aseguramiento (régimen subsidiado o contributivo y que no son PPNA) que recibió servicios de salud por parte del ente territorial durante el periodo de reporte. | DU3: 1= Neoadyuvancia (manejo inicial prequirúrgico) 2= Tratamiento inicial curativo sin cirugía sugerida (por ejemplo, Solo algunos cánceres que se curan con radioterapia exclusiva) 3= Adyuvancia (manejo inicial postquirúrgico) 11= Manejo de recaída 12= Manejo de enfermedad metastásica 13= Manejo paliativo (sin manejo de recaída ni enfermedad metastásica) 98= No aplica 55= Persona con aseguramiento (régimen subsidiado o contributivo y que no son PPNA) que recibió servicios de salud por parte del ente territorial durante el periodo de reporte. | DV3: Registre el codigo de procedimiento CUPS. 98= No aplica. 55= Persona con aseguramiento | DW3: Registre el número de IPS que intervinieron en la administración de la dosis de radioterapia 98= No Aplica 55= Persona con aseguramiento (régimen subsidiado o contributivo y que no son PPNA) que recibió servicios de salud por parte del ente territorial durante el periodo de reporte. | DX3: Registre el código de Habilitación de IPS (disponible en la página web REPS). 98= No Aplica 55= Persona con aseguramiento (régimen subsidiado o contributivo y que no son PPNA) que recibió servicios de salud por parte del ente territorial durante el periodo de reporte. | DY3: Registre el código de Habilitación de IPS (disponible en la página web REPS). 98= No Aplica 55= Persona con aseguramiento (régimen subsidiado o contributivo y que no son PPNA) que recibió servicios de salud por parte del ente territorial durante el periodo de reporte. | DZ3: Registre la Fecha de finalización de cualquiera de los tipos de radioterapia en el formato AAAA-MM-DD. Si conoce sólo el año y el mes, registre el día 15. Registre 1800-01-01= para esquemas de radioterapia que aún no finalizan Registre 1845-01-01= No Aplica. Registre 1846-01-01= Persona con aseguramiento (régimen subsidiado o contributivo y que no son PPNA) que recibió servicios de salud por parte del ente territorial durante el periodo de reporte. | EA3: 1= Finalizado, dosis completa de radioterapia administrada PRESCRITA 2= Finalizado, dosis incompleta pero finalizada por algún motivo 3= No finalizado, esquema incompleto, pero aún bajo tratamiento 98= No Aplica 55= Persona con aseguramiento (régimen subsidiado o contributivo y que no son PPNA) que recibió servicios de salud por parte del ente territorial durante el periodo de reporte. | EB3: 1= Toxicidad 2= Otros motivos médicos 3= Muerte 4= Cambio de EPS 5= Decisión del usuario 6= Otros motivos administrativos 7= Otras causas no contempladas 98= No Aplica 55= Persona con aseguramiento (régimen subsidiado o contributivo y que no son PPNA) que recibió servicios de salud por parte del ente territorial durante el periodo de reporte. | EC3: 1= Sí recibió 98= No Aplica (No fue propuesto dentro del plan terapéutico verifique que en las variables 107 a 110 se registra No Aplica) 55= Persona con aseguramiento (régimen subsidiado o contributivo y que no son PPNA) que recibió servicios de salud por parte del ente territorial durante el periodo de reporte. | ED3: 1= Autólogo 2= Alogénico de donante idéntico relacionado 3= Alogénico de donante no idéntico relacionado 4= Alogénico de donante idéntico no relacionado 5= Alogénico de donante no idéntico no relacionado 6= Alogénico de cordón umbilical idéntico familiar 7= Alogénico de cordón umbilical idéntico no familiar 8= Alogénico de cordón no idéntico no familiar 9= Alogénico de dos unidades de cordón 98= No Aplica (respondió 2 o 98 en la pregunta anterior) 55= Persona con aseguramiento (régimen subsidiado o contributivo y que no son PPNA) que recibió servicios de salud por parte del ente territorial durante el periodo de reporte. | EE3: Este trasplante de células progenitoras hematopoyéticas fue: 95. Recaida 96. refractariedad. 97. Esquema de Consolidacion. 98= No Aplica 55= Persona con aseguramiento (régimen subsidiado o contributivo y que no son PPNA) que recibió servicios de salud por parte del ente territorial durante el periodo de reporte. | EF3: Fecha de realización del trasplante en el formato AAAA-MM-DD. Si conoce sólo el año y el mes, registre el día 15. Registre 1845-01-01= No Aplica. Registre 1846-01-01= Persona con aseguramiento (régimen subsidiado o contributivo y que no son PPNA) que recibió servicios de salud por parte del ente territorial durante el periodo de reporte. | EG3: Registre código de Habilitación de IPS (disponible en la página web REPS). 98= No Aplica 55= Persona con aseguramiento (régimen subsidiado o contributivo y que no son PPNA) que recibió servicios de salud por parte del ente territorial durante el periodo de reporte. | EH3: 1= Sí recibió cirugía 98= No Aplica (No RECIBIO este tipo de cirugía, verifique que en las variables 112 y 113 se registra No Aplica) 55= Persona con aseguramiento (régimen subsidiado o contributivo y que no son PPNA) que recibió servicios de salud por parte del ente territorial durante el periodo de reporte. | EI3: Fecha en que se realizó la cirugía en el formato AAAA-MMDD. Si conoce sólo el año y el mes, registre el día 15. Registre 1845-01-01= No Aplica. Registre 1846-01-01= Persona con aseguramiento (régimen subsidiado o contributivo y que no son PPNA) que recibió servicios de salud por parte del ente territorial durante el periodo de reporte. | EJ3: Registre código de Habilitación de IPS (disponible en la página web REPS). 98= No Aplica 55= Persona con aseguramiento (régimen subsidiado o contributivo y que no son PPNA) que recibió servicios de salud por parte del ente territorial durante el periodo de reporte. | EK3: Registre: 1= Sí Fue valorado 2= No recibió. 55= Persona con aseguramiento (régimen subsidiado o contributivo y que no son PPNA) que recibió servicios de salud por parte del ente territorial durante el periodo de reporte. | EL3: Registre: 1= Sí Fue valorado 2= No recibió. 55= Persona con aseguramiento (régimen subsidiado o contributivo y que no son PPNA) que recibió servicios de salud por parte del ente territorial durante el periodo de reporte. | EM3: Registre: 1= Sí Fue valorado 2= No recibió. 55= Persona con aseguramiento (régimen subsidiado o contributivo y que no son PPNA) que recibió servicios de salud por parte del ente territorial durante el periodo de reporte. | EN3: Registre: 1= Sí Fue valorado 2= No recibió. 55= Persona con aseguramiento (régimen subsidiado o contributivo y que no son PPNA) que recibió servicios de salud por parte del ente territorial durante el periodo de reporte. | EO3: Registre: 1= Sí Fue valorado 2= No recibió. 55= Persona con aseguramiento (régimen subsidiado o contributivo y que no son PPNA) que recibió servicios de salud por parte del ente territorial durante el periodo de reporte. | EP3: Registre: 1= Sí Fue valorado 2= No recibió. 55= Persona con aseguramiento (régimen subsidiado o contributivo y que no son PPNA) que recibió servicios de salud por parte del ente territorial durante el periodo de reporte. | EQ3: Registre: 1= Sí Fue valorado 2= No recibió. 55= Persona con aseguramiento (régimen subsidiado o contributivo y que no son PPNA) que recibió servicios de salud por parte del ente territorial durante el periodo de reporte. | ER3: Registre la fecha de primera interconsulta o procedimiento en el formato AAAA-MM-DD. Si conoce sólo el año y el mes, registre el día 15. Registre 1845-01-01= No Aplica. Registre 1846-01-01= Persona con aseguramiento (régimen subsidiado o contributivo y que no son PPNA) que recibió servicios de salud por parte del ente territorial durante el periodo de reporte. | ES3: Registre el código de Habilitación de IPS (disponible en la página web REPS). 98= No Aplica 55= Persona con aseguramiento (régimen subsidiado o contributivo y que no son PPNA) que recibió servicios de salud por parte del ente territorial durante el periodo de reporte. | ET3: Registre: 1= Sí 2= No, se ordenó, pero está pendiente 98= No aplica, no se ha ordenado valoración por psiquiatría 55= Persona con aseguramiento (régimen subsidiado o contributivo y que no son PPNA) que recibió servicios de salud por parte del ente territorial durante el periodo de reporte. | EU3: Fecha de primera interconsulta en el formato AAAA-MM-DD. Si conoce sólo el año y el mes, registre el día 15. Registre 1845-01-01= No Aplica. Registre 1846-01-01= Persona con aseguramiento (régimen subsidiado o contributivo y que no son PPNA) que recibió servicios de salud por parte del ente territorial durante el periodo de reporte. | EV3: Registre el código de Habilitación de IPS (disponible en la página web REPS). 98= No Aplica 55= Persona con aseguramiento (régimen subsidiado o contributivo y que no son PPNA) que recibió servicios de salud por parte del ente territorial durante el periodo de reporte. | EW3: Registre: 1= Sí 2= No, se ordenó, pero está pendiente 98= No aplica, no se ha ordenado valoración por nutrición 55= Persona con aseguramiento (régimen subsidiado o contributivo y que no son PPNA) que recibió servicios de salud por parte del ente territorial durante el periodo de reporte. | EX3: Registre la Fecha en que se inició esta atención en el formato AAAA-MM-DD. Si conoce sólo el año y el mes, registre el día 15. Registre 1845-01-01= No Aplica. Registre 1846-01-01= Persona con aseguramiento (régimen subsidiado o contributivo y que no son PPNA) que recibió servicios de salud por parte del ente territorial durante el periodo de reporte. | EY3: Registre el código de Habilitación de IPS (disponible en la página web REPS). 98= No Aplica 55= Persona con aseguramiento (régimen subsidiado o contributivo y que no son PPNA) que recibió servicios de salud por parte del ente territorial durante el periodo de reporte. | EZ3: 1=Si recibió soporte nutricional enteral 2= Si recibió soporte nutricional, parenteral 3= Si recibió soporte nutricional enteral y parenteral (opciones:1 y 2) 4= No recibió soporte nutricional 55= Persona con aseguramiento (régimen subsidiado o contributivo y que no son PPNA) que recibió servicios de salud por parte del ente territorial durante el periodo de reporte. Aclaraciones *Vía de nutrición enteral: técnica de soporte nutricional administrada mediante sonda, directamente al sistema gastrointestinal. *Vía de nutrición parenteral: técnica de soporte nutricional administrada por vía venosa. *No es válido el reporte de fórmulas nutricionales de administración oral | FA3: 1= Si, Terapia física 2= Si, terapia de lenguaje 3= Si, Terapia ocupacional 4= No, se ordenó, pero está pendiente 5= 1 y 2 6= 1 y 3 7= 2 y 3 8= 1, 2 y 3 98= No aplica, no se han ordenado terapias. 55= Persona con aseguramiento (régimen subsidiado o contributivo y que no son PPNA) que recibió servicios de salud por parte del ente territorial durante el periodo de reporte. | FB3: 1= Radioterapia 2= Terapia sistémica (incluye quimioterapia, anticuerpos monoclonales, terapia biológica, terapia hormonal) 3= Cirugía (reporte solo cuando el procedimiento se haya realizado a partir del 1 de noviembre de 2019) 4= 1 y 2 5= 1 y 3 6= 2 y 3 7= Manejo expectante pretratamiento 8= En seguimiento, luego de tratamiento durante el periodo 9= Antecedente de cáncer (no recibió ningún tratamiento dentro del periodo) 10=1, 2 y 3 11= Manejo de cuidado paliativo o terapia complementaria. 98= No Aplica (paciente se encuentra fallecido, abandonó el tratamiento, alta voluntaria o se encuentra desafiliado) 55= Persona con aseguramiento (régimen subsidiado o contributivo y que no son PPNA) que recibió servicios de salud por parte del ente territorial durante el periodo de reporte. | FC3: 1= Pseudoprogresión (aplica solo para inmunoterapia) 2= Progresión o recaída 3= Respuesta parcial 4= Respuesta completa 5= Enfermedad estable 6= Abandono del tratamiento o alta voluntaria 7= Paciente en seguimiento por antecedente de cáncer 8= Pendiente iniciar el tratamiento luego del diagnóstico (fue definido por especialista o aún esta pendiente por valoración oncológica inicial, en la cual se defina el tratamiento) 97= No aplicable en este periodo, aún bajo tratamiento inicial 98= No aplicable en este periodo, aún bajo tratamiento de recaída 99= No aplica, el paciente se encuentra fallecido, o se encuentra desafiliado 55= Persona con aseguramiento (régimen subsidiado o contributivo y que no son PPNA) que recibió servicios de salud por parte del ente territorial durante el periodo de reporte. | FD3: Registre: 1= Vivo 2= Fallecido 99= Desconocido 55= Persona con aseguramiento (régimen subsidiado o contributivo y que no son PPNA) que recibió servicios de salud por parte del ente territorial durante el periodo de reporte. | FE3: 0= no presenta novedad con respecto al reporte anterior (vivo y afiliado a la entidad). 1= usuario ingresó a la EAPB en el periodo de reporte y ya tenía el diagnóstico de cáncer 2= usuario con un nuevo diagnóstico de cáncer entre el 2 de enero de 2022 y el 1 de enero de 2023 3= usuario con diagnóstico antiguo de cáncer que no había sido incluido en el reporte anterior 4= usuario que falleció 5= usuario que se desafilió 6= usuario para eliminar de la base de datos por corrección luego de auditoría interna o de CAC 7= usuario que firmó alta voluntaria del tratamiento 8= usuario con cambio de tipo o número de ID 9= usuario abandonó el tratamiento y es imposible de ubicar 10= usuario no incluido en reporte anterior y está fallecido en el momento del reporte actual 11= trasladado de IPS 12= usuario que es notificado con dos o más cánceres en este periodo 13=usuario no incluido en reporte anterior y está desafiliado en el momento del reporte actual 14= Persona con aseguramiento (régimen subsidiado o contributivo y que no son PPNA) que recibió servicios de salud por parte del ente territorial durante el periodo de reporte. 15 = Comunidad migrante de la República de Venezuela 16= Usuario con cambio de CIE-10: aplica para casos con cánceres secundarios o no especificados en los que se define el primario o se especifica el tipo de cáncer. 17= Usuario identificado por cruce con fuentes externas, con diagnóstico de cáncer, no confirmado o no gestionado por la EAPB 18= Usuario identificado por cruce con fuentes externas, con diagnóstico descartado por la EAPB 19= Paciente trasladado que fue glosado en periodo anterior, que no fue gestionado por la entidad en el periodo actual | FF3: 1= Usuario que está en manejo inicial curativo 3= Usuario que finalizó tratamiento inicial y está en seguimiento 8= Abandono de tratamiento 9= Usuario firmó alta voluntaria 10= Usuario en manejo expectante antes de tratamiento 11= Usuario que está en manejo paliativo (incluye manejo de metástasis o de recaída) 12= Usuario fallecido o desafiliado 55= Persona con aseguramiento (régimen subsidiado o contributivo y que no son PPNA) que recibió servicios de salud por parte del ente territorial durante el periodo de reporte. Aclaraciones *La opción 11, recopila los pacientes con todos los tipos de cáncer, que reciben terapia con intención paliativa a la fecha de corte. | FG3: Registre la fecha en la que el usuario se desafilió de la EAPB en el formato AAAA-MM-DD 1845-01-01= No Aplica, el usuario no se desafilió 1846-01-01= Persona con aseguramiento (régimen subsidiado o contributivo y que no son PPNA) que recibió servicios de salud por parte del ente territorial durante el periodo de reporte | FH3: Registre la fecha en la que el usuario falleció en el formato AAAA-MM-DD | FI3: 1= Muerte asociada al cáncer 2= Muerte por patología clínica no relacionada al cáncer 3= Muerte por causa externa 4= Muerte por causa no conocida 98= No Aplica, usuario vivo o se desconoce su estado vital 55= Persona con aseguramiento (régimen subsidiado o contributivo y que no son PPNA) que recibió servicios de salud por parte del ente territorial durante el periodo de reporte. | FJ3: Registre el código único serial de identificación BDUA- BDEX- PVS asignado al paciente por el Ministerio de Salud y Protección Social. | FK3: Diligencie esta variable con la fecha 2023-01-01 | FL3: VAR | FM3: % | FN3: AGRUPADOR | FO3: Fecha de modificación | FP3: QUIMIO | FQ3: RT INICIO | FR3: RT FIN | FS3: CIRUGIA | FT3: HCEO | FU3: Tratamiento
A4: Abandono confirmado | B4: MARGARITA | C4: ISABEL | D4: MARTINEZ | E4: SANTANA | F4: CC | G4: 25844702 | H4: 20216 | I4: F | R4: C509 | S4: 34515 | T4: 1800-01-01 | U4: 1800-01-01 | V4: 10 | W4: 98 | X4: 1800-01-01 | Y4: 1800-01-01 | Z4: 99 | AA4: 1800-01-01 | AB4: 99 | AC4: 99 | AD4: 99 | AE4: 1800-01-01 | AF4: 99 | AG4: 1800-01-01 | AH4: 99 | AI4: 98 | AJ4: 1845-01-01 | AK4: 98 | AL4: 98 | AM4: 98 | AN4: 1845-01-01 | AO4: 1 | AP4: 99 | AR4: =+IF(AQ4=2,"1845-01-01","") | AS4: =+IF(AQ4=2,"99","") | AT4: =IF(OR($AP4=1,$AP4=3,$AP4=99),98,"") -> 98 | AU4: =IF(AND(OR($R4="C835",$R4="C910",$R4="C920",$R4="C924",$R4="C925"),OR($AT4=98)),0,IF($AT4=55,55,IF(OR($R4="C835",$R4="C910",$R4="C920",$R4="C924",$R4="C925"),SUMIF($AV4:$BC4,1),98))) -> 98 | AV4: =IF($AT4=98,97,IF(AND(OR($R4="C835",$R4="C910",$R4="C920",$R4="C924",$R4="C925"),$AT4=98),97,"")) -> 97 | AW4: =IF($AT4=98,97,IF(AND(OR($R4="C835",$R4="C910",$R4="C920",$R4="C924",$R4="C925"),$AT4=98),97,"")) -> 97 | AX4: =IF($AT4=98,97,IF(AND(OR($R4="C835",$R4="C910",$R4="C920",$R4="C924",$R4="C925"),$AT4=98),97,"")) -> 97 | AY4: =IF($AT4=98,97,IF(AND(OR($R4="C835",$R4="C910",$R4="C920",$R4="C924",$R4="C925"),$AT4=98),97,"")) -> 97 | AZ4: =IF($AT4=98,97,IF(AND(OR($R4="C835",$R4="C910",$R4="C920",$R4="C924",$R4="C925"),$AT4=98),97,"")) -> 97 | BA4: =IF($AT4=98,97,IF(AND(OR($R4="C835",$R4="C910",$R4="C920",$R4="C924",$R4="C925"),$AT4=98),97,"")) -> 97 | BB4: =IF($AT4=98,97,IF(AND(OR($R4="C835",$R4="C910",$R4="C920",$R4="C924",$R4="C925"),$AT4=98),97,"")) -> 97 | BC4: =IF($AT4=98,97,IF(AND(OR($R4="C835",$R4="C910",$R4="C920",$R4="C924",$R4="C925"),$AT4=98),97,"")) -> 97 | BD4: =IF($AT4=98,98,"") -> 98 | BE4: =IF($AT4=98,98,"") -> 98 | BF4: =IF($AT4=98,"1845-01-01","") -> 1845-01-01 | BG4: =IF($AT4=98,98,"") -> 98 | BH4: =IF($AT4=98,98,IF(AT4=1,230010094901,"")) -> 98 | BI4: =IF(OR($AT4=98,$BG4=1),98,"") -> 98 | BJ4: =IF(OR($AT4=98),98,IF($AT4=55,55,"")) -> 98 | BK4: =IF(OR($AT4=98),98,IF($AT4=55,55,"")) -> 98 | BL4: =IF(OR($AT4=98),98,IF($AT4=55,55,"")) -> 98 | BM4: =IF(OR($AT4=98),98,IF($AT4=55,55,"")) -> 98 | BN4: =IF(OR($AT4=98),98,IF($AT4=55,55,"")) -> 98 | BO4: =IF(OR($AT4=98),98,IF($AT4=55,55,"")) -> 98 | BP4: =IF(OR($AT4=98),98,IF($AT4=55,55,"")) -> 98 | BQ4: =IF(OR($AT4=98),98,IF($AT4=55,55,"")) -> 98 | ... BW4: =IF(OR($AT4=98),98,IF($AT4=55,55,"")) -> 98 | BX4: =IF($AT4=98,"1845-01-01","") -> 1845-01-01 | BY4: =IF(OR($AT4=98),98,IF($AT4=55,55,"")) -> 98 | BZ4: =IF(OR($AT4=98,BY4<>2),98,IF($AT4=55,55,"")) -> 98 | CA4: =IF(OR($AT4=98,$AP4=1,$AP4=3,$AP4=99),98,IF($AT4=55,55," ")) -> 98 | CB4: =IF(OR($AT4=98,$CA4=97,$AP4=1,$AP4=3,$AP4=99),"1845-01-01",IF($AT4=55,"1846-01-01"," ")) -> 1845-01-01 | CC4: =IF(OR($AT4=2,$AT4=98,$CA4=97,$AP4=1,$AP4=3,$AP4=99),98,IF($AT4=55,55," ")) -> 98 | CD4: =IF(OR($AT4=2,$AT4=98,$CA4=97,$AP4=1,$AP4=3,$AP4=99),98,IF($AT4=55,55," ")) -> 98 | CE4: =IF(OR($AT4=2,$AT4=98,$CA4=97,$AP4=1,$AP4=3,$AP4=99,$CC4=1),98,IF($AT4=55,55," ")) -> 98 | CF4: =IF(OR($AT4=2,$AT4=98,$CA4=97,$AP4=1,$AP4=3,$AP4=99),98,IF($AT4=55,55,"")) -> 98 | CG4: =IF(OR($AT4=98,$CA4=97,$AP4=1,$AP4=3,$AP4=99),98,IF($AT4=55,55,"")) -> 98 | CH4: =IF(OR($AT4=2,$AT4=98,$CA4=97,$AP4=1,$AP4=3,$AP4=99),98,IF($AT4=55,55,97)) -> 98 | CI4: =IF(OR($AT4=2,$AT4=98,$CA4=97,$AP4=1,$AP4=3,$AP4=99),98,IF($AT4=55,55,97)) -> 98 | CJ4: =IF(OR($AT4=2,$AT4=98,$CA4=97,$AP4=1,$AP4=3,$AP4=99),98,IF($AT4=55,55,97)) -> 98 | CK4: =IF(OR($AT4=2,$AT4=98,$CA4=97,$AP4=1,$AP4=3,$AP4=99),98,IF($AT4=55,55,97)) -> 98 | CL4: =IF(OR($AT4=2,$AT4=98,$CA4=97,$AP4=1,$AP4=3,$AP4=99),98,IF($AT4=55,55,97)) -> 98 | CM4: =IF(OR($AT4=2,$AT4=98,$CA4=97,$AP4=1,$AP4=3,$AP4=99),98,IF($AT4=55,55,97)) -> 98 | CN4: =IF(OR($AT4=2,$AT4=98,$CA4=97,$AP4=1,$AP4=3,$AP4=99),98,IF($AT4=55,55,97)) -> 98 | CO4: =IF(OR($AT4=2,$AT4=98,$CA4=97,$AP4=1,$AP4=3,$AP4=99),98,IF($AT4=55,55,97)) -> 98 | ... CR4: =IF(OR($AT4=2,$AT4=98,$CA4=97,$AP4=1,$AP4=3,$AP4=99),98,IF($AT4=55,55,97)) -> 98 | CS4: =IF($CA4<=10,"",IF(OR($AT4=98,$AT4=2,$CA4=97,$CA4=98,$AP4=1,$AP4=3,$AP4=99),98,IF($AT4=55,55," "))) -> 98 | CT4: =IF($CA4<=10,"",IF(OR($AT4=98,$AT4=2,$CA4=97,$CA4=98,$AP4=1,$AP4=3,$AP4=99),"1845-01-01",IF($AT4=55,"1846-01-01"," "))) -> 1845-01-01 | CU4: =IF($CA4<=10,"",IF(OR($AT4=98,$AT4=2,$CA4=97,$CA4=98,$AP4=1,$AP4=3,$AP4=99),98,IF($AT4=55,55," "))) -> 98 | CV4: =IF($CA4<=10,"",IF(OR($AT4=98,$AT4=2,$CA4=97,$CA4=98,$AP4=1,$AP4=3,$AP4=99),98,IF($AT4=55,55," "))) -> 98 | CW4: =IF(OR($AP4=1,$AP4=3,$AP4=99),2,IF($AP4=55,55," ")) -> 2 | CX4: =IF(OR($AP4=1,$AP4=3,$AP4=99,$CW4=2,$CW4=3),98,IF($AP4=55,55," ")) -> 98 | CY4: =IF(OR($AP4=1,$AP4=3,$AP4=99,$CW4=2,$CW4=3),"1845-01-01",IF($AP4=55,"1846-01-01"," ")) -> 1845-01-01 | CZ4: =IF(OR($AP4=1,$AP4=3,$AP4=99,$CW4=2,$CW4=3),98,IF($AP4=55,55,"230010094901")) -> 98 | DA4: =IF(OR($AP4=1,$AP4=3,$AP4=99,$CW4=2,$CW4=3),98,IF($AP4=55,55," ")) -> 98 | DB4: =IF(OR($AP4=1,$AP4=3,$AP4=99,$CW4=2,$CW4=3),98,IF($AP4=55,55," ")) -> 98 | DC4: =IF(OR($AP4=1,$AP4=3,$AP4=99,$CX4<=1,$CW4=2,$CW4=3),"1845-01-01",IF($AP4=55,"1846-01-01"," ")) -> 1845-01-01 | DD4: =IF(OR($AP4=1,$AP4=3,$AP4=99,$CX4<=1,$CW4=2,$CW4=3),98,IF($AP4=55,55," ")) -> 98 | DE4: =IF(OR($AP4=1,$AP4=3,$AP4=99,$CX4<=1,$CW4=2,$CW4=3),98,IF($AP4=55,55," ")) -> 98 | DF4: =IF(OR($AP4=1,$AP4=3,$AP4=99,$CX4<=1,$CW4=2,$CW4=3),98,IF($AP4=55,55," ")) -> 98 | DG4: =IF(OR($AP4=1,$AP4=3,$AP4=99,$CX4<=1,$CW4=2,$CW4=3),98,IF($AP4=55,55," ")) -> 98 | DH4: =IF(OR($AP4=1,$AP4=3,$AP4=99,$CW4=2,$CW4=3),98,IF($AP4=55,55," ")) -> 98 | DI4: =IF(OR($AP4=1,$AP4=3,$AP4=99),98,IF($AP4=55,55," ")) -> 98 | DJ4: =IF(OR($AP4=1,$AP4=3,$AP4=98,$DI4=98,$DI4=2,$AP4=99),98,IF($AP4=55,55," ")) -> 98 | DK4: =IF(OR($AP4=1,$AP4=3,$AP4=98,$DI4=98,$DI4=2,$AP4=99),"1845-01-01",IF($AP4=55,"1846-01-01"," ")) -> 1845-01-01 | DL4: =IF(OR($AP4=1,$AP4=3,$AP4=98,$DI4=98,$DI4=2,$AP4=99),98,IF($AP4=55,55," ")) -> 98 | DM4: =IF(OR($AP4=1,$AP4=3,$AP4=98,$DI4=98,$DI4=2,$AP4=99),98,IF($AP4=55,55," ")) -> 98 | DN4: =IF(OR($AP4=1,$AP4=3,$AP4=98,$DI4=98,$DI4=2,$AP4=99),98,IF($AP4=55,55," ")) -> 98 | DO4: =IF(OR($AP4=1,$AP4=3,$AP4=98,$DI4=98,$DI4=2,$AP4=99),98,IF($AP4=55,55,"230010094901")) -> 98 | DP4: =IF(OR($AP4=1,$AP4=3,$AP4=98,$DI4=98,$DI4=2,$AP4=99,DN4<=1),98,IF($AP4=55,55," ")) -> 98 | DQ4: =IF(OR($AP4=1,$AP4=3,$AP4=98,$DI4=98,$DI4=2,$AP4=99),"1845-01-01",IF($AP4=55,"1846-01-01"," ")) -> 1845-01-01 | DR4: =IF(OR($AP4=1,$AP4=3,$AP4=98,$DI4=98,$DI4=2,$AP4=99),98,IF($AP4=55,55," ")) -> 98 | DS4: =IF(OR($AP4=1,$AP4=3,$AP4=98,$AP4=99,$DI4=98,$DI4=2,$DR4<>2),98,IF($AP4=55,55," ")) -> 98 | DT4: =IF(OR($AP4=1,$AP4=3,$AP4=98,$AP4=99,$DI4=98,$DI4=2,),"1845-01-01",IF($AP4=55,"1846-01-01"," ")) -> 1845-01-01 | DU4: =IF(OR($AP4=1,$AP4=3,$AP4=98,$AP4=99,$DI4=98,$DI4=2,$DT4="1845-01-01"),98,IF($AP4=55,55," ")) -> 98 | DV4: =IF(OR($AP4=1,$AP4=3,$AP4=98,$AP4=99,$DI4=98,$DI4=2,$DT4="1845-01-01"),98,IF($AP4=55,55," ")) -> 98 | DW4: =IF(OR($AP4=1,$AP4=3,$AP4=98,$AP4=99,$DI4=98,$DI4=2,$DT4="1845-01-01"),98,IF($AP4=55,55," ")) -> 98 | DX4: =IF(OR($AP4=1,$AP4=3,$AP4=98,$AP4=99,$DI4=98,$DI4=2,$DT4="1845-01-01"),98,IF($AP4=55,55," ")) -> 98 | DY4: =IF(OR($AP4=1,$AP4=3,$AP4=98,$AP4=99,$DI4=98,$DI4=2,$DT4="1845-01-01"),98,IF($AP4=55,55," ")) -> 98 | DZ4: =IF(OR($AP4=1,$AP4=3,$AP4=99,$AP4=98,$DI4=98,$DI4=2,$DT4="1845-01-01"),"1845-01-01",IF($AP4=55,"1846-01-01"," ")) -> 1845-01-01 | EA4: =IF(OR($AP4=1,$AP4=3,$AP4=98,$AP4=99,$DI4=98,$DI4=2,$DT4="1845-01-01"),98,IF($AP4=55,55," ")) -> 98 | EB4: =IF(OR($AP4=1,$AP4=3,$AP4=98,$AP4=99,$DI4=98,$DI4=2,$DT4="1845-01-01",$EA4<>2),98,IF($AP4=55,55," ")) -> 98 | EC4: =IF(OR($AP4=1,$AP4=3,$AP4=99),98,IF($AP4=55,55," ")) -> 98 | ED4: =IF(OR($AP4=1,$AP4=3,$EC4=98),98,IF($AP4=55,55," ")) -> 98 | EE4: =IF(OR($AP4=1,$AP4=3,$EC4=98),98,IF($AP4=55,55," ")) -> 98 | EF4: =IF(OR($AP4=1,$AP4=3,$EC4=98),"1845-01-01",IF($AP4=55,"1846-01-01"," ")) -> 1845-01-01 | EG4: =IF(OR($AP4=1,$AP4=3,$EC4=98),98,IF($AP4=55,55,"230010094901")) -> 98 | EH4: =IF(OR($AP4=1,$AP4=3,$AP4=99),98,IF($AP4=55,55," ")) -> 98 | EI4: =IF(OR($AP4=1,$AP4=3,,$AP4=99,$EH4=98),"1845-01-01",IF($AP4=55,"1846-01-01"," ")) -> 1845-01-01 | EJ4: =IF(OR($AP4=1,$AP4=3,,$AP4=99,$EH4=98),98,IF($AP4=55,55," ")) -> 98 | EK4: =IF(OR($AP4=1,$AP4=3,$AP4=99),2,IF($AP4=55,55," ")) -> 2 | EL4: =IF(OR($AP4=1,$AP4=3,$AP4=99,$EK4=2),2,IF($AP4=55,55," ")) -> 2 | EM4: =IF(OR($AP4=1,$AP4=3,$AP4=99,$EK4=2),2,IF($AP4=55,55," ")) -> 2 | EN4: =IF(OR($AP4=1,$AP4=3,$AP4=99,$EK4=2),2,IF($AP4=55,55," ")) -> 2 | EO4: =IF(OR($AP4=1,$AP4=3,$AP4=99,$EK4=2),2,IF($AP4=55,55," ")) -> 2 | EP4: =IF(OR($AP4=1,$AP4=3,$AP4=99,$EK4=2),2,IF($AP4=55,55," ")) -> 2 | EQ4: =IF(OR($AP4=1,$AP4=3,$AP4=99,$EK4=2),2,IF($AP4=55,55," ")) -> 2 | ER4: =IF(OR($AP4=1,$AP4=3,$AP4=99,$EK4=2),"1845-01-01",IF($AP4=55,"1846-01-01"," ")) -> 1845-01-01 | ES4: =IF(OR($AP4=1,$AP4=3,$AP4=99,$EK4=2),98,IF($AP4=55,55," ")) -> 98 | ET4: =IF(OR($AP4=1,$AP4=3,$AP4=99,$EK4=2),98,IF($AP4=55,55," ")) -> 98 | EU4: =IF($AP4=55,"1846-01-01",IF(OR($ET4=2,$ET4=98),"1845-01-01"," ")) -> 1845-01-01 | EV4: =IF($AP4=55,55,IF(OR($ET4=2,$ET4=98),98," ")) -> 98 | EW4: =IF(OR($AP4=1,$AP4=3,$AP4=99),98,IF($AP4=55,55," ")) -> 98 | EX4: =IF($AP4=55,55,IF(OR($EW4=98,$EW4=2),"1845-01-01"," ")) -> 1845-01-01 | EY4: =IF($AP4=55,55,IF(OR($EW4=98,$EW4=2),98,IF($EW4<>" ","230010094901",""))) -> 98 | EZ4: =IF($AP4=55,55,IF(OR($EW4=98,$EW4=2),4," ")) -> 4 | FA4: =IF($AP4=55,55,IF(OR($AP4=1,$AP4=3),98," ")) | FB4: =IF($AP4=55,55,IF(OR($AP4=99,$FD4=2),98,IF($AP4=1,7,IF($AP4=3,9,IF(OR($AP4=5,$AP4=6),8," "))))) -> 98 | FC4: =IF($AP4=1,5,IF($AP4=3,7,IF($AP4=99,6,IF($FB4=98,99,IF($AP4=55,55,""))))) -> 6 | FD4: =IF($AP4=55,55,IF($AP4=99,99,"")) -> 99 | FE4: =IF($FD4=2,4,IF($FD4=55,14,IF(YEAR($S4)=2023,2,IF(AP4=3,0,"")))) | FF4: =IF($AP4=1,10,IF($AP4=99,8, IF($FD4=2,12,IF($AP4=3,7,"")))) -> 8 | FH4: =IF(OR($FD4=1,$FD4=99),"1845-01-01"," ") -> 1845-01-01 | FI4: =IF(OR($FD4=1,$FD4=99),98," ") -> 98 | FL4: =COUNTIF(R4:FI4,"<>""")-COUNTBLANK(R4:FI4) -> 143 | FM4: =+FL4/147 -> 0.97278912 | FN4: =+VLOOKUP(R4,'CIE-10'!$A$3:$C$558,3,FALSE) -> 1= CAC Mama | FU4: =SUM(FP4:FS4) -> 0
A5: Abandono confirmado | B5: JOSE | C5: ASTERIO | D5: CARO | E5: IZQUIERDO | F5: CC | G5: 6861474 | H5: 18403 | I5: M | R5: C189 | S5: 34880 | T5: 1800-01-01 | U5: 1800-01-01 | V5: 10 | W5: 98 | X5: 1800-01-01 | Y5: 1800-01-01 | Z5: 99 | AA5: 1800-01-01 | AB5: 99 | AC5: 99 | AD5: 99 | AE5: 1800-01-01 | AF5: 98 | AG5: 1845-01-01 | AH5: 98 | AI5: 99 | AJ5: 1845-01-01 | AK5: 98 | AL5: 98 | AM5: 98 | AN5: 1845-01-01 | AO5: 1 | AP5: 99 | AR5: =+IF(AQ5=2,"1845-01-01","") | AS5: =+IF(AQ5=2,"99","") | AT5: =IF(OR($AP5=1,$AP5=3,$AP5=99),98,"") -> 98 | AU5: =IF(AND(OR($R5="C835",$R5="C910",$R5="C920",$R5="C924",$R5="C925"),OR($AT5=98)),0,IF($AT5=55,55,IF(OR($R5="C835",$R5="C910",$R5="C920",$R5="C924",$R5="C925"),SUMIF($AV5:$BC5,1),98))) -> 98 | AV5: =IF($AT5=98,97,IF(AND(OR($R5="C835",$R5="C910",$R5="C920",$R5="C924",$R5="C925"),$AT5=98),97,"")) -> 97 | AW5: =IF($AT5=98,97,IF(AND(OR($R5="C835",$R5="C910",$R5="C920",$R5="C924",$R5="C925"),$AT5=98),97,"")) -> 97 | AX5: =IF($AT5=98,97,IF(AND(OR($R5="C835",$R5="C910",$R5="C920",$R5="C924",$R5="C925"),$AT5=98),97,"")) -> 97 | AY5: =IF($AT5=98,97,IF(AND(OR($R5="C835",$R5="C910",$R5="C920",$R5="C924",$R5="C925"),$AT5=98),97,"")) -> 97 | AZ5: =IF($AT5=98,97,IF(AND(OR($R5="C835",$R5="C910",$R5="C920",$R5="C924",$R5="C925"),$AT5=98),97,"")) -> 97 | BA5: =IF($AT5=98,97,IF(AND(OR($R5="C835",$R5="C910",$R5="C920",$R5="C924",$R5="C925"),$AT5=98),97,"")) -> 97 | BB5: =IF($AT5=98,97,IF(AND(OR($R5="C835",$R5="C910",$R5="C920",$R5="C924",$R5="C925"),$AT5=98),97,"")) -> 97 | BC5: =IF($AT5=98,97,IF(AND(OR($R5="C835",$R5="C910",$R5="C920",$R5="C924",$R5="C925"),$AT5=98),97,"")) -> 97 | BD5: =IF($AT5=98,98,"") -> 98 | BE5: =IF($AT5=98,98,"") -> 98 | BF5: =IF($AT5=98,"1845-01-01","") -> 1845-01-01 | BG5: =IF($AT5=98,98,"") -> 98 | BH5: =IF($AT5=98,98,IF(AT5=1,230010094901,"")) -> 98 | BI5: =IF(OR($AT5=98,$BG5=1),98,"") -> 98 | BJ5: =IF(OR($AT5=98),98,IF($AT5=55,55,"")) -> 98 | BK5: =IF(OR($AT5=98),98,IF($AT5=55,55,"")) -> 98 | BL5: =IF(OR($AT5=98),98,IF($AT5=55,55,"")) -> 98 | BM5: =IF(OR($AT5=98),98,IF($AT5=55,55,"")) -> 98 | BN5: =IF(OR($AT5=98),98,IF($AT5=55,55,"")) -> 98 | BO5: =IF(OR($AT5=98),98,IF($AT5=55,55,"")) -> 98 | BP5: =IF(OR($AT5=98),98,IF($AT5=55,55,"")) -> 98 | BQ5: =IF(OR($AT5=98),98,IF($AT5=55,55,"")) -> 98 | ... BW5: =IF(OR($AT5=98),98,IF($AT5=55,55,"")) -> 98 | BX5: =IF($AT5=98,"1845-01-01","") -> 1845-01-01 | BY5: =IF(OR($AT5=98),98,IF($AT5=55,55,"")) -> 98 | BZ5: =IF(OR($AT5=98,BY5<>2),98,IF($AT5=55,55,"")) -> 98 | CA5: =IF(OR($AT5=98,$AP5=1,$AP5=3,$AP5=99),98,IF($AT5=55,55," ")) -> 98 | CB5: =IF(OR($AT5=98,$CA5=97,$AP5=1,$AP5=3,$AP5=99),"1845-01-01",IF($AT5=55,"1846-01-01"," ")) -> 1845-01-01 | CC5: =IF(OR($AT5=2,$AT5=98,$CA5=97,$AP5=1,$AP5=3,$AP5=99),98,IF($AT5=55,55," ")) -> 98 | CD5: =IF(OR($AT5=2,$AT5=98,$CA5=97,$AP5=1,$AP5=3,$AP5=99),98,IF($AT5=55,55," ")) -> 98 | CE5: =IF(OR($AT5=2,$AT5=98,$CA5=97,$AP5=1,$AP5=3,$AP5=99,$CC5=1),98,IF($AT5=55,55," ")) -> 98 | CF5: =IF(OR($AT5=2,$AT5=98,$CA5=97,$AP5=1,$AP5=3,$AP5=99),98,IF($AT5=55,55,"")) -> 98 | CG5: =IF(OR($AT5=98,$CA5=97,$AP5=1,$AP5=3,$AP5=99),98,IF($AT5=55,55,"")) -> 98 | CH5: =IF(OR($AT5=2,$AT5=98,$CA5=97,$AP5=1,$AP5=3,$AP5=99),98,IF($AT5=55,55,97)) -> 98 | CI5: =IF(OR($AT5=2,$AT5=98,$CA5=97,$AP5=1,$AP5=3,$AP5=99),98,IF($AT5=55,55,97)) -> 98 | CJ5: =IF(OR($AT5=2,$AT5=98,$CA5=97,$AP5=1,$AP5=3,$AP5=99),98,IF($AT5=55,55,97)) -> 98 | CK5: =IF(OR($AT5=2,$AT5=98,$CA5=97,$AP5=1,$AP5=3,$AP5=99),98,IF($AT5=55,55,97)) -> 98 | CL5: =IF(OR($AT5=2,$AT5=98,$CA5=97,$AP5=1,$AP5=3,$AP5=99),98,IF($AT5=55,55,97)) -> 98 | CM5: =IF(OR($AT5=2,$AT5=98,$CA5=97,$AP5=1,$AP5=3,$AP5=99),98,IF($AT5=55,55,97)) -> 98 | CN5: =IF(OR($AT5=2,$AT5=98,$CA5=97,$AP5=1,$AP5=3,$AP5=99),98,IF($AT5=55,55,97)) -> 98 | CO5: =IF(OR($AT5=2,$AT5=98,$CA5=97,$AP5=1,$AP5=3,$AP5=99),98,IF($AT5=55,55,97)) -> 98 | ... CR5: =IF(OR($AT5=2,$AT5=98,$CA5=97,$AP5=1,$AP5=3,$AP5=99),98,IF($AT5=55,55,97)) -> 98 | CS5: =IF($CA5<=10,"",IF(OR($AT5=98,$AT5=2,$CA5=97,$CA5=98,$AP5=1,$AP5=3,$AP5=99),98,IF($AT5=55,55," "))) -> 98 | CT5: =IF($CA5<=10,"",IF(OR($AT5=98,$AT5=2,$CA5=97,$CA5=98,$AP5=1,$AP5=3,$AP5=99),"1845-01-01",IF($AT5=55,"1846-01-01"," "))) -> 1845-01-01 | CU5: =IF($CA5<=10,"",IF(OR($AT5=98,$AT5=2,$CA5=97,$CA5=98,$AP5=1,$AP5=3,$AP5=99),98,IF($AT5=55,55," "))) -> 98 | CV5: =IF($CA5<=10,"",IF(OR($AT5=98,$AT5=2,$CA5=97,$CA5=98,$AP5=1,$AP5=3,$AP5=99),98,IF($AT5=55,55," "))) -> 98 | CW5: =IF(OR($AP5=1,$AP5=3,$AP5=99),2,IF($AP5=55,55," ")) -> 2 | CX5: =IF(OR($AP5=1,$AP5=3,$AP5=99,$CW5=2,$CW5=3),98,IF($AP5=55,55," ")) -> 98 | CY5: =IF(OR($AP5=1,$AP5=3,$AP5=99,$CW5=2,$CW5=3),"1845-01-01",IF($AP5=55,"1846-01-01"," ")) -> 1845-01-01 | CZ5: =IF(OR($AP5=1,$AP5=3,$AP5=99,$CW5=2,$CW5=3),98,IF($AP5=55,55,"230010094901")) -> 98 | DA5: =IF(OR($AP5=1,$AP5=3,$AP5=99,$CW5=2,$CW5=3),98,IF($AP5=55,55," ")) -> 98 | DB5: =IF(OR($AP5=1,$AP5=3,$AP5=99,$CW5=2,$CW5=3),98,IF($AP5=55,55," ")) -> 98 | DC5: =IF(OR($AP5=1,$AP5=3,$AP5=99,$CX5<=1,$CW5=2,$CW5=3),"1845-01-01",IF($AP5=55,"1846-01-01"," ")) -> 1845-01-01 | DD5: =IF(OR($AP5=1,$AP5=3,$AP5=99,$CX5<=1,$CW5=2,$CW5=3),98,IF($AP5=55,55," ")) -> 98 | DE5: =IF(OR($AP5=1,$AP5=3,$AP5=99,$CX5<=1,$CW5=2,$CW5=3),98,IF($AP5=55,55," ")) -> 98 | DF5: =IF(OR($AP5=1,$AP5=3,$AP5=99,$CX5<=1,$CW5=2,$CW5=3),98,IF($AP5=55,55," ")) -> 98 | DG5: =IF(OR($AP5=1,$AP5=3,$AP5=99,$CX5<=1,$CW5=2,$CW5=3),98,IF($AP5=55,55," ")) -> 98 | DH5: =IF(OR($AP5=1,$AP5=3,$AP5=99,$CW5=2,$CW5=3),98,IF($AP5=55,55," ")) -> 98 | DI5: =IF(OR($AP5=1,$AP5=3,$AP5=99),98,IF($AP5=55,55," ")) -> 98 | DJ5: =IF(OR($AP5=1,$AP5=3,$AP5=98,$DI5=98,$DI5=2,$AP5=99),98,IF($AP5=55,55," ")) -> 98 | DK5: =IF(OR($AP5=1,$AP5=3,$AP5=98,$DI5=98,$DI5=2,$AP5=99),"1845-01-01",IF($AP5=55,"1846-01-01"," ")) -> 1845-01-01 | DL5: =IF(OR($AP5=1,$AP5=3,$AP5=98,$DI5=98,$DI5=2,$AP5=99),98,IF($AP5=55,55," ")) -> 98 | DM5: =IF(OR($AP5=1,$AP5=3,$AP5=98,$DI5=98,$DI5=2,$AP5=99),98,IF($AP5=55,55," ")) -> 98 | DN5: =IF(OR($AP5=1,$AP5=3,$AP5=98,$DI5=98,$DI5=2,$AP5=99),98,IF($AP5=55,55," ")) -> 98 | DO5: =IF(OR($AP5=1,$AP5=3,$AP5=98,$DI5=98,$DI5=2,$AP5=99),98,IF($AP5=55,55,"230010094901")) -> 98 | DP5: =IF(OR($AP5=1,$AP5=3,$AP5=98,$DI5=98,$DI5=2,$AP5=99,DN5<=1),98,IF($AP5=55,55," ")) -> 98 | DQ5: =IF(OR($AP5=1,$AP5=3,$AP5=98,$DI5=98,$DI5=2,$AP5=99),"1845-01-01",IF($AP5=55,"1846-01-01"," ")) -> 1845-01-01 | DR5: =IF(OR($AP5=1,$AP5=3,$AP5=98,$DI5=98,$DI5=2,$AP5=99),98,IF($AP5=55,55," ")) -> 98 | DS5: =IF(OR($AP5=1,$AP5=3,$AP5=98,$AP5=99,$DI5=98,$DI5=2,$DR5<>2),98,IF($AP5=55,55," ")) -> 98 | DT5: =IF(OR($AP5=1,$AP5=3,$AP5=98,$AP5=99,$DI5=98,$DI5=2,),"1845-01-01",IF($AP5=55,"1846-01-01"," ")) -> 1845-01-01 | DU5: =IF(OR($AP5=1,$AP5=3,$AP5=98,$AP5=99,$DI5=98,$DI5=2,$DT5="1845-01-01"),98,IF($AP5=55,55," ")) -> 98 | DV5: =IF(OR($AP5=1,$AP5=3,$AP5=98,$AP5=99,$DI5=98,$DI5=2,$DT5="1845-01-01"),98,IF($AP5=55,55," ")) -> 98 | DW5: =IF(OR($AP5=1,$AP5=3,$AP5=98,$AP5=99,$DI5=98,$DI5=2,$DT5="1845-01-01"),98,IF($AP5=55,55," ")) -> 98 | DX5: =IF(OR($AP5=1,$AP5=3,$AP5=98,$AP5=99,$DI5=98,$DI5=2,$DT5="1845-01-01"),98,IF($AP5=55,55," ")) -> 98 | DY5: =IF(OR($AP5=1,$AP5=3,$AP5=98,$AP5=99,$DI5=98,$DI5=2,$DT5="1845-01-01"),98,IF($AP5=55,55," ")) -> 98 | DZ5: =IF(OR($AP5=1,$AP5=3,$AP5=99,$AP5=98,$DI5=98,$DI5=2,$DT5="1845-01-01"),"1845-01-01",IF($AP5=55,"1846-01-01"," ")) -> 1845-01-01 | EA5: =IF(OR($AP5=1,$AP5=3,$AP5=98,$AP5=99,$DI5=98,$DI5=2,$DT5="1845-01-01"),98,IF($AP5=55,55," ")) -> 98 | EB5: =IF(OR($AP5=1,$AP5=3,$AP5=98,$AP5=99,$DI5=98,$DI5=2,$DT5="1845-01-01",$EA5<>2),98,IF($AP5=55,55," ")) -> 98 | EC5: =IF(OR($AP5=1,$AP5=3,$AP5=99),98,IF($AP5=55,55," ")) -> 98 | ED5: =IF(OR($AP5=1,$AP5=3,$EC5=98),98,IF($AP5=55,55," ")) -> 98 | EE5: =IF(OR($AP5=1,$AP5=3,$EC5=98),98,IF($AP5=55,55," ")) -> 98 | EF5: =IF(OR($AP5=1,$AP5=3,$EC5=98),"1845-01-01",IF($AP5=55,"1846-01-01"," ")) -> 1845-01-01 | EG5: =IF(OR($AP5=1,$AP5=3,$EC5=98),98,IF($AP5=55,55,"230010094901")) -> 98 | EH5: =IF(OR($AP5=1,$AP5=3,$AP5=99),98,IF($AP5=55,55," ")) -> 98 | EI5: =IF(OR($AP5=1,$AP5=3,,$AP5=99,$EH5=98),"1845-01-01",IF($AP5=55,"1846-01-01"," ")) -> 1845-01-01 | EJ5: =IF(OR($AP5=1,$AP5=3,,$AP5=99,$EH5=98),98,IF($AP5=55,55," ")) -> 98 | EK5: =IF(OR($AP5=1,$AP5=3,$AP5=99),2,IF($AP5=55,55," ")) -> 2 | EL5: =IF(OR($AP5=1,$AP5=3,$AP5=99,$EK5=2),2,IF($AP5=55,55," ")) -> 2 | EM5: =IF(OR($AP5=1,$AP5=3,$AP5=99,$EK5=2),2,IF($AP5=55,55," ")) -> 2 | EN5: =IF(OR($AP5=1,$AP5=3,$AP5=99,$EK5=2),2,IF($AP5=55,55," ")) -> 2 | EO5: =IF(OR($AP5=1,$AP5=3,$AP5=99,$EK5=2),2,IF($AP5=55,55," ")) -> 2 | EP5: =IF(OR($AP5=1,$AP5=3,$AP5=99,$EK5=2),2,IF($AP5=55,55," ")) -> 2 | EQ5: =IF(OR($AP5=1,$AP5=3,$AP5=99,$EK5=2),2,IF($AP5=55,55," ")) -> 2 | ER5: =IF(OR($AP5=1,$AP5=3,$AP5=99,$EK5=2),"1845-01-01",IF($AP5=55,"1846-01-01"," ")) -> 1845-01-01 | ES5: =IF(OR($AP5=1,$AP5=3,$AP5=99,$EK5=2),98,IF($AP5=55,55," ")) -> 98 | ET5: =IF(OR($AP5=1,$AP5=3,$AP5=99,$EK5=2),98,IF($AP5=55,55," ")) -> 98 | EU5: =IF($AP5=55,"1846-01-01",IF(OR($ET5=2,$ET5=98),"1845-01-01"," ")) -> 1845-01-01 | EV5: =IF($AP5=55,55,IF(OR($ET5=2,$ET5=98),98," ")) -> 98 | EW5: =IF(OR($AP5=1,$AP5=3,$AP5=99),98,IF($AP5=55,55," ")) -> 98 | EX5: =IF($AP5=55,55,IF(OR($EW5=98,$EW5=2),"1845-01-01"," ")) -> 1845-01-01 | EY5: =IF($AP5=55,55,IF(OR($EW5=98,$EW5=2),98,IF($EW5<>" ","230010094901",""))) -> 98 | EZ5: =IF($AP5=55,55,IF(OR($EW5=98,$EW5=2),4," ")) -> 4 | FA5: =IF($AP5=55,55,IF(OR($AP5=1,$AP5=3),98," ")) | FB5: =IF($AP5=55,55,IF(OR($AP5=99,$FD5=2),98,IF($AP5=1,7,IF($AP5=3,9,IF(OR($AP5=5,$AP5=6),8," "))))) -> 98 | FC5: =IF($AP5=1,5,IF($AP5=3,7,IF($AP5=99,6,IF($FB5=98,99,IF($AP5=55,55,""))))) -> 6 | FD5: =IF($AP5=55,55,IF($AP5=99,99,"")) -> 99 | FE5: =IF($FD5=2,4,IF($FD5=55,14,IF(YEAR($S5)=2023,2,IF(AP5=3,0,"")))) | FF5: =IF($AP5=1,10,IF($AP5=99,8, IF($FD5=2,12,IF($AP5=3,7,"")))) -> 8 | FH5: =IF(OR($FD5=1,$FD5=99),"1845-01-01"," ") -> 1845-01-01 | FI5: =IF(OR($FD5=1,$FD5=99),98," ") -> 98 | FL5: =COUNTIF(R5:FI5,"<>""")-COUNTBLANK(R5:FI5) -> 143 | FM5: =+FL5/147 -> 0.97278912 | FN5: =+VLOOKUP(R5,'CIE-10'!$A$3:$C$558,3,FALSE) -> 4= CAC Colorectal | FU5: =SUM(FP5:FS5) -> 0
A6: Abandono confirmado | B6: ENITH | C6: DEL CARMEN | D6: MARTINEZ | E6: GOMEZ CASSERES | F6: CC | G6: 33143542 | H6: 18964 | I6: F | R6: C539 | S6: 35976 | T6: 1800-01-01 | U6: 1800-01-01 | V6: 10 | W6: 98 | X6: 1800-01-01 | Y6: 1800-01-01 | Z6: 99 | AA6: 1800-01-01 | AB6: 99 | AC6: 99 | AD6: 99 | AE6: 1800-01-01 | AF6: 98 | AG6: 1845-01-01 | AH6: 98 | AI6: 98 | AJ6: 1845-01-01 | AK6: 98 | AL6: 98 | AM6: 98 | AN6: 1845-01-01 | AO6: 1 | AP6: 99 | AR6: =+IF(AQ6=2,"1845-01-01","") | AS6: =+IF(AQ6=2,"99","") | AT6: =IF(OR($AP6=1,$AP6=3,$AP6=99),98,"") -> 98 | AU6: =IF(AND(OR($R6="C835",$R6="C910",$R6="C920",$R6="C924",$R6="C925"),OR($AT6=98)),0,IF($AT6=55,55,IF(OR($R6="C835",$R6="C910",$R6="C920",$R6="C924",$R6="C925"),SUMIF($AV6:$BC6,1),98))) -> 98 | AV6: =IF($AT6=98,97,IF(AND(OR($R6="C835",$R6="C910",$R6="C920",$R6="C924",$R6="C925"),$AT6=98),97,"")) -> 97 | AW6: =IF($AT6=98,97,IF(AND(OR($R6="C835",$R6="C910",$R6="C920",$R6="C924",$R6="C925"),$AT6=98),97,"")) -> 97 | AX6: =IF($AT6=98,97,IF(AND(OR($R6="C835",$R6="C910",$R6="C920",$R6="C924",$R6="C925"),$AT6=98),97,"")) -> 97 | AY6: =IF($AT6=98,97,IF(AND(OR($R6="C835",$R6="C910",$R6="C920",$R6="C924",$R6="C925"),$AT6=98),97,"")) -> 97 | AZ6: =IF($AT6=98,97,IF(AND(OR($R6="C835",$R6="C910",$R6="C920",$R6="C924",$R6="C925"),$AT6=98),97,"")) -> 97 | BA6: =IF($AT6=98,97,IF(AND(OR($R6="C835",$R6="C910",$R6="C920",$R6="C924",$R6="C925"),$AT6=98),97,"")) -> 97 | BB6: =IF($AT6=98,97,IF(AND(OR($R6="C835",$R6="C910",$R6="C920",$R6="C924",$R6="C925"),$AT6=98),97,"")) -> 97 | BC6: =IF($AT6=98,97,IF(AND(OR($R6="C835",$R6="C910",$R6="C920",$R6="C924",$R6="C925"),$AT6=98),97,"")) -> 97 | BD6: =IF($AT6=98,98,"") -> 98 | BE6: =IF($AT6=98,98,"") -> 98 | BF6: =IF($AT6=98,"1845-01-01","") -> 1845-01-01 | BG6: =IF($AT6=98,98,"") -> 98 | BH6: =IF($AT6=98,98,IF(AT6=1,230010094901,"")) -> 98 | BI6: =IF(OR($AT6=98,$BG6=1),98,"") -> 98 | BJ6: =IF(OR($AT6=98),98,IF($AT6=55,55,"")) -> 98 | BK6: =IF(OR($AT6=98),98,IF($AT6=55,55,"")) -> 98 | BL6: =IF(OR($AT6=98),98,IF($AT6=55,55,"")) -> 98 | BM6: =IF(OR($AT6=98),98,IF($AT6=55,55,"")) -> 98 | BN6: =IF(OR($AT6=98),98,IF($AT6=55,55,"")) -> 98 | BO6: =IF(OR($AT6=98),98,IF($AT6=55,55,"")) -> 98 | BP6: =IF(OR($AT6=98),98,IF($AT6=55,55,"")) -> 98 | BQ6: =IF(OR($AT6=98),98,IF($AT6=55,55,"")) -> 98 | ... BW6: =IF(OR($AT6=98),98,IF($AT6=55,55,"")) -> 98 | BX6: =IF($AT6=98,"1845-01-01","") -> 1845-01-01 | BY6: =IF(OR($AT6=98),98,IF($AT6=55,55,"")) -> 98 | BZ6: =IF(OR($AT6=98,BY6<>2),98,IF($AT6=55,55,"")) -> 98 | CA6: =IF(OR($AT6=98,$AP6=1,$AP6=3,$AP6=99),98,IF($AT6=55,55," ")) -> 98 | CB6: =IF(OR($AT6=98,$CA6=97,$AP6=1,$AP6=3,$AP6=99),"1845-01-01",IF($AT6=55,"1846-01-01"," ")) -> 1845-01-01 | CC6: =IF(OR($AT6=2,$AT6=98,$CA6=97,$AP6=1,$AP6=3,$AP6=99),98,IF($AT6=55,55," ")) -> 98 | CD6: =IF(OR($AT6=2,$AT6=98,$CA6=97,$AP6=1,$AP6=3,$AP6=99),98,IF($AT6=55,55," ")) -> 98 | CE6: =IF(OR($AT6=2,$AT6=98,$CA6=97,$AP6=1,$AP6=3,$AP6=99,$CC6=1),98,IF($AT6=55,55," ")) -> 98 | CF6: =IF(OR($AT6=2,$AT6=98,$CA6=97,$AP6=1,$AP6=3,$AP6=99),98,IF($AT6=55,55,"")) -> 98 | CG6: =IF(OR($AT6=98,$CA6=97,$AP6=1,$AP6=3,$AP6=99),98,IF($AT6=55,55,"")) -> 98 | CH6: =IF(OR($AT6=2,$AT6=98,$CA6=97,$AP6=1,$AP6=3,$AP6=99),98,IF($AT6=55,55,97)) -> 98 | CI6: =IF(OR($AT6=2,$AT6=98,$CA6=97,$AP6=1,$AP6=3,$AP6=99),98,IF($AT6=55,55,97)) -> 98 | CJ6: =IF(OR($AT6=2,$AT6=98,$CA6=97,$AP6=1,$AP6=3,$AP6=99),98,IF($AT6=55,55,97)) -> 98 | CK6: =IF(OR($AT6=2,$AT6=98,$CA6=97,$AP6=1,$AP6=3,$AP6=99),98,IF($AT6=55,55,97)) -> 98 | CL6: =IF(OR($AT6=2,$AT6=98,$CA6=97,$AP6=1,$AP6=3,$AP6=99),98,IF($AT6=55,55,97)) -> 98 | CM6: =IF(OR($AT6=2,$AT6=98,$CA6=97,$AP6=1,$AP6=3,$AP6=99),98,IF($AT6=55,55,97)) -> 98 | CN6: =IF(OR($AT6=2,$AT6=98,$CA6=97,$AP6=1,$AP6=3,$AP6=99),98,IF($AT6=55,55,97)) -> 98 | CO6: =IF(OR($AT6=2,$AT6=98,$CA6=97,$AP6=1,$AP6=3,$AP6=99),98,IF($AT6=55,55,97)) -> 98 | ... CR6: =IF(OR($AT6=2,$AT6=98,$CA6=97,$AP6=1,$AP6=3,$AP6=99),98,IF($AT6=55,55,97)) -> 98 | CS6: =IF($CA6<=10,"",IF(OR($AT6=98,$AT6=2,$CA6=97,$CA6=98,$AP6=1,$AP6=3,$AP6=99),98,IF($AT6=55,55," "))) -> 98 | CT6: =IF($CA6<=10,"",IF(OR($AT6=98,$AT6=2,$CA6=97,$CA6=98,$AP6=1,$AP6=3,$AP6=99),"1845-01-01",IF($AT6=55,"1846-01-01"," "))) -> 1845-01-01 | CU6: =IF($CA6<=10,"",IF(OR($AT6=98,$AT6=2,$CA6=97,$CA6=98,$AP6=1,$AP6=3,$AP6=99),98,IF($AT6=55,55," "))) -> 98 | CV6: =IF($CA6<=10,"",IF(OR($AT6=98,$AT6=2,$CA6=97,$CA6=98,$AP6=1,$AP6=3,$AP6=99),98,IF($AT6=55,55," "))) -> 98 | CW6: =IF(OR($AP6=1,$AP6=3,$AP6=99),2,IF($AP6=55,55," ")) -> 2 | CX6: =IF(OR($AP6=1,$AP6=3,$AP6=99,$CW6=2,$CW6=3),98,IF($AP6=55,55," ")) -> 98 | CY6: =IF(OR($AP6=1,$AP6=3,$AP6=99,$CW6=2,$CW6=3),"1845-01-01",IF($AP6=55,"1846-01-01"," ")) -> 1845-01-01 | CZ6: =IF(OR($AP6=1,$AP6=3,$AP6=99,$CW6=2,$CW6=3),98,IF($AP6=55,55,"230010094901")) -> 98 | DA6: =IF(OR($AP6=1,$AP6=3,$AP6=99,$CW6=2,$CW6=3),98,IF($AP6=55,55," ")) -> 98 | DB6: =IF(OR($AP6=1,$AP6=3,$AP6=99,$CW6=2,$CW6=3),98,IF($AP6=55,55," ")) -> 98 | DC6: =IF(OR($AP6=1,$AP6=3,$AP6=99,$CX6<=1,$CW6=2,$CW6=3),"1845-01-01",IF($AP6=55,"1846-01-01"," ")) -> 1845-01-01 | DD6: =IF(OR($AP6=1,$AP6=3,$AP6=99,$CX6<=1,$CW6=2,$CW6=3),98,IF($AP6=55,55," ")) -> 98 | DE6: =IF(OR($AP6=1,$AP6=3,$AP6=99,$CX6<=1,$CW6=2,$CW6=3),98,IF($AP6=55,55," ")) -> 98 | DF6: =IF(OR($AP6=1,$AP6=3,$AP6=99,$CX6<=1,$CW6=2,$CW6=3),98,IF($AP6=55,55," ")) -> 98 | DG6: =IF(OR($AP6=1,$AP6=3,$AP6=99,$CX6<=1,$CW6=2,$CW6=3),98,IF($AP6=55,55," ")) -> 98 | DH6: =IF(OR($AP6=1,$AP6=3,$AP6=99,$CW6=2,$CW6=3),98,IF($AP6=55,55," ")) -> 98 | DI6: =IF(OR($AP6=1,$AP6=3,$AP6=99),98,IF($AP6=55,55," ")) -> 98 | DJ6: =IF(OR($AP6=1,$AP6=3,$AP6=98,$DI6=98,$DI6=2,$AP6=99),98,IF($AP6=55,55," ")) -> 98 | DK6: =IF(OR($AP6=1,$AP6=3,$AP6=98,$DI6=98,$DI6=2,$AP6=99),"1845-01-01",IF($AP6=55,"1846-01-01"," ")) -> 1845-01-01 | DL6: =IF(OR($AP6=1,$AP6=3,$AP6=98,$DI6=98,$DI6=2,$AP6=99),98,IF($AP6=55,55," ")) -> 98 | DM6: =IF(OR($AP6=1,$AP6=3,$AP6=98,$DI6=98,$DI6=2,$AP6=99),98,IF($AP6=55,55," ")) -> 98 | DN6: =IF(OR($AP6=1,$AP6=3,$AP6=98,$DI6=98,$DI6=2,$AP6=99),98,IF($AP6=55,55," ")) -> 98 | DO6: =IF(OR($AP6=1,$AP6=3,$AP6=98,$DI6=98,$DI6=2,$AP6=99),98,IF($AP6=55,55,"230010094901")) -> 98 | DP6: =IF(OR($AP6=1,$AP6=3,$AP6=98,$DI6=98,$DI6=2,$AP6=99,DN6<=1),98,IF($AP6=55,55," ")) -> 98 | DQ6: =IF(OR($AP6=1,$AP6=3,$AP6=98,$DI6=98,$DI6=2,$AP6=99),"1845-01-01",IF($AP6=55,"1846-01-01"," ")) -> 1845-01-01 | DR6: =IF(OR($AP6=1,$AP6=3,$AP6=98,$DI6=98,$DI6=2,$AP6=99),98,IF($AP6=55,55," ")) -> 98 | DS6: =IF(OR($AP6=1,$AP6=3,$AP6=98,$AP6=99,$DI6=98,$DI6=2,$DR6<>2),98,IF($AP6=55,55," ")) -> 98 | DT6: =IF(OR($AP6=1,$AP6=3,$AP6=98,$AP6=99,$DI6=98,$DI6=2,),"1845-01-01",IF($AP6=55,"1846-01-01"," ")) -> 1845-01-01 | DU6: =IF(OR($AP6=1,$AP6=3,$AP6=98,$AP6=99,$DI6=98,$DI6=2,$DT6="1845-01-01"),98,IF($AP6=55,55," ")) -> 98 | DV6: =IF(OR($AP6=1,$AP6=3,$AP6=98,$AP6=99,$DI6=98,$DI6=2,$DT6="1845-01-01"),98,IF($AP6=55,55," ")) -> 98 | DW6: =IF(OR($AP6=1,$AP6=3,$AP6=98,$AP6=99,$DI6=98,$DI6=2,$DT6="1845-01-01"),98,IF($AP6=55,55," ")) -> 98 | DX6: =IF(OR($AP6=1,$AP6=3,$AP6=98,$AP6=99,$DI6=98,$DI6=2,$DT6="1845-01-01"),98,IF($AP6=55,55," ")) -> 98 | DY6: =IF(OR($AP6=1,$AP6=3,$AP6=98,$AP6=99,$DI6=98,$DI6=2,$DT6="1845-01-01"),98,IF($AP6=55,55," ")) -> 98 | DZ6: =IF(OR($AP6=1,$AP6=3,$AP6=99,$AP6=98,$DI6=98,$DI6=2,$DT6="1845-01-01"),"1845-01-01",IF($AP6=55,"1846-01-01"," ")) -> 1845-01-01 | EA6: =IF(OR($AP6=1,$AP6=3,$AP6=98,$AP6=99,$DI6=98,$DI6=2,$DT6="1845-01-01"),98,IF($AP6=55,55," ")) -> 98 | EB6: =IF(OR($AP6=1,$AP6=3,$AP6=98,$AP6=99,$DI6=98,$DI6=2,$DT6="1845-01-01",$EA6<>2),98,IF($AP6=55,55," ")) -> 98 | EC6: =IF(OR($AP6=1,$AP6=3,$AP6=99),98,IF($AP6=55,55," ")) -> 98 | ED6: =IF(OR($AP6=1,$AP6=3,$EC6=98),98,IF($AP6=55,55," ")) -> 98 | EE6: =IF(OR($AP6=1,$AP6=3,$EC6=98),98,IF($AP6=55,55," ")) -> 98 | EF6: =IF(OR($AP6=1,$AP6=3,$EC6=98),"1845-01-01",IF($AP6=55,"1846-01-01"," ")) -> 1845-01-01 | EG6: =IF(OR($AP6=1,$AP6=3,$EC6=98),98,IF($AP6=55,55,"230010094901")) -> 98 | EH6: =IF(OR($AP6=1,$AP6=3,$AP6=99),98,IF($AP6=55,55," ")) -> 98 | EI6: =IF(OR($AP6=1,$AP6=3,,$AP6=99,$EH6=98),"1845-01-01",IF($AP6=55,"1846-01-01"," ")) -> 1845-01-01 | EJ6: =IF(OR($AP6=1,$AP6=3,,$AP6=99,$EH6=98),98,IF($AP6=55,55," ")) -> 98 | EK6: =IF(OR($AP6=1,$AP6=3,$AP6=99),2,IF($AP6=55,55," ")) -> 2 | EL6: =IF(OR($AP6=1,$AP6=3,$AP6=99,$EK6=2),2,IF($AP6=55,55," ")) -> 2 | EM6: =IF(OR($AP6=1,$AP6=3,$AP6=99,$EK6=2),2,IF($AP6=55,55," ")) -> 2 | EN6: =IF(OR($AP6=1,$AP6=3,$AP6=99,$EK6=2),2,IF($AP6=55,55," ")) -> 2 | EO6: =IF(OR($AP6=1,$AP6=3,$AP6=99,$EK6=2),2,IF($AP6=55,55," ")) -> 2 | EP6: =IF(OR($AP6=1,$AP6=3,$AP6=99,$EK6=2),2,IF($AP6=55,55," ")) -> 2 | EQ6: =IF(OR($AP6=1,$AP6=3,$AP6=99,$EK6=2),2,IF($AP6=55,55," ")) -> 2 | ER6: =IF(OR($AP6=1,$AP6=3,$AP6=99,$EK6=2),"1845-01-01",IF($AP6=55,"1846-01-01"," ")) -> 1845-01-01 | ES6: =IF(OR($AP6=1,$AP6=3,$AP6=99,$EK6=2),98,IF($AP6=55,55," ")) -> 98 | ET6: =IF(OR($AP6=1,$AP6=3,$AP6=99,$EK6=2),98,IF($AP6=55,55," ")) -> 98 | EU6: =IF($AP6=55,"1846-01-01",IF(OR($ET6=2,$ET6=98),"1845-01-01"," ")) -> 1845-01-01 | EV6: =IF($AP6=55,55,IF(OR($ET6=2,$ET6=98),98," ")) -> 98 | EW6: =IF(OR($AP6=1,$AP6=3,$AP6=99),98,IF($AP6=55,55," ")) -> 98 | EX6: =IF($AP6=55,55,IF(OR($EW6=98,$EW6=2),"1845-01-01"," ")) -> 1845-01-01 | EY6: =IF($AP6=55,55,IF(OR($EW6=98,$EW6=2),98,IF($EW6<>" ","230010094901",""))) -> 98 | EZ6: =IF($AP6=55,55,IF(OR($EW6=98,$EW6=2),4," ")) -> 4 | FA6: =IF($AP6=55,55,IF(OR($AP6=1,$AP6=3),98," ")) | FB6: =IF($AP6=55,55,IF(OR($AP6=99,$FD6=2),98,IF($AP6=1,7,IF($AP6=3,9,IF(OR($AP6=5,$AP6=6),8," "))))) -> 98 | FC6: =IF($AP6=1,5,IF($AP6=3,7,IF($AP6=99,6,IF($FB6=98,99,IF($AP6=55,55,""))))) -> 6 | FD6: =IF($AP6=55,55,IF($AP6=99,99,"")) -> 99 | FE6: =IF($FD6=2,4,IF($FD6=55,14,IF(YEAR($S6)=2023,2,IF(AP6=3,0,"")))) | FF6: =IF($AP6=1,10,IF($AP6=99,8, IF($FD6=2,12,IF($AP6=3,7,"")))) -> 8 | FH6: =IF(OR($FD6=1,$FD6=99),"1845-01-01"," ") -> 1845-01-01 | FI6: =IF(OR($FD6=1,$FD6=99),98," ") -> 98 | FL6: =COUNTIF(R6:FI6,"<>""")-COUNTBLANK(R6:FI6) -> 143 | FM6: =+FL6/147 -> 0.97278912 | FN6: =+VLOOKUP(R6,'CIE-10'!$A$3:$C$558,3,FALSE) -> 3= CAC Cérvix | FU6: =SUM(FP6:FS6) -> 0
A7: Abandono confirmado | B7: YOSENIS | C7: ISABEL | D7: MARTINEZ | E7: GARCIA | F7: CC | G7: 25887520 | H7: 24594 | I7: F | R7: C509 | S7: 37026 | T7: 1800-01-01 | U7: 1800-01-01 | V7: 10 | W7: 98 | X7: 1800-01-01 | Y7: 1800-01-01 | Z7: 99 | AA7: 1800-01-01 | AB7: 4 | AC7: 99 | AD7: 14 | AE7: 1800-01-01 | AF7: 99 | AG7: 1800-01-01 | AH7: 99 | AI7: 98 | AJ7: 1845-01-01 | AK7: 98 | AL7: 98 | AM7: 98 | AN7: 1845-01-01 | AO7: 2 | AP7: 99 | AR7: =+IF(AQ7=2,"1845-01-01","") | AS7: =+IF(AQ7=2,"99","") | AT7: =IF(OR($AP7=1,$AP7=3,$AP7=99),98,"") -> 98 | AU7: =IF(AND(OR($R7="C835",$R7="C910",$R7="C920",$R7="C924",$R7="C925"),OR($AT7=98)),0,IF($AT7=55,55,IF(OR($R7="C835",$R7="C910",$R7="C920",$R7="C924",$R7="C925"),SUMIF($AV7:$BC7,1),98))) -> 98 | AV7: =IF($AT7=98,97,IF(AND(OR($R7="C835",$R7="C910",$R7="C920",$R7="C924",$R7="C925"),$AT7=98),97,"")) -> 97 | AW7: =IF($AT7=98,97,IF(AND(OR($R7="C835",$R7="C910",$R7="C920",$R7="C924",$R7="C925"),$AT7=98),97,"")) -> 97 | AX7: =IF($AT7=98,97,IF(AND(OR($R7="C835",$R7="C910",$R7="C920",$R7="C924",$R7="C925"),$AT7=98),97,"")) -> 97 | AY7: =IF($AT7=98,97,IF(AND(OR($R7="C835",$R7="C910",$R7="C920",$R7="C924",$R7="C925"),$AT7=98),97,"")) -> 97 | AZ7: =IF($AT7=98,97,IF(AND(OR($R7="C835",$R7="C910",$R7="C920",$R7="C924",$R7="C925"),$AT7=98),97,"")) -> 97 | BA7: =IF($AT7=98,97,IF(AND(OR($R7="C835",$R7="C910",$R7="C920",$R7="C924",$R7="C925"),$AT7=98),97,"")) -> 97 | BB7: =IF($AT7=98,97,IF(AND(OR($R7="C835",$R7="C910",$R7="C920",$R7="C924",$R7="C925"),$AT7=98),97,"")) -> 97 | BC7: =IF($AT7=98,97,IF(AND(OR($R7="C835",$R7="C910",$R7="C920",$R7="C924",$R7="C925"),$AT7=98),97,"")) -> 97 | BD7: =IF($AT7=98,98,"") -> 98 | BE7: =IF($AT7=98,98,"") -> 98 | BF7: =IF($AT7=98,"1845-01-01","") -> 1845-01-01 | BG7: =IF($AT7=98,98,"") -> 98 | BH7: =IF($AT7=98,98,IF(AT7=1,230010094901,"")) -> 98 | BI7: =IF(OR($AT7=98,$BG7=1),98,"") -> 98 | BJ7: =IF(OR($AT7=98),98,IF($AT7=55,55,"")) -> 98 | BK7: =IF(OR($AT7=98),98,IF($AT7=55,55,"")) -> 98 | BL7: =IF(OR($AT7=98),98,IF($AT7=55,55,"")) -> 98 | BM7: =IF(OR($AT7=98),98,IF($AT7=55,55,"")) -> 98 | BN7: =IF(OR($AT7=98),98,IF($AT7=55,55,"")) -> 98 | BO7: =IF(OR($AT7=98),98,IF($AT7=55,55,"")) -> 98 | BP7: =IF(OR($AT7=98),98,IF($AT7=55,55,"")) -> 98 | BQ7: =IF(OR($AT7=98),98,IF($AT7=55,55,"")) -> 98 | ... BW7: =IF(OR($AT7=98),98,IF($AT7=55,55,"")) -> 98 | BX7: =IF($AT7=98,"1845-01-01","") -> 1845-01-01 | BY7: =IF(OR($AT7=98),98,IF($AT7=55,55,"")) -> 98 | BZ7: =IF(OR($AT7=98,BY7<>2),98,IF($AT7=55,55,"")) -> 98 | CA7: =IF(OR($AT7=98,$AP7=1,$AP7=3,$AP7=99),98,IF($AT7=55,55," ")) -> 98 | CB7: =IF(OR($AT7=98,$CA7=97,$AP7=1,$AP7=3,$AP7=99),"1845-01-01",IF($AT7=55,"1846-01-01"," ")) -> 1845-01-01 | CC7: =IF(OR($AT7=2,$AT7=98,$CA7=97,$AP7=1,$AP7=3,$AP7=99),98,IF($AT7=55,55," ")) -> 98 | CD7: =IF(OR($AT7=2,$AT7=98,$CA7=97,$AP7=1,$AP7=3,$AP7=99),98,IF($AT7=55,55," ")) -> 98 | CE7: =IF(OR($AT7=2,$AT7=98,$CA7=97,$AP7=1,$AP7=3,$AP7=99,$CC7=1),98,IF($AT7=55,55," ")) -> 98 | CF7: =IF(OR($AT7=2,$AT7=98,$CA7=97,$AP7=1,$AP7=3,$AP7=99),98,IF($AT7=55,55,"")) -> 98 | CG7: =IF(OR($AT7=98,$CA7=97,$AP7=1,$AP7=3,$AP7=99),98,IF($AT7=55,55,"")) -> 98 | CH7: =IF(OR($AT7=2,$AT7=98,$CA7=97,$AP7=1,$AP7=3,$AP7=99),98,IF($AT7=55,55,97)) -> 98 | CI7: =IF(OR($AT7=2,$AT7=98,$CA7=97,$AP7=1,$AP7=3,$AP7=99),98,IF($AT7=55,55,97)) -> 98 | CJ7: =IF(OR($AT7=2,$AT7=98,$CA7=97,$AP7=1,$AP7=3,$AP7=99),98,IF($AT7=55,55,97)) -> 98 | CK7: =IF(OR($AT7=2,$AT7=98,$CA7=97,$AP7=1,$AP7=3,$AP7=99),98,IF($AT7=55,55,97)) -> 98 | CL7: =IF(OR($AT7=2,$AT7=98,$CA7=97,$AP7=1,$AP7=3,$AP7=99),98,IF($AT7=55,55,97)) -> 98 | CM7: =IF(OR($AT7=2,$AT7=98,$CA7=97,$AP7=1,$AP7=3,$AP7=99),98,IF($AT7=55,55,97)) -> 98 | CN7: =IF(OR($AT7=2,$AT7=98,$CA7=97,$AP7=1,$AP7=3,$AP7=99),98,IF($AT7=55,55,97)) -> 98 | CO7: =IF(OR($AT7=2,$AT7=98,$CA7=97,$AP7=1,$AP7=3,$AP7=99),98,IF($AT7=55,55,97)) -> 98 | ... CR7: =IF(OR($AT7=2,$AT7=98,$CA7=97,$AP7=1,$AP7=3,$AP7=99),98,IF($AT7=55,55,97)) -> 98 | CS7: =IF($CA7<=10,"",IF(OR($AT7=98,$AT7=2,$CA7=97,$CA7=98,$AP7=1,$AP7=3,$AP7=99),98,IF($AT7=55,55," "))) -> 98 | CT7: =IF($CA7<=10,"",IF(OR($AT7=98,$AT7=2,$CA7=97,$CA7=98,$AP7=1,$AP7=3,$AP7=99),"1845-01-01",IF($AT7=55,"1846-01-01"," "))) -> 1845-01-01 | CU7: =IF($CA7<=10,"",IF(OR($AT7=98,$AT7=2,$CA7=97,$CA7=98,$AP7=1,$AP7=3,$AP7=99),98,IF($AT7=55,55," "))) -> 98 | CV7: =IF($CA7<=10,"",IF(OR($AT7=98,$AT7=2,$CA7=97,$CA7=98,$AP7=1,$AP7=3,$AP7=99),98,IF($AT7=55,55," "))) -> 98 | CW7: =IF(OR($AP7=1,$AP7=3,$AP7=99),2,IF($AP7=55,55," ")) -> 2 | CX7: =IF(OR($AP7=1,$AP7=3,$AP7=99,$CW7=2,$CW7=3),98,IF($AP7=55,55," ")) -> 98 | CY7: =IF(OR($AP7=1,$AP7=3,$AP7=99,$CW7=2,$CW7=3),"1845-01-01",IF($AP7=55,"1846-01-01"," ")) -> 1845-01-01 | CZ7: =IF(OR($AP7=1,$AP7=3,$AP7=99,$CW7=2,$CW7=3),98,IF($AP7=55,55,"230010094901")) -> 98 | DA7: =IF(OR($AP7=1,$AP7=3,$AP7=99,$CW7=2,$CW7=3),98,IF($AP7=55,55," ")) -> 98 | DB7: =IF(OR($AP7=1,$AP7=3,$AP7=99,$CW7=2,$CW7=3),98,IF($AP7=55,55," ")) -> 98 | DC7: =IF(OR($AP7=1,$AP7=3,$AP7=99,$CX7<=1,$CW7=2,$CW7=3),"1845-01-01",IF($AP7=55,"1846-01-01"," ")) -> 1845-01-01 | DD7: =IF(OR($AP7=1,$AP7=3,$AP7=99,$CX7<=1,$CW7=2,$CW7=3),98,IF($AP7=55,55," ")) -> 98 | DE7: =IF(OR($AP7=1,$AP7=3,$AP7=99,$CX7<=1,$CW7=2,$CW7=3),98,IF($AP7=55,55," ")) -> 98 | DF7: =IF(OR($AP7=1,$AP7=3,$AP7=99,$CX7<=1,$CW7=2,$CW7=3),98,IF($AP7=55,55," ")) -> 98 | DG7: =IF(OR($AP7=1,$AP7=3,$AP7=99,$CX7<=1,$CW7=2,$CW7=3),98,IF($AP7=55,55," ")) -> 98 | DH7: =IF(OR($AP7=1,$AP7=3,$AP7=99,$CW7=2,$CW7=3),98,IF($AP7=55,55," ")) -> 98 | DI7: =IF(OR($AP7=1,$AP7=3,$AP7=99),98,IF($AP7=55,55," ")) -> 98 | DJ7: =IF(OR($AP7=1,$AP7=3,$AP7=98,$DI7=98,$DI7=2,$AP7=99),98,IF($AP7=55,55," ")) -> 98 | DK7: =IF(OR($AP7=1,$AP7=3,$AP7=98,$DI7=98,$DI7=2,$AP7=99),"1845-01-01",IF($AP7=55,"1846-01-01"," ")) -> 1845-01-01 | DL7: =IF(OR($AP7=1,$AP7=3,$AP7=98,$DI7=98,$DI7=2,$AP7=99),98,IF($AP7=55,55," ")) -> 98 | DM7: =IF(OR($AP7=1,$AP7=3,$AP7=98,$DI7=98,$DI7=2,$AP7=99),98,IF($AP7=55,55," ")) -> 98 | DN7: =IF(OR($AP7=1,$AP7=3,$AP7=98,$DI7=98,$DI7=2,$AP7=99),98,IF($AP7=55,55," ")) -> 98 | DO7: =IF(OR($AP7=1,$AP7=3,$AP7=98,$DI7=98,$DI7=2,$AP7=99),98,IF($AP7=55,55,"230010094901")) -> 98 | DP7: =IF(OR($AP7=1,$AP7=3,$AP7=98,$DI7=98,$DI7=2,$AP7=99,DN7<=1),98,IF($AP7=55,55," ")) -> 98 | DQ7: =IF(OR($AP7=1,$AP7=3,$AP7=98,$DI7=98,$DI7=2,$AP7=99),"1845-01-01",IF($AP7=55,"1846-01-01"," ")) -> 1845-01-01 | DR7: =IF(OR($AP7=1,$AP7=3,$AP7=98,$DI7=98,$DI7=2,$AP7=99),98,IF($AP7=55,55," ")) -> 98 | DS7: =IF(OR($AP7=1,$AP7=3,$AP7=98,$AP7=99,$DI7=98,$DI7=2,$DR7<>2),98,IF($AP7=55,55," ")) -> 98 | DT7: =IF(OR($AP7=1,$AP7=3,$AP7=98,$AP7=99,$DI7=98,$DI7=2,),"1845-01-01",IF($AP7=55,"1846-01-01"," ")) -> 1845-01-01 | DU7: =IF(OR($AP7=1,$AP7=3,$AP7=98,$AP7=99,$DI7=98,$DI7=2,$DT7="1845-01-01"),98,IF($AP7=55,55," ")) -> 98 | DV7: =IF(OR($AP7=1,$AP7=3,$AP7=98,$AP7=99,$DI7=98,$DI7=2,$DT7="1845-01-01"),98,IF($AP7=55,55," ")) -> 98 | DW7: =IF(OR($AP7=1,$AP7=3,$AP7=98,$AP7=99,$DI7=98,$DI7=2,$DT7="1845-01-01"),98,IF($AP7=55,55," ")) -> 98 | DX7: =IF(OR($AP7=1,$AP7=3,$AP7=98,$AP7=99,$DI7=98,$DI7=2,$DT7="1845-01-01"),98,IF($AP7=55,55," ")) -> 98 | DY7: =IF(OR($AP7=1,$AP7=3,$AP7=98,$AP7=99,$DI7=98,$DI7=2,$DT7="1845-01-01"),98,IF($AP7=55,55," ")) -> 98 | DZ7: =IF(OR($AP7=1,$AP7=3,$AP7=99,$AP7=98,$DI7=98,$DI7=2,$DT7="1845-01-01"),"1845-01-01",IF($AP7=55,"1846-01-01"," ")) -> 1845-01-01 | EA7: =IF(OR($AP7=1,$AP7=3,$AP7=98,$AP7=99,$DI7=98,$DI7=2,$DT7="1845-01-01"),98,IF($AP7=55,55," ")) -> 98 | EB7: =IF(OR($AP7=1,$AP7=3,$AP7=98,$AP7=99,$DI7=98,$DI7=2,$DT7="1845-01-01",$EA7<>2),98,IF($AP7=55,55," ")) -> 98 | EC7: =IF(OR($AP7=1,$AP7=3,$AP7=99),98,IF($AP7=55,55," ")) -> 98 | ED7: =IF(OR($AP7=1,$AP7=3,$EC7=98),98,IF($AP7=55,55," ")) -> 98 | EE7: =IF(OR($AP7=1,$AP7=3,$EC7=98),98,IF($AP7=55,55," ")) -> 98 | EF7: =IF(OR($AP7=1,$AP7=3,$EC7=98),"1845-01-01",IF($AP7=55,"1846-01-01"," ")) -> 1845-01-01 | EG7: =IF(OR($AP7=1,$AP7=3,$EC7=98),98,IF($AP7=55,55,"230010094901")) -> 98 | EH7: =IF(OR($AP7=1,$AP7=3,$AP7=99),98,IF($AP7=55,55," ")) -> 98 | EI7: =IF(OR($AP7=1,$AP7=3,,$AP7=99,$EH7=98),"1845-01-01",IF($AP7=55,"1846-01-01"," ")) -> 1845-01-01 | EJ7: =IF(OR($AP7=1,$AP7=3,,$AP7=99,$EH7=98),98,IF($AP7=55,55," ")) -> 98 | EK7: =IF(OR($AP7=1,$AP7=3,$AP7=99),2,IF($AP7=55,55," ")) -> 2 | EL7: =IF(OR($AP7=1,$AP7=3,$AP7=99,$EK7=2),2,IF($AP7=55,55," ")) -> 2 | EM7: =IF(OR($AP7=1,$AP7=3,$AP7=99,$EK7=2),2,IF($AP7=55,55," ")) -> 2 | EN7: =IF(OR($AP7=1,$AP7=3,$AP7=99,$EK7=2),2,IF($AP7=55,55," ")) -> 2 | EO7: =IF(OR($AP7=1,$AP7=3,$AP7=99,$EK7=2),2,IF($AP7=55,55," ")) -> 2 | EP7: =IF(OR($AP7=1,$AP7=3,$AP7=99,$EK7=2),2,IF($AP7=55,55," ")) -> 2 | EQ7: =IF(OR($AP7=1,$AP7=3,$AP7=99,$EK7=2),2,IF($AP7=55,55," ")) -> 2 | ER7: =IF(OR($AP7=1,$AP7=3,$AP7=99,$EK7=2),"1845-01-01",IF($AP7=55,"1846-01-01"," ")) -> 1845-01-01 | ES7: =IF(OR($AP7=1,$AP7=3,$AP7=99,$EK7=2),98,IF($AP7=55,55," ")) -> 98 | ET7: =IF(OR($AP7=1,$AP7=3,$AP7=99,$EK7=2),98,IF($AP7=55,55," ")) -> 98 | EU7: =IF($AP7=55,"1846-01-01",IF(OR($ET7=2,$ET7=98),"1845-01-01"," ")) -> 1845-01-01 | EV7: =IF($AP7=55,55,IF(OR($ET7=2,$ET7=98),98," ")) -> 98 | EW7: =IF(OR($AP7=1,$AP7=3,$AP7=99),98,IF($AP7=55,55," ")) -> 98 | EX7: =IF($AP7=55,55,IF(OR($EW7=98,$EW7=2),"1845-01-01"," ")) -> 1845-01-01 | EY7: =IF($AP7=55,55,IF(OR($EW7=98,$EW7=2),98,IF($EW7<>" ","230010094901",""))) -> 98 | EZ7: =IF($AP7=55,55,IF(OR($EW7=98,$EW7=2),4," ")) -> 4 | FA7: =IF($AP7=55,55,IF(OR($AP7=1,$AP7=3),98," ")) | FB7: =IF($AP7=55,55,IF(OR($AP7=99,$FD7=2),98,IF($AP7=1,7,IF($AP7=3,9,IF(OR($AP7=5,$AP7=6),8," "))))) -> 98 | FC7: =IF($AP7=1,5,IF($AP7=3,7,IF($AP7=99,6,IF($FB7=98,99,IF($AP7=55,55,""))))) -> 6 | FD7: =IF($AP7=55,55,IF($AP7=99,99,"")) -> 99 | FE7: =IF($FD7=2,4,IF($FD7=55,14,IF(YEAR($S7)=2023,2,IF(AP7=3,0,"")))) | FF7: =IF($AP7=1,10,IF($AP7=99,8, IF($FD7=2,12,IF($AP7=3,7,"")))) -> 8 | FH7: =IF(OR($FD7=1,$FD7=99),"1845-01-01"," ") -> 1845-01-01 | FI7: =IF(OR($FD7=1,$FD7=99),98," ") -> 98 | FL7: =COUNTIF(R7:FI7,"<>""")-COUNTBLANK(R7:FI7) -> 143 | FM7: =+FL7/147 -> 0.97278912 | FN7: =+VLOOKUP(R7,'CIE-10'!$A$3:$C$558,3,FALSE) -> 1= CAC Mama | FU7: =SUM(FP7:FS7) -> 0
A8: Con tratamiento | B8: NEILA | C8: SOFIA | D8: MARTINEZ | E8: NORIEGA | F8: CC | G8: 26136005 | H8: 21458 | I8: F | R8: C509 | S8: 37302 | T8: 37271 | U8: 1800-01-01 | V8: 10 | W8: 98 | X8: 1800-01-01 | Y8: 37302 | Z8: 99 | AA8: 1800-01-01 | AB8: 4 | AC8: 99 | AD8: 99 | AE8: 1800-01-01 | AF8: 1 | AG8: 42005 | AH8: 1 | AI8: 98 | AJ8: 1845-01-01 | AK8: 98 | AL8: 98 | AM8: 98 | AN8: 1845-01-01 | AO8: 1 | AP8: 2 | AQ8: 2 | AR8: =+IF(AQ8=2,"1845-01-01","") -> 1845-01-01 | AS8: =+IF(AQ8=2,"99","") -> 99 | AT8: 1 | AU8: =IF(AND(OR($R8="C835",$R8="C910",$R8="C920",$R8="C924",$R8="C925"),OR($AT8=98)),0,IF($AT8=55,55,IF(OR($R8="C835",$R8="C910",$R8="C920",$R8="C924",$R8="C925"),SUMIF($AV8:$BC8,1),98))) -> 98 | AV8: 97 | AW8: 97 | AX8: 97 | AY8: 97 | AZ8: 97 | BA8: 97 | BB8: 97 | BC8: 97 | BD8: 5 | BE8: 13 | BF8: 44778 | BG8: 1 | BH8: =IF($AT8=98,98,IF(AT8=1,230010094901,"")) -> 230010094901 | BI8: =IF(OR($AT8=98,$BG8=1),98,"") -> 98 | BJ8: 1 | BK8: L01XC14 TRASTUZUMAB EMTANSINE | BL8: 97 | BM8: 97 | BN8: 97 | BO8: 97 | BP8: 97 | BQ8: 97 | BR8: 97 | BS8: 97 | BT8: 97 | BU8: 97 | BV8: 97 | BW8: 2 | BX8: 1800-01-01 | BY8: 3 | BZ8: =IF(OR($AT8=98,BY8<>2),98,IF($AT8=55,55,"")) -> 98 | CA8: 97 | CB8: 1845-01-01 | CC8: 98 | CD8: 98 | CE8: 98 | CF8: 98 | CG8: 98 | CH8: =IF(OR($AT8=2,$AT8=98,$CA8=97,$AP8=1,$AP8=3,$AP8=99),98,IF($AT8=55,55,97)) -> 98 | CI8: =IF(OR($AT8=2,$AT8=98,$CA8=97,$AP8=1,$AP8=3,$AP8=99),98,IF($AT8=55,55,97)) -> 98 | CJ8: =IF(OR($AT8=2,$AT8=98,$CA8=97,$AP8=1,$AP8=3,$AP8=99),98,IF($AT8=55,55,97)) -> 98 | CK8: =IF(OR($AT8=2,$AT8=98,$CA8=97,$AP8=1,$AP8=3,$AP8=99),98,IF($AT8=55,55,97)) -> 98 | CL8: =IF(OR($AT8=2,$AT8=98,$CA8=97,$AP8=1,$AP8=3,$AP8=99),98,IF($AT8=55,55,97)) -> 98 | CM8: =IF(OR($AT8=2,$AT8=98,$CA8=97,$AP8=1,$AP8=3,$AP8=99),98,IF($AT8=55,55,97)) -> 98 | CN8: =IF(OR($AT8=2,$AT8=98,$CA8=97,$AP8=1,$AP8=3,$AP8=99),98,IF($AT8=55,55,97)) -> 98 | CO8: =IF(OR($AT8=2,$AT8=98,$CA8=97,$AP8=1,$AP8=3,$AP8=99),98,IF($AT8=55,55,97)) -> 98 | ... CR8: =IF(OR($AT8=2,$AT8=98,$CA8=97,$AP8=1,$AP8=3,$AP8=99),98,IF($AT8=55,55,97)) -> 98 | CS8: =IF($CA8<=10,"",IF(OR($AT8=98,$AT8=2,$CA8=97,$CA8=98,$AP8=1,$AP8=3,$AP8=99),98,IF($AT8=55,55," "))) -> 98 | CT8: =IF($CA8<=10,"",IF(OR($AT8=98,$AT8=2,$CA8=97,$CA8=98,$AP8=1,$AP8=3,$AP8=99),"1845-01-01",IF($AT8=55,"1846-01-01"," "))) -> 1845-01-01 | CU8: =IF($CA8<=10,"",IF(OR($AT8=98,$AT8=2,$CA8=97,$CA8=98,$AP8=1,$AP8=3,$AP8=99),98,IF($AT8=55,55," "))) -> 98 | CV8: =IF($CA8<=10,"",IF(OR($AT8=98,$AT8=2,$CA8=97,$CA8=98,$AP8=1,$AP8=3,$AP8=99),98,IF($AT8=55,55," "))) -> 98 | CW8: 2 | CX8: =IF(OR($AP8=1,$AP8=3,$AP8=99,$CW8=2,$CW8=3),98,IF($AP8=55,55," ")) -> 98 | CY8: =IF(OR($AP8=1,$AP8=3,$AP8=99,$CW8=2,$CW8=3),"1845-01-01",IF($AP8=55,"1846-01-01"," ")) -> 1845-01-01 | CZ8: =IF(OR($AP8=1,$AP8=3,$AP8=99,$CW8=2,$CW8=3),98,IF($AP8=55,55,"230010094901")) -> 98 | DA8: =IF(OR($AP8=1,$AP8=3,$AP8=99,$CW8=2,$CW8=3),98,IF($AP8=55,55," ")) -> 98 | DB8: =IF(OR($AP8=1,$AP8=3,$AP8=99,$CW8=2,$CW8=3),98,IF($AP8=55,55," ")) -> 98 | DC8: =IF(OR($AP8=1,$AP8=3,$AP8=99,$CX8<=1,$CW8=2,$CW8=3),"1845-01-01",IF($AP8=55,"1846-01-01"," ")) -> 1845-01-01 | DD8: =IF(OR($AP8=1,$AP8=3,$AP8=99,$CX8<=1,$CW8=2,$CW8=3),98,IF($AP8=55,55," ")) -> 98 | DE8: =IF(OR($AP8=1,$AP8=3,$AP8=99,$CX8<=1,$CW8=2,$CW8=3),98,IF($AP8=55,55," ")) -> 98 | DF8: =IF(OR($AP8=1,$AP8=3,$AP8=99,$CX8<=1,$CW8=2,$CW8=3),98,IF($AP8=55,55," ")) -> 98 | DG8: =IF(OR($AP8=1,$AP8=3,$AP8=99,$CX8<=1,$CW8=2,$CW8=3),98,IF($AP8=55,55," ")) -> 98 | DH8: =IF(OR($AP8=1,$AP8=3,$AP8=99,$CW8=2,$CW8=3),98,IF($AP8=55,55," ")) -> 98 | DI8: 98 | DJ8: =IF(OR($AP8=1,$AP8=3,$AP8=98,$DI8=98,$DI8=2,$AP8=99),98,IF($AP8=55,55," ")) -> 98 | DK8: =IF(OR($AP8=1,$AP8=3,$AP8=98,$DI8=98,$DI8=2,$AP8=99),"1845-01-01",IF($AP8=55,"1846-01-01"," ")) -> 1845-01-01 | DL8: =IF(OR($AP8=1,$AP8=3,$AP8=98,$DI8=98,$DI8=2,$AP8=99),98,IF($AP8=55,55," ")) -> 98 | DM8: =IF(OR($AP8=1,$AP8=3,$AP8=98,$DI8=98,$DI8=2,$AP8=99),98,IF($AP8=55,55," ")) -> 98 | DN8: =IF(OR($AP8=1,$AP8=3,$AP8=98,$DI8=98,$DI8=2,$AP8=99),98,IF($AP8=55,55," ")) -> 98 | DO8: =IF(OR($AP8=1,$AP8=3,$AP8=98,$DI8=98,$DI8=2,$AP8=99),98,IF($AP8=55,55,"230010094901")) -> 98 | DP8: =IF(OR($AP8=1,$AP8=3,$AP8=98,$DI8=98,$DI8=2,$AP8=99,DN8<=1),98,IF($AP8=55,55," ")) -> 98 | DQ8: =IF(OR($AP8=1,$AP8=3,$AP8=98,$DI8=98,$DI8=2,$AP8=99),"1845-01-01",IF($AP8=55,"1846-01-01"," ")) -> 1845-01-01 | DR8: =IF(OR($AP8=1,$AP8=3,$AP8=98,$DI8=98,$DI8=2,$AP8=99),98,IF($AP8=55,55," ")) -> 98 | DS8: =IF(OR($AP8=1,$AP8=3,$AP8=98,$AP8=99,$DI8=98,$DI8=2,$DR8<>2),98,IF($AP8=55,55," ")) -> 98 | DT8: =IF(OR($AP8=1,$AP8=3,$AP8=98,$AP8=99,$DI8=98,$DI8=2,),"1845-01-01",IF($AP8=55,"1846-01-01"," ")) -> 1845-01-01 | DU8: =IF(OR($AP8=1,$AP8=3,$AP8=98,$AP8=99,$DI8=98,$DI8=2,$DT8="1845-01-01"),98,IF($AP8=55,55," ")) -> 98 | DV8: =IF(OR($AP8=1,$AP8=3,$AP8=98,$AP8=99,$DI8=98,$DI8=2,$DT8="1845-01-01"),98,IF($AP8=55,55," ")) -> 98 | DW8: =IF(OR($AP8=1,$AP8=3,$AP8=98,$AP8=99,$DI8=98,$DI8=2,$DT8="1845-01-01"),98,IF($AP8=55,55," ")) -> 98 | DX8: =IF(OR($AP8=1,$AP8=3,$AP8=98,$AP8=99,$DI8=98,$DI8=2,$DT8="1845-01-01"),98,IF($AP8=55,55," ")) -> 98 | DY8: =IF(OR($AP8=1,$AP8=3,$AP8=98,$AP8=99,$DI8=98,$DI8=2,$DT8="1845-01-01"),98,IF($AP8=55,55," ")) -> 98 | DZ8: =IF(OR($AP8=1,$AP8=3,$AP8=99,$AP8=98,$DI8=98,$DI8=2,$DT8="1845-01-01"),"1845-01-01",IF($AP8=55,"1846-01-01"," ")) -> 1845-01-01 | EA8: =IF(OR($AP8=1,$AP8=3,$AP8=98,$AP8=99,$DI8=98,$DI8=2,$DT8="1845-01-01"),98,IF($AP8=55,55," ")) -> 98 | EB8: =IF(OR($AP8=1,$AP8=3,$AP8=98,$AP8=99,$DI8=98,$DI8=2,$DT8="1845-01-01",$EA8<>2),98,IF($AP8=55,55," ")) -> 98 | EC8: 98 | ED8: =IF(OR($AP8=1,$AP8=3,$EC8=98),98,IF($AP8=55,55," ")) -> 98 | EE8: =IF(OR($AP8=1,$AP8=3,$EC8=98),98,IF($AP8=55,55," ")) -> 98 | EF8: =IF(OR($AP8=1,$AP8=3,$EC8=98),"1845-01-01",IF($AP8=55,"1846-01-01"," ")) -> 1845-01-01 | EG8: =IF(OR($AP8=1,$AP8=3,$EC8=98),98,IF($AP8=55,55,"230010094901")) -> 98 | EH8: 98 | EI8: =IF(OR($AP8=1,$AP8=3,,$AP8=99,$EH8=98),"1845-01-01",IF($AP8=55,"1846-01-01"," ")) -> 1845-01-01 | EJ8: =IF(OR($AP8=1,$AP8=3,,$AP8=99,$EH8=98),98,IF($AP8=55,55," ")) -> 98 | EK8: 2 | EL8: =IF(OR($AP8=1,$AP8=3,$AP8=99,$EK8=2),2,IF($AP8=55,55," ")) -> 2 | EM8: =IF(OR($AP8=1,$AP8=3,$AP8=99,$EK8=2),2,IF($AP8=55,55," ")) -> 2 | EN8: =IF(OR($AP8=1,$AP8=3,$AP8=99,$EK8=2),2,IF($AP8=55,55," ")) -> 2 | EO8: =IF(OR($AP8=1,$AP8=3,$AP8=99,$EK8=2),2,IF($AP8=55,55," ")) -> 2 | EP8: =IF(OR($AP8=1,$AP8=3,$AP8=99,$EK8=2),2,IF($AP8=55,55," ")) -> 2 | EQ8: =IF(OR($AP8=1,$AP8=3,$AP8=99,$EK8=2),2,IF($AP8=55,55," ")) -> 2 | ER8: =IF(OR($AP8=1,$AP8=3,$AP8=99,$EK8=2),"1845-01-01",IF($AP8=55,"1846-01-01"," ")) -> 1845-01-01 | ES8: =IF(OR($AP8=1,$AP8=3,$AP8=99,$EK8=2),98,IF($AP8=55,55," ")) -> 98 | ET8: =IF(OR($AP8=1,$AP8=3,$AP8=99,$EK8=2),98,IF($AP8=55,55," ")) -> 98 | EU8: =IF($AP8=55,"1846-01-01",IF(OR($ET8=2,$ET8=98),"1845-01-01"," ")) -> 1845-01-01 | EV8: =IF($AP8=55,55,IF(OR($ET8=2,$ET8=98),98," ")) -> 98 | EW8: 98 | EX8: =IF($AP8=55,55,IF(OR($EW8=98,$EW8=2),"1845-01-01"," ")) -> 1845-01-01 | EY8: =IF($AP8=55,55,IF(OR($EW8=98,$EW8=2),98,IF($EW8<>" ","230010094901",""))) -> 98 | EZ8: =IF($AP8=55,55,IF(OR($EW8=98,$EW8=2),4," ")) -> 4 | FA8: 98 | FB8: 2 | FC8: 97 | FD8: 1 | FE8: 0 | FF8: 11 | FH8: =IF(OR($FD8=1,$FD8=99),"1845-01-01"," ") -> 1845-01-01 | FI8: =IF(OR($FD8=1,$FD8=99),98," ") -> 98 | FL8: =COUNTIF(R8:FI8,"<>""")-COUNTBLANK(R8:FI8) -> 147 | FM8: =+FL8/147 -> 1 | FN8: =+VLOOKUP(R8,'CIE-10'!$A$3:$C$558,3,FALSE) -> 1= CAC Mama | FT8: 1 | FU8: =SUM(FP8:FS8) -> 0
A9: CREAR SEGUNDA LINEA DE LIPOSARCOMA | B9: MARNEDYS | C9: DEL SOCORRO | D9: PAYAREZ | E9: PATERNINA | F9: CC | G9: 34989164 | H9: 23337 | I9: F | R9: C509 | S9: 37638 | T9: 37602 | U9: 37638 | V9: 10 | W9: 98 | X9: 37638 | Y9: 37638 | Z9: 230010144701 | AA9: 37638 | AB9: 4 | AC9: 1 | AD9: 18 | AE9: 37638 | AF9: 2 | AG9: 1845-01-01 | AH9: 98 | AI9: 98 | AJ9: 1845-01-01 | AK9: 98 | AL9: 98 | AM9: 98 | AN9: 1845-01-01 | AO9: 1 | AP9: 3 | AR9: =+IF(AQ9=2,"1845-01-01","") | AS9: =+IF(AQ9=2,"99","") | AT9: =IF(OR($AP9=1,$AP9=3,$AP9=99),98,"") -> 98 | AU9: =IF(AND(OR($R9="C835",$R9="C910",$R9="C920",$R9="C924",$R9="C925"),OR($AT9=98)),0,IF($AT9=55,55,IF(OR($R9="C835",$R9="C910",$R9="C920",$R9="C924",$R9="C925"),SUMIF($AV9:$BC9,1),98))) -> 98 | AV9: =IF($AT9=98,97,IF(AND(OR($R9="C835",$R9="C910",$R9="C920",$R9="C924",$R9="C925"),$AT9=98),97,"")) -> 97 | AW9: =IF($AT9=98,97,IF(AND(OR($R9="C835",$R9="C910",$R9="C920",$R9="C924",$R9="C925"),$AT9=98),97,"")) -> 97 | AX9: =IF($AT9=98,97,IF(AND(OR($R9="C835",$R9="C910",$R9="C920",$R9="C924",$R9="C925"),$AT9=98),97,"")) -> 97 | AY9: =IF($AT9=98,97,IF(AND(OR($R9="C835",$R9="C910",$R9="C920",$R9="C924",$R9="C925"),$AT9=98),97,"")) -> 97 | AZ9: =IF($AT9=98,97,IF(AND(OR($R9="C835",$R9="C910",$R9="C920",$R9="C924",$R9="C925"),$AT9=98),97,"")) -> 97 | BA9: =IF($AT9=98,97,IF(AND(OR($R9="C835",$R9="C910",$R9="C920",$R9="C924",$R9="C925"),$AT9=98),97,"")) -> 97 | BB9: =IF($AT9=98,97,IF(AND(OR($R9="C835",$R9="C910",$R9="C920",$R9="C924",$R9="C925"),$AT9=98),97,"")) -> 97 | BC9: =IF($AT9=98,97,IF(AND(OR($R9="C835",$R9="C910",$R9="C920",$R9="C924",$R9="C925"),$AT9=98),97,"")) -> 97 | BD9: =IF($AT9=98,98,"") -> 98 | BE9: =IF($AT9=98,98,"") -> 98 | BF9: =IF($AT9=98,"1845-01-01","") -> 1845-01-01 | BG9: =IF($AT9=98,98,"") -> 98 | BH9: =IF($AT9=98,98,IF(AT9=1,230010094901,"")) -> 98 | BI9: =IF(OR($AT9=98,$BG9=1),98,"") -> 98 | BJ9: =IF(OR($AT9=98),98,IF($AT9=55,55,"")) -> 98 | BK9: =IF(OR($AT9=98),98,IF($AT9=55,55,"")) -> 98 | BL9: =IF(OR($AT9=98),98,IF($AT9=55,55,"")) -> 98 | BM9: =IF(OR($AT9=98),98,IF($AT9=55,55,"")) -> 98 | BN9: =IF(OR($AT9=98),98,IF($AT9=55,55,"")) -> 98 | BO9: =IF(OR($AT9=98),98,IF($AT9=55,55,"")) -> 98 | BP9: =IF(OR($AT9=98),98,IF($AT9=55,55,"")) -> 98 | BQ9: =IF(OR($AT9=98),98,IF($AT9=55,55,"")) -> 98 | ... BW9: =IF(OR($AT9=98),98,IF($AT9=55,55,"")) -> 98 | BX9: =IF($AT9=98,"1845-01-01","") -> 1845-01-01 | BY9: =IF(OR($AT9=98),98,IF($AT9=55,55,"")) -> 98 | BZ9: =IF(OR($AT9=98,BY9<>2),98,IF($AT9=55,55,"")) -> 98 | CA9: =IF(OR($AT9=98,$AP9=1,$AP9=3,$AP9=99),98,IF($AT9=55,55," ")) -> 98 | CB9: =IF(OR($AT9=98,$CA9=97,$AP9=1,$AP9=3,$AP9=99),"1845-01-01",IF($AT9=55,"1846-01-01"," ")) -> 1845-01-01 | CC9: =IF(OR($AT9=2,$AT9=98,$CA9=97,$AP9=1,$AP9=3,$AP9=99),98,IF($AT9=55,55," ")) -> 98 | CD9: =IF(OR($AT9=2,$AT9=98,$CA9=97,$AP9=1,$AP9=3,$AP9=99),98,IF($AT9=55,55," ")) -> 98 | CE9: =IF(OR($AT9=2,$AT9=98,$CA9=97,$AP9=1,$AP9=3,$AP9=99,$CC9=1),98,IF($AT9=55,55," ")) -> 98 | CF9: =IF(OR($AT9=2,$AT9=98,$CA9=97,$AP9=1,$AP9=3,$AP9=99),98,IF($AT9=55,55,"")) -> 98 | CG9: =IF(OR($AT9=98,$CA9=97,$AP9=1,$AP9=3,$AP9=99),98,IF($AT9=55,55,"")) -> 98 | CH9: =IF(OR($AT9=2,$AT9=98,$CA9=97,$AP9=1,$AP9=3,$AP9=99),98,IF($AT9=55,55,97)) -> 98 | CI9: =IF(OR($AT9=2,$AT9=98,$CA9=97,$AP9=1,$AP9=3,$AP9=99),98,IF($AT9=55,55,97)) -> 98 | CJ9: =IF(OR($AT9=2,$AT9=98,$CA9=97,$AP9=1,$AP9=3,$AP9=99),98,IF($AT9=55,55,97)) -> 98 | CK9: =IF(OR($AT9=2,$AT9=98,$CA9=97,$AP9=1,$AP9=3,$AP9=99),98,IF($AT9=55,55,97)) -> 98 | CL9: =IF(OR($AT9=2,$AT9=98,$CA9=97,$AP9=1,$AP9=3,$AP9=99),98,IF($AT9=55,55,97)) -> 98 | CM9: =IF(OR($AT9=2,$AT9=98,$CA9=97,$AP9=1,$AP9=3,$AP9=99),98,IF($AT9=55,55,97)) -> 98 | CN9: =IF(OR($AT9=2,$AT9=98,$CA9=97,$AP9=1,$AP9=3,$AP9=99),98,IF($AT9=55,55,97)) -> 98 | CO9: =IF(OR($AT9=2,$AT9=98,$CA9=97,$AP9=1,$AP9=3,$AP9=99),98,IF($AT9=55,55,97)) -> 98 | ... CR9: =IF(OR($AT9=2,$AT9=98,$CA9=97,$AP9=1,$AP9=3,$AP9=99),98,IF($AT9=55,55,97)) -> 98 | CS9: =IF($CA9<=10,"",IF(OR($AT9=98,$AT9=2,$CA9=97,$CA9=98,$AP9=1,$AP9=3,$AP9=99),98,IF($AT9=55,55," "))) -> 98 | CT9: =IF($CA9<=10,"",IF(OR($AT9=98,$AT9=2,$CA9=97,$CA9=98,$AP9=1,$AP9=3,$AP9=99),"1845-01-01",IF($AT9=55,"1846-01-01"," "))) -> 1845-01-01 | CU9: =IF($CA9<=10,"",IF(OR($AT9=98,$AT9=2,$CA9=97,$CA9=98,$AP9=1,$AP9=3,$AP9=99),98,IF($AT9=55,55," "))) -> 98 | CV9: =IF($CA9<=10,"",IF(OR($AT9=98,$AT9=2,$CA9=97,$CA9=98,$AP9=1,$AP9=3,$AP9=99),98,IF($AT9=55,55," "))) -> 98 | CW9: =IF(OR($AP9=1,$AP9=3,$AP9=99),2,IF($AP9=55,55," ")) -> 2 | CX9: =IF(OR($AP9=1,$AP9=3,$AP9=99,$CW9=2,$CW9=3),98,IF($AP9=55,55," ")) -> 98 | CY9: =IF(OR($AP9=1,$AP9=3,$AP9=99,$CW9=2,$CW9=3),"1845-01-01",IF($AP9=55,"1846-01-01"," ")) -> 1845-01-01 | CZ9: =IF(OR($AP9=1,$AP9=3,$AP9=99,$CW9=2,$CW9=3),98,IF($AP9=55,55,"230010094901")) -> 98 | DA9: =IF(OR($AP9=1,$AP9=3,$AP9=99,$CW9=2,$CW9=3),98,IF($AP9=55,55," ")) -> 98 | DB9: =IF(OR($AP9=1,$AP9=3,$AP9=99,$CW9=2,$CW9=3),98,IF($AP9=55,55," ")) -> 98 | DC9: =IF(OR($AP9=1,$AP9=3,$AP9=99,$CX9<=1,$CW9=2,$CW9=3),"1845-01-01",IF($AP9=55,"1846-01-01"," ")) -> 1845-01-01 | DD9: =IF(OR($AP9=1,$AP9=3,$AP9=99,$CX9<=1,$CW9=2,$CW9=3),98,IF($AP9=55,55," ")) -> 98 | DE9: =IF(OR($AP9=1,$AP9=3,$AP9=99,$CX9<=1,$CW9=2,$CW9=3),98,IF($AP9=55,55," ")) -> 98 | DF9: =IF(OR($AP9=1,$AP9=3,$AP9=99,$CX9<=1,$CW9=2,$CW9=3),98,IF($AP9=55,55," ")) -> 98 | DG9: =IF(OR($AP9=1,$AP9=3,$AP9=99,$CX9<=1,$CW9=2,$CW9=3),98,IF($AP9=55,55," ")) -> 98 | DH9: =IF(OR($AP9=1,$AP9=3,$AP9=99,$CW9=2,$CW9=3),98,IF($AP9=55,55," ")) -> 98 | DI9: =IF(OR($AP9=1,$AP9=3,$AP9=99),98,IF($AP9=55,55," ")) -> 98 | DJ9: =IF(OR($AP9=1,$AP9=3,$AP9=98,$DI9=98,$DI9=2,$AP9=99),98,IF($AP9=55,55," ")) -> 98 | DK9: =IF(OR($AP9=1,$AP9=3,$AP9=98,$DI9=98,$DI9=2,$AP9=99),"1845-01-01",IF($AP9=55,"1846-01-01"," ")) -> 1845-01-01 | DL9: =IF(OR($AP9=1,$AP9=3,$AP9=98,$DI9=98,$DI9=2,$AP9=99),98,IF($AP9=55,55," ")) -> 98 | DM9: =IF(OR($AP9=1,$AP9=3,$AP9=98,$DI9=98,$DI9=2,$AP9=99),98,IF($AP9=55,55," ")) -> 98 | DN9: =IF(OR($AP9=1,$AP9=3,$AP9=98,$DI9=98,$DI9=2,$AP9=99),98,IF($AP9=55,55," ")) -> 98 | DO9: =IF(OR($AP9=1,$AP9=3,$AP9=98,$DI9=98,$DI9=2,$AP9=99),98,IF($AP9=55,55,"230010094901")) -> 98 | DP9: =IF(OR($AP9=1,$AP9=3,$AP9=98,$DI9=98,$DI9=2,$AP9=99,DN9<=1),98,IF($AP9=55,55," ")) -> 98 | DQ9: =IF(OR($AP9=1,$AP9=3,$AP9=98,$DI9=98,$DI9=2,$AP9=99),"1845-01-01",IF($AP9=55,"1846-01-01"," ")) -> 1845-01-01 | DR9: =IF(OR($AP9=1,$AP9=3,$AP9=98,$DI9=98,$DI9=2,$AP9=99),98,IF($AP9=55,55," ")) -> 98 | DS9: =IF(OR($AP9=1,$AP9=3,$AP9=98,$AP9=99,$DI9=98,$DI9=2,$DR9<>2),98,IF($AP9=55,55," ")) -> 98 | DT9: =IF(OR($AP9=1,$AP9=3,$AP9=98,$AP9=99,$DI9=98,$DI9=2,),"1845-01-01",IF($AP9=55,"1846-01-01"," ")) -> 1845-01-01 | DU9: =IF(OR($AP9=1,$AP9=3,$AP9=98,$AP9=99,$DI9=98,$DI9=2,$DT9="1845-01-01"),98,IF($AP9=55,55," ")) -> 98 | DV9: =IF(OR($AP9=1,$AP9=3,$AP9=98,$AP9=99,$DI9=98,$DI9=2,$DT9="1845-01-01"),98,IF($AP9=55,55," ")) -> 98 | DW9: =IF(OR($AP9=1,$AP9=3,$AP9=98,$AP9=99,$DI9=98,$DI9=2,$DT9="1845-01-01"),98,IF($AP9=55,55," ")) -> 98 | DX9: =IF(OR($AP9=1,$AP9=3,$AP9=98,$AP9=99,$DI9=98,$DI9=2,$DT9="1845-01-01"),98,IF($AP9=55,55," ")) -> 98 | DY9: =IF(OR($AP9=1,$AP9=3,$AP9=98,$AP9=99,$DI9=98,$DI9=2,$DT9="1845-01-01"),98,IF($AP9=55,55," ")) -> 98 | DZ9: =IF(OR($AP9=1,$AP9=3,$AP9=99,$AP9=98,$DI9=98,$DI9=2,$DT9="1845-01-01"),"1845-01-01",IF($AP9=55,"1846-01-01"," ")) -> 1845-01-01 | EA9: =IF(OR($AP9=1,$AP9=3,$AP9=98,$AP9=99,$DI9=98,$DI9=2,$DT9="1845-01-01"),98,IF($AP9=55,55," ")) -> 98 | EB9: =IF(OR($AP9=1,$AP9=3,$AP9=98,$AP9=99,$DI9=98,$DI9=2,$DT9="1845-01-01",$EA9<>2),98,IF($AP9=55,55," ")) -> 98 | EC9: =IF(OR($AP9=1,$AP9=3,$AP9=99),98,IF($AP9=55,55," ")) -> 98 | ED9: =IF(OR($AP9=1,$AP9=3,$EC9=98),98,IF($AP9=55,55," ")) -> 98 | EE9: =IF(OR($AP9=1,$AP9=3,$EC9=98),98,IF($AP9=55,55," ")) -> 98 | EF9: =IF(OR($AP9=1,$AP9=3,$EC9=98),"1845-01-01",IF($AP9=55,"1846-01-01"," ")) -> 1845-01-01 | EG9: =IF(OR($AP9=1,$AP9=3,$EC9=98),98,IF($AP9=55,55,"230010094901")) -> 98 | EH9: =IF(OR($AP9=1,$AP9=3,$AP9=99),98,IF($AP9=55,55," ")) -> 98 | EI9: =IF(OR($AP9=1,$AP9=3,,$AP9=99,$EH9=98),"1845-01-01",IF($AP9=55,"1846-01-01"," ")) -> 1845-01-01 | EJ9: =IF(OR($AP9=1,$AP9=3,,$AP9=99,$EH9=98),98,IF($AP9=55,55," ")) -> 98 | EK9: =IF(OR($AP9=1,$AP9=3,$AP9=99),2,IF($AP9=55,55," ")) -> 2 | EL9: =IF(OR($AP9=1,$AP9=3,$AP9=99,$EK9=2),2,IF($AP9=55,55," ")) -> 2 | EM9: =IF(OR($AP9=1,$AP9=3,$AP9=99,$EK9=2),2,IF($AP9=55,55," ")) -> 2 | EN9: =IF(OR($AP9=1,$AP9=3,$AP9=99,$EK9=2),2,IF($AP9=55,55," ")) -> 2 | EO9: =IF(OR($AP9=1,$AP9=3,$AP9=99,$EK9=2),2,IF($AP9=55,55," ")) -> 2 | EP9: =IF(OR($AP9=1,$AP9=3,$AP9=99,$EK9=2),2,IF($AP9=55,55," ")) -> 2 | EQ9: =IF(OR($AP9=1,$AP9=3,$AP9=99,$EK9=2),2,IF($AP9=55,55," ")) -> 2 | ER9: =IF(OR($AP9=1,$AP9=3,$AP9=99,$EK9=2),"1845-01-01",IF($AP9=55,"1846-01-01"," ")) -> 1845-01-01 | ES9: =IF(OR($AP9=1,$AP9=3,$AP9=99,$EK9=2),98,IF($AP9=55,55," ")) -> 98 | ET9: =IF(OR($AP9=1,$AP9=3,$AP9=99,$EK9=2),98,IF($AP9=55,55," ")) -> 98 | EU9: =IF($AP9=55,"1846-01-01",IF(OR($ET9=2,$ET9=98),"1845-01-01"," ")) -> 1845-01-01 | EV9: =IF($AP9=55,55,IF(OR($ET9=2,$ET9=98),98," ")) -> 98 | EW9: =IF(OR($AP9=1,$AP9=3,$AP9=99),98,IF($AP9=55,55," ")) -> 98 | EX9: =IF($AP9=55,55,IF(OR($EW9=98,$EW9=2),"1845-01-01"," ")) -> 1845-01-01 | EY9: =IF($AP9=55,55,IF(OR($EW9=98,$EW9=2),98,IF($EW9<>" ","230010094901",""))) -> 98 | EZ9: =IF($AP9=55,55,IF(OR($EW9=98,$EW9=2),4," ")) -> 4 | FA9: =IF($AP9=55,55,IF(OR($AP9=1,$AP9=3),98," ")) -> 98 | FB9: =IF($AP9=55,55,IF(OR($AP9=99,$FD9=2),98,IF($AP9=1,7,IF($AP9=3,9,IF(OR($AP9=5,$AP9=6),8," "))))) -> 9 | FC9: =IF($AP9=1,5,IF($AP9=3,7,IF($AP9=99,6,IF($FB9=98,99,IF($AP9=55,55,""))))) -> 7 | FD9: =IF($AP9=55,55,IF($AP9=99,99,"")) | FE9: =IF($FD9=2,4,IF($FD9=55,14,IF(YEAR($S9)=2023,2,IF(AP9=3,0,"")))) -> 0 | FF9: =IF($AP9=1,10,IF($AP9=99,8, IF($FD9=2,12,IF($AP9=3,7,"")))) -> 7 | FH9: =IF(OR($FD9=1,$FD9=99),"1845-01-01"," ") | FI9: =IF(OR($FD9=1,$FD9=99),98," ") | FL9: =COUNTIF(R9:FI9,"<>""")-COUNTBLANK(R9:FI9) -> 143 | FM9: =+FL9/147 -> 0.97278912 | FN9: =+VLOOKUP(R9,'CIE-10'!$A$3:$C$558,3,FALSE) -> 1= CAC Mama | FT9: 1 | FU9: =SUM(FP9:FS9) -> 0
A10: Abandono confirmado | B10: MARIA | C10: AUXILIADORA | D10: DAVID | E10: JURIS | F10: CC | G10: 26043768 | H10: 12203 | I10: F | R10: C509 | S10: 37683 | T10: 37642 | U10: 37642 | V10: 10 | W10: 98 | X10: 37642 | Y10: 37642 | Z10: 230010144701 | AA10: 38738 | AB10: 4 | AC10: 99 | AD10: 18 | AE10: 38738 | AF10: 1 | AG10: 42384 | AH10: 3 | AI10: 98 | AJ10: 1845-01-01 | AK10: 98 | AL10: 98 | AM10: 98 | AN10: 1845-01-01 | AO10: 1 | AP10: 99 | AR10: =+IF(AQ10=2,"1845-01-01","") | AS10: =+IF(AQ10=2,"99","") | AT10: =IF(OR($AP10=1,$AP10=3,$AP10=99),98,"") -> 98 | AU10: =IF(AND(OR($R10="C835",$R10="C910",$R10="C920",$R10="C924",$R10="C925"),OR($AT10=98)),0,IF($AT10=55,55,IF(OR($R10="C835",$R10="C910",$R10="C920",$R10="C924",$R10="C925"),SUMIF($AV10:$BC10,1),98))) -> 98 | AV10: =IF($AT10=98,97,IF(AND(OR($R10="C835",$R10="C910",$R10="C920",$R10="C924",$R10="C925"),$AT10=98),97,"")) -> 97 | AW10: =IF($AT10=98,97,IF(AND(OR($R10="C835",$R10="C910",$R10="C920",$R10="C924",$R10="C925"),$AT10=98),97,"")) -> 97 | AX10: =IF($AT10=98,97,IF(AND(OR($R10="C835",$R10="C910",$R10="C920",$R10="C924",$R10="C925"),$AT10=98),97,"")) -> 97 | AY10: =IF($AT10=98,97,IF(AND(OR($R10="C835",$R10="C910",$R10="C920",$R10="C924",$R10="C925"),$AT10=98),97,"")) -> 97 | AZ10: =IF($AT10=98,97,IF(AND(OR($R10="C835",$R10="C910",$R10="C920",$R10="C924",$R10="C925"),$AT10=98),97,"")) -> 97 | BA10: =IF($AT10=98,97,IF(AND(OR($R10="C835",$R10="C910",$R10="C920",$R10="C924",$R10="C925"),$AT10=98),97,"")) -> 97 | BB10: =IF($AT10=98,97,IF(AND(OR($R10="C835",$R10="C910",$R10="C920",$R10="C924",$R10="C925"),$AT10=98),97,"")) -> 97 | BC10: =IF($AT10=98,97,IF(AND(OR($R10="C835",$R10="C910",$R10="C920",$R10="C924",$R10="C925"),$AT10=98),97,"")) -> 97 | BD10: =IF($AT10=98,98,"") -> 98 | BE10: =IF($AT10=98,98,"") -> 98 | BF10: =IF($AT10=98,"1845-01-01","") -> 1845-01-01 | BG10: =IF($AT10=98,98,"") -> 98 | BH10: =IF($AT10=98,98,IF(AT10=1,230010094901,"")) -> 98 | BI10: =IF(OR($AT10=98,$BG10=1),98,"") -> 98 | BJ10: =IF(OR($AT10=98),98,IF($AT10=55,55,"")) -> 98 | BK10: =IF(OR($AT10=98),98,IF($AT10=55,55,"")) -> 98 | BL10: =IF(OR($AT10=98),98,IF($AT10=55,55,"")) -> 98 | BM10: =IF(OR($AT10=98),98,IF($AT10=55,55,"")) -> 98 | BN10: =IF(OR($AT10=98),98,IF($AT10=55,55,"")) -> 98 | BO10: =IF(OR($AT10=98),98,IF($AT10=55,55,"")) -> 98 | BP10: =IF(OR($AT10=98),98,IF($AT10=55,55,"")) -> 98 | BQ10: =IF(OR($AT10=98),98,IF($AT10=55,55,"")) -> 98 | ... BW10: =IF(OR($AT10=98),98,IF($AT10=55,55,"")) -> 98 | BX10: =IF($AT10=98,"1845-01-01","") -> 1845-01-01 | BY10: =IF(OR($AT10=98),98,IF($AT10=55,55,"")) -> 98 | BZ10: =IF(OR($AT10=98,BY10<>2),98,IF($AT10=55,55,"")) -> 98 | CA10: =IF(OR($AT10=98,$AP10=1,$AP10=3,$AP10=99),98,IF($AT10=55,55," ")) -> 98 | CB10: =IF(OR($AT10=98,$CA10=97,$AP10=1,$AP10=3,$AP10=99),"1845-01-01",IF($AT10=55,"1846-01-01"," ")) -> 1845-01-01 | CC10: =IF(OR($AT10=2,$AT10=98,$CA10=97,$AP10=1,$AP10=3,$AP10=99),98,IF($AT10=55,55," ")) -> 98 | CD10: =IF(OR($AT10=2,$AT10=98,$CA10=97,$AP10=1,$AP10=3,$AP10=99),98,IF($AT10=55,55," ")) -> 98 | CE10: =IF(OR($AT10=2,$AT10=98,$CA10=97,$AP10=1,$AP10=3,$AP10=99,$CC10=1),98,IF($AT10=55,55," ")) -> 98 | CF10: =IF(OR($AT10=2,$AT10=98,$CA10=97,$AP10=1,$AP10=3,$AP10=99),98,IF($AT10=55,55,"")) -> 98 | CG10: =IF(OR($AT10=98,$CA10=97,$AP10=1,$AP10=3,$AP10=99),98,IF($AT10=55,55,"")) -> 98 | CH10: =IF(OR($AT10=2,$AT10=98,$CA10=97,$AP10=1,$AP10=3,$AP10=99),98,IF($AT10=55,55,97)) -> 98 | CI10: =IF(OR($AT10=2,$AT10=98,$CA10=97,$AP10=1,$AP10=3,$AP10=99),98,IF($AT10=55,55,97)) -> 98 | CJ10: =IF(OR($AT10=2,$AT10=98,$CA10=97,$AP10=1,$AP10=3,$AP10=99),98,IF($AT10=55,55,97)) -> 98 | CK10: =IF(OR($AT10=2,$AT10=98,$CA10=97,$AP10=1,$AP10=3,$AP10=99),98,IF($AT10=55,55,97)) -> 98 | CL10: =IF(OR($AT10=2,$AT10=98,$CA10=97,$AP10=1,$AP10=3,$AP10=99),98,IF($AT10=55,55,97)) -> 98 | CM10: =IF(OR($AT10=2,$AT10=98,$CA10=97,$AP10=1,$AP10=3,$AP10=99),98,IF($AT10=55,55,97)) -> 98 | CN10: =IF(OR($AT10=2,$AT10=98,$CA10=97,$AP10=1,$AP10=3,$AP10=99),98,IF($AT10=55,55,97)) -> 98 | CO10: =IF(OR($AT10=2,$AT10=98,$CA10=97,$AP10=1,$AP10=3,$AP10=99),98,IF($AT10=55,55,97)) -> 98 | ... CR10: =IF(OR($AT10=2,$AT10=98,$CA10=97,$AP10=1,$AP10=3,$AP10=99),98,IF($AT10=55,55,97)) -> 98 | CS10: =IF($CA10<=10,"",IF(OR($AT10=98,$AT10=2,$CA10=97,$CA10=98,$AP10=1,$AP10=3,$AP10=99),98,IF($AT10=55,55," "))) -> 98 | CT10: =IF($CA10<=10,"",IF(OR($AT10=98,$AT10=2,$CA10=97,$CA10=98,$AP10=1,$AP10=3,$AP10=99),"1845-01-01",IF($AT10=55,"1846-01-01"," "))) -> 1845-01-01 | CU10: =IF($CA10<=10,"",IF(OR($AT10=98,$AT10=2,$CA10=97,$CA10=98,$AP10=1,$AP10=3,$AP10=99),98,IF($AT10=55,55," "))) -> 98 | CV10: =IF($CA10<=10,"",IF(OR($AT10=98,$AT10=2,$CA10=97,$CA10=98,$AP10=1,$AP10=3,$AP10=99),98,IF($AT10=55,55," "))) -> 98 | CW10: =IF(OR($AP10=1,$AP10=3,$AP10=99),2,IF($AP10=55,55," ")) -> 2 | CX10: =IF(OR($AP10=1,$AP10=3,$AP10=99,$CW10=2,$CW10=3),98,IF($AP10=55,55," ")) -> 98 | CY10: =IF(OR($AP10=1,$AP10=3,$AP10=99,$CW10=2,$CW10=3),"1845-01-01",IF($AP10=55,"1846-01-01"," ")) -> 1845-01-01 | CZ10: =IF(OR($AP10=1,$AP10=3,$AP10=99,$CW10=2,$CW10=3),98,IF($AP10=55,55,"230010094901")) -> 98 | DA10: =IF(OR($AP10=1,$AP10=3,$AP10=99,$CW10=2,$CW10=3),98,IF($AP10=55,55," ")) -> 98 | DB10: =IF(OR($AP10=1,$AP10=3,$AP10=99,$CW10=2,$CW10=3),98,IF($AP10=55,55," ")) -> 98 | DC10: =IF(OR($AP10=1,$AP10=3,$AP10=99,$CX10<=1,$CW10=2,$CW10=3),"1845-01-01",IF($AP10=55,"1846-01-01"," ")) -> 1845-01-01 | DD10: =IF(OR($AP10=1,$AP10=3,$AP10=99,$CX10<=1,$CW10=2,$CW10=3),98,IF($AP10=55,55," ")) -> 98 | DE10: =IF(OR($AP10=1,$AP10=3,$AP10=99,$CX10<=1,$CW10=2,$CW10=3),98,IF($AP10=55,55," ")) -> 98 | DF10: =IF(OR($AP10=1,$AP10=3,$AP10=99,$CX10<=1,$CW10=2,$CW10=3),98,IF($AP10=55,55," ")) -> 98 | DG10: =IF(OR($AP10=1,$AP10=3,$AP10=99,$CX10<=1,$CW10=2,$CW10=3),98,IF($AP10=55,55," ")) -> 98 | DH10: =IF(OR($AP10=1,$AP10=3,$AP10=99,$CW10=2,$CW10=3),98,IF($AP10=55,55," ")) -> 98 | DI10: =IF(OR($AP10=1,$AP10=3,$AP10=99),98,IF($AP10=55,55," ")) -> 98 | DJ10: =IF(OR($AP10=1,$AP10=3,$AP10=98,$DI10=98,$DI10=2,$AP10=99),98,IF($AP10=55,55," ")) -> 98 | DK10: =IF(OR($AP10=1,$AP10=3,$AP10=98,$DI10=98,$DI10=2,$AP10=99),"1845-01-01",IF($AP10=55,"1846-01-01"," ")) -> 1845-01-01 | DL10: =IF(OR($AP10=1,$AP10=3,$AP10=98,$DI10=98,$DI10=2,$AP10=99),98,IF($AP10=55,55," ")) -> 98 | DM10: =IF(OR($AP10=1,$AP10=3,$AP10=98,$DI10=98,$DI10=2,$AP10=99),98,IF($AP10=55,55," ")) -> 98 | DN10: =IF(OR($AP10=1,$AP10=3,$AP10=98,$DI10=98,$DI10=2,$AP10=99),98,IF($AP10=55,55," ")) -> 98 | DO10: =IF(OR($AP10=1,$AP10=3,$AP10=98,$DI10=98,$DI10=2,$AP10=99),98,IF($AP10=55,55,"230010094901")) -> 98 | DP10: =IF(OR($AP10=1,$AP10=3,$AP10=98,$DI10=98,$DI10=2,$AP10=99,DN10<=1),98,IF($AP10=55,55," ")) -> 98 | DQ10: =IF(OR($AP10=1,$AP10=3,$AP10=98,$DI10=98,$DI10=2,$AP10=99),"1845-01-01",IF($AP10=55,"1846-01-01"," ")) -> 1845-01-01 | DR10: =IF(OR($AP10=1,$AP10=3,$AP10=98,$DI10=98,$DI10=2,$AP10=99),98,IF($AP10=55,55," ")) -> 98 | DS10: =IF(OR($AP10=1,$AP10=3,$AP10=98,$AP10=99,$DI10=98,$DI10=2,$DR10<>2),98,IF($AP10=55,55," ")) -> 98 | DT10: =IF(OR($AP10=1,$AP10=3,$AP10=98,$AP10=99,$DI10=98,$DI10=2,),"1845-01-01",IF($AP10=55,"1846-01-01"," ")) -> 1845-01-01 | DU10: =IF(OR($AP10=1,$AP10=3,$AP10=98,$AP10=99,$DI10=98,$DI10=2,$DT10="1845-01-01"),98,IF($AP10=55,55," ")) -> 98 | DV10: =IF(OR($AP10=1,$AP10=3,$AP10=98,$AP10=99,$DI10=98,$DI10=2,$DT10="1845-01-01"),98,IF($AP10=55,55," ")) -> 98 | DW10: =IF(OR($AP10=1,$AP10=3,$AP10=98,$AP10=99,$DI10=98,$DI10=2,$DT10="1845-01-01"),98,IF($AP10=55,55," ")) -> 98 | DX10: =IF(OR($AP10=1,$AP10=3,$AP10=98,$AP10=99,$DI10=98,$DI10=2,$DT10="1845-01-01"),98,IF($AP10=55,55," ")) -> 98 | DY10: =IF(OR($AP10=1,$AP10=3,$AP10=98,$AP10=99,$DI10=98,$DI10=2,$DT10="1845-01-01"),98,IF($AP10=55,55," ")) -> 98 | DZ10: =IF(OR($AP10=1,$AP10=3,$AP10=99,$AP10=98,$DI10=98,$DI10=2,$DT10="1845-01-01"),"1845-01-01",IF($AP10=55,"1846-01-01"," ")) -> 1845-01-01 | EA10: =IF(OR($AP10=1,$AP10=3,$AP10=98,$AP10=99,$DI10=98,$DI10=2,$DT10="1845-01-01"),98,IF($AP10=55,55," ")) -> 98 | EB10: =IF(OR($AP10=1,$AP10=3,$AP10=98,$AP10=99,$DI10=98,$DI10=2,$DT10="1845-01-01",$EA10<>2),98,IF($AP10=55,55," ")) -> 98 | EC10: =IF(OR($AP10=1,$AP10=3,$AP10=99),98,IF($AP10=55,55," ")) -> 98 | ED10: =IF(OR($AP10=1,$AP10=3,$EC10=98),98,IF($AP10=55,55," ")) -> 98 | EE10: =IF(OR($AP10=1,$AP10=3,$EC10=98),98,IF($AP10=55,55," ")) -> 98 | EF10: =IF(OR($AP10=1,$AP10=3,$EC10=98),"1845-01-01",IF($AP10=55,"1846-01-01"," ")) -> 1845-01-01 | EG10: =IF(OR($AP10=1,$AP10=3,$EC10=98),98,IF($AP10=55,55,"230010094901")) -> 98 | EH10: =IF(OR($AP10=1,$AP10=3,$AP10=99),98,IF($AP10=55,55," ")) -> 98 | EI10: =IF(OR($AP10=1,$AP10=3,,$AP10=99,$EH10=98),"1845-01-01",IF($AP10=55,"1846-01-01"," ")) -> 1845-01-01 | EJ10: =IF(OR($AP10=1,$AP10=3,,$AP10=99,$EH10=98),98,IF($AP10=55,55," ")) -> 98 | EK10: =IF(OR($AP10=1,$AP10=3,$AP10=99),2,IF($AP10=55,55," ")) -> 2 | EL10: =IF(OR($AP10=1,$AP10=3,$AP10=99,$EK10=2),2,IF($AP10=55,55," ")) -> 2 | EM10: =IF(OR($AP10=1,$AP10=3,$AP10=99,$EK10=2),2,IF($AP10=55,55," ")) -> 2 | EN10: =IF(OR($AP10=1,$AP10=3,$AP10=99,$EK10=2),2,IF($AP10=55,55," ")) -> 2 | EO10: =IF(OR($AP10=1,$AP10=3,$AP10=99,$EK10=2),2,IF($AP10=55,55," ")) -> 2 | EP10: =IF(OR($AP10=1,$AP10=3,$AP10=99,$EK10=2),2,IF($AP10=55,55," ")) -> 2 | EQ10: =IF(OR($AP10=1,$AP10=3,$AP10=99,$EK10=2),2,IF($AP10=55,55," ")) -> 2 | ER10: =IF(OR($AP10=1,$AP10=3,$AP10=99,$EK10=2),"1845-01-01",IF($AP10=55,"1846-01-01"," ")) -> 1845-01-01 | ES10: =IF(OR($AP10=1,$AP10=3,$AP10=99,$EK10=2),98,IF($AP10=55,55," ")) -> 98 | ET10: =IF(OR($AP10=1,$AP10=3,$AP10=99,$EK10=2),98,IF($AP10=55,55," ")) -> 98 | EU10: =IF($AP10=55,"1846-01-01",IF(OR($ET10=2,$ET10=98),"1845-01-01"," ")) -> 1845-01-01 | EV10: =IF($AP10=55,55,IF(OR($ET10=2,$ET10=98),98," ")) -> 98 | EW10: =IF(OR($AP10=1,$AP10=3,$AP10=99),98,IF($AP10=55,55," ")) -> 98 | EX10: =IF($AP10=55,55,IF(OR($EW10=98,$EW10=2),"1845-01-01"," ")) -> 1845-01-01 | EY10: =IF($AP10=55,55,IF(OR($EW10=98,$EW10=2),98,IF($EW10<>" ","230010094901",""))) -> 98 | EZ10: =IF($AP10=55,55,IF(OR($EW10=98,$EW10=2),4," ")) -> 4 | FA10: =IF($AP10=55,55,IF(OR($AP10=1,$AP10=3),98," ")) | FB10: =IF($AP10=55,55,IF(OR($AP10=99,$FD10=2),98,IF($AP10=1,7,IF($AP10=3,9,IF(OR($AP10=5,$AP10=6),8," "))))) -> 98 | FC10: =IF($AP10=1,5,IF($AP10=3,7,IF($AP10=99,6,IF($FB10=98,99,IF($AP10=55,55,""))))) -> 6 | FD10: =IF($AP10=55,55,IF($AP10=99,99,"")) -> 99 | FE10: =IF($FD10=2,4,IF($FD10=55,14,IF(YEAR($S10)=2023,2,IF(AP10=3,0,"")))) | FF10: =IF($AP10=1,10,IF($AP10=99,8, IF($FD10=2,12,IF($AP10=3,7,"")))) -> 8 | FH10: =IF(OR($FD10=1,$FD10=99),"1845-01-01"," ") -> 1845-01-01 | FI10: =IF(OR($FD10=1,$FD10=99),98," ") -> 98 | FL10: =COUNTIF(R10:FI10,"<>""")-COUNTBLANK(R10:FI10) -> 143 | FM10: =+FL10/147 -> 0.97278912 | FN10: =+VLOOKUP(R10,'CIE-10'!$A$3:$C$558,3,FALSE) -> 1= CAC Mama | FU10: =SUM(FP10:FS10) -> 0
A11: Posible segumiento | B11: EMPERATRIZ | C11: DEL SOCORRO | D11: OVIEDO | E11: ACEVEDO | F11: CC | G11: 25844985 | H11: 21028 | I11: F | R11: C443 | S11: 37787 | T11: 37787 | U11: 1800-01-01 | V11: 10 | W11: 98 | X11: 37778 | Y11: 37786 | Z11: 230010144701 | AA11: 1800-01-01 | AB11: 20 | AC11: 99 | AD11: 2 | AE11: 37787 | AF11: 98 | AG11: 1845-01-01 | AH11: 98 | AI11: 98 | AJ11: 1845-01-01 | AK11: 98 | AL11: 98 | AM11: 98 | AN11: 1845-01-01 | AO11: 1 | AP11: 3 | AR11: =+IF(AQ11=2,"1845-01-01","") | AS11: =+IF(AQ11=2,"99","") | AT11: =IF(OR($AP11=1,$AP11=3,$AP11=99),98,"") -> 98 | AU11: =IF(AND(OR($R11="C835",$R11="C910",$R11="C920",$R11="C924",$R11="C925"),OR($AT11=98)),0,IF($AT11=55,55,IF(OR($R11="C835",$R11="C910",$R11="C920",$R11="C924",$R11="C925"),SUMIF($AV11:$BC11,1),98))) -> 98 | AV11: =IF($AT11=98,97,IF(AND(OR($R11="C835",$R11="C910",$R11="C920",$R11="C924",$R11="C925"),$AT11=98),97,"")) -> 97 | AW11: =IF($AT11=98,97,IF(AND(OR($R11="C835",$R11="C910",$R11="C920",$R11="C924",$R11="C925"),$AT11=98),97,"")) -> 97 | AX11: =IF($AT11=98,97,IF(AND(OR($R11="C835",$R11="C910",$R11="C920",$R11="C924",$R11="C925"),$AT11=98),97,"")) -> 97 | AY11: =IF($AT11=98,97,IF(AND(OR($R11="C835",$R11="C910",$R11="C920",$R11="C924",$R11="C925"),$AT11=98),97,"")) -> 97 | AZ11: =IF($AT11=98,97,IF(AND(OR($R11="C835",$R11="C910",$R11="C920",$R11="C924",$R11="C925"),$AT11=98),97,"")) -> 97 | BA11: =IF($AT11=98,97,IF(AND(OR($R11="C835",$R11="C910",$R11="C920",$R11="C924",$R11="C925"),$AT11=98),97,"")) -> 97 | BB11: =IF($AT11=98,97,IF(AND(OR($R11="C835",$R11="C910",$R11="C920",$R11="C924",$R11="C925"),$AT11=98),97,"")) -> 97 | BC11: =IF($AT11=98,97,IF(AND(OR($R11="C835",$R11="C910",$R11="C920",$R11="C924",$R11="C925"),$AT11=98),97,"")) -> 97 | BD11: =IF($AT11=98,98,"") -> 98 | BE11: =IF($AT11=98,98,"") -> 98 | BF11: =IF($AT11=98,"1845-01-01","") -> 1845-01-01 | BG11: =IF($AT11=98,98,"") -> 98 | BH11: =IF($AT11=98,98,IF(AT11=1,230010094901,"")) -> 98 | BI11: =IF(OR($AT11=98,$BG11=1),98,"") -> 98 | BJ11: =IF(OR($AT11=98),98,IF($AT11=55,55,"")) -> 98 | BK11: =IF(OR($AT11=98),98,IF($AT11=55,55,"")) -> 98 | BL11: =IF(OR($AT11=98),98,IF($AT11=55,55,"")) -> 98 | BM11: =IF(OR($AT11=98),98,IF($AT11=55,55,"")) -> 98 | BN11: =IF(OR($AT11=98),98,IF($AT11=55,55,"")) -> 98 | BO11: =IF(OR($AT11=98),98,IF($AT11=55,55,"")) -> 98 | BP11: =IF(OR($AT11=98),98,IF($AT11=55,55,"")) -> 98 | BQ11: =IF(OR($AT11=98),98,IF($AT11=55,55,"")) -> 98 | ... BW11: =IF(OR($AT11=98),98,IF($AT11=55,55,"")) -> 98 | BX11: =IF($AT11=98,"1845-01-01","") -> 1845-01-01 | BY11: =IF(OR($AT11=98),98,IF($AT11=55,55,"")) -> 98 | BZ11: =IF(OR($AT11=98,BY11<>2),98,IF($AT11=55,55,"")) -> 98 | CA11: =IF(OR($AT11=98,$AP11=1,$AP11=3,$AP11=99),98,IF($AT11=55,55," ")) -> 98 | CB11: =IF(OR($AT11=98,$CA11=97,$AP11=1,$AP11=3,$AP11=99),"1845-01-01",IF($AT11=55,"1846-01-01"," ")) -> 1845-01-01 | CC11: =IF(OR($AT11=2,$AT11=98,$CA11=97,$AP11=1,$AP11=3,$AP11=99),98,IF($AT11=55,55," ")) -> 98 | CD11: =IF(OR($AT11=2,$AT11=98,$CA11=97,$AP11=1,$AP11=3,$AP11=99),98,IF($AT11=55,55," ")) -> 98 | CE11: =IF(OR($AT11=2,$AT11=98,$CA11=97,$AP11=1,$AP11=3,$AP11=99,$CC11=1),98,IF($AT11=55,55," ")) -> 98 | CF11: =IF(OR($AT11=2,$AT11=98,$CA11=97,$AP11=1,$AP11=3,$AP11=99),98,IF($AT11=55,55,"")) -> 98 | CG11: =IF(OR($AT11=98,$CA11=97,$AP11=1,$AP11=3,$AP11=99),98,IF($AT11=55,55,"")) -> 98 | CH11: =IF(OR($AT11=2,$AT11=98,$CA11=97,$AP11=1,$AP11=3,$AP11=99),98,IF($AT11=55,55,97)) -> 98 | CI11: =IF(OR($AT11=2,$AT11=98,$CA11=97,$AP11=1,$AP11=3,$AP11=99),98,IF($AT11=55,55,97)) -> 98 | CJ11: =IF(OR($AT11=2,$AT11=98,$CA11=97,$AP11=1,$AP11=3,$AP11=99),98,IF($AT11=55,55,97)) -> 98 | CK11: =IF(OR($AT11=2,$AT11=98,$CA11=97,$AP11=1,$AP11=3,$AP11=99),98,IF($AT11=55,55,97)) -> 98 | CL11: =IF(OR($AT11=2,$AT11=98,$CA11=97,$AP11=1,$AP11=3,$AP11=99),98,IF($AT11=55,55,97)) -> 98 | CM11: =IF(OR($AT11=2,$AT11=98,$CA11=97,$AP11=1,$AP11=3,$AP11=99),98,IF($AT11=55,55,97)) -> 98 | CN11: =IF(OR($AT11=2,$AT11=98,$CA11=97,$AP11=1,$AP11=3,$AP11=99),98,IF($AT11=55,55,97)) -> 98 | CO11: =IF(OR($AT11=2,$AT11=98,$CA11=97,$AP11=1,$AP11=3,$AP11=99),98,IF($AT11=55,55,97)) -> 98 | ... CR11: =IF(OR($AT11=2,$AT11=98,$CA11=97,$AP11=1,$AP11=3,$AP11=99),98,IF($AT11=55,55,97)) -> 98 | CS11: =IF($CA11<=10,"",IF(OR($AT11=98,$AT11=2,$CA11=97,$CA11=98,$AP11=1,$AP11=3,$AP11=99),98,IF($AT11=55,55," "))) -> 98 | CT11: =IF($CA11<=10,"",IF(OR($AT11=98,$AT11=2,$CA11=97,$CA11=98,$AP11=1,$AP11=3,$AP11=99),"1845-01-01",IF($AT11=55,"1846-01-01"," "))) -> 1845-01-01 | CU11: =IF($CA11<=10,"",IF(OR($AT11=98,$AT11=2,$CA11=97,$CA11=98,$AP11=1,$AP11=3,$AP11=99),98,IF($AT11=55,55," "))) -> 98 | CV11: =IF($CA11<=10,"",IF(OR($AT11=98,$AT11=2,$CA11=97,$CA11=98,$AP11=1,$AP11=3,$AP11=99),98,IF($AT11=55,55," "))) -> 98 | CW11: =IF(OR($AP11=1,$AP11=3,$AP11=99),2,IF($AP11=55,55," ")) -> 2 | CX11: =IF(OR($AP11=1,$AP11=3,$AP11=99,$CW11=2,$CW11=3),98,IF($AP11=55,55," ")) -> 98 | CY11: =IF(OR($AP11=1,$AP11=3,$AP11=99,$CW11=2,$CW11=3),"1845-01-01",IF($AP11=55,"1846-01-01"," ")) -> 1845-01-01 | CZ11: =IF(OR($AP11=1,$AP11=3,$AP11=99,$CW11=2,$CW11=3),98,IF($AP11=55,55,"230010094901")) -> 98 | DA11: =IF(OR($AP11=1,$AP11=3,$AP11=99,$CW11=2,$CW11=3),98,IF($AP11=55,55," ")) -> 98 | DB11: =IF(OR($AP11=1,$AP11=3,$AP11=99,$CW11=2,$CW11=3),98,IF($AP11=55,55," ")) -> 98 | DC11: =IF(OR($AP11=1,$AP11=3,$AP11=99,$CX11<=1,$CW11=2,$CW11=3),"1845-01-01",IF($AP11=55,"1846-01-01"," ")) -> 1845-01-01 | DD11: =IF(OR($AP11=1,$AP11=3,$AP11=99,$CX11<=1,$CW11=2,$CW11=3),98,IF($AP11=55,55," ")) -> 98 | DE11: =IF(OR($AP11=1,$AP11=3,$AP11=99,$CX11<=1,$CW11=2,$CW11=3),98,IF($AP11=55,55," ")) -> 98 | DF11: =IF(OR($AP11=1,$AP11=3,$AP11=99,$CX11<=1,$CW11=2,$CW11=3),98,IF($AP11=55,55," ")) -> 98 | DG11: =IF(OR($AP11=1,$AP11=3,$AP11=99,$CX11<=1,$CW11=2,$CW11=3),98,IF($AP11=55,55," ")) -> 98 | DH11: =IF(OR($AP11=1,$AP11=3,$AP11=99,$CW11=2,$CW11=3),98,IF($AP11=55,55," ")) -> 98 | DI11: =IF(OR($AP11=1,$AP11=3,$AP11=99),98,IF($AP11=55,55," ")) -> 98 | DJ11: =IF(OR($AP11=1,$AP11=3,$AP11=98,$DI11=98,$DI11=2,$AP11=99),98,IF($AP11=55,55," ")) -> 98 | DK11: =IF(OR($AP11=1,$AP11=3,$AP11=98,$DI11=98,$DI11=2,$AP11=99),"1845-01-01",IF($AP11=55,"1846-01-01"," ")) -> 1845-01-01 | DL11: =IF(OR($AP11=1,$AP11=3,$AP11=98,$DI11=98,$DI11=2,$AP11=99),98,IF($AP11=55,55," ")) -> 98 | DM11: =IF(OR($AP11=1,$AP11=3,$AP11=98,$DI11=98,$DI11=2,$AP11=99),98,IF($AP11=55,55," ")) -> 98 | DN11: =IF(OR($AP11=1,$AP11=3,$AP11=98,$DI11=98,$DI11=2,$AP11=99),98,IF($AP11=55,55," ")) -> 98 | DO11: =IF(OR($AP11=1,$AP11=3,$AP11=98,$DI11=98,$DI11=2,$AP11=99),98,IF($AP11=55,55,"230010094901")) -> 98 | DP11: =IF(OR($AP11=1,$AP11=3,$AP11=98,$DI11=98,$DI11=2,$AP11=99,DN11<=1),98,IF($AP11=55,55," ")) -> 98 | DQ11: =IF(OR($AP11=1,$AP11=3,$AP11=98,$DI11=98,$DI11=2,$AP11=99),"1845-01-01",IF($AP11=55,"1846-01-01"," ")) -> 1845-01-01 | DR11: =IF(OR($AP11=1,$AP11=3,$AP11=98,$DI11=98,$DI11=2,$AP11=99),98,IF($AP11=55,55," ")) -> 98 | DS11: =IF(OR($AP11=1,$AP11=3,$AP11=98,$AP11=99,$DI11=98,$DI11=2,$DR11<>2),98,IF($AP11=55,55," ")) -> 98 | DT11: =IF(OR($AP11=1,$AP11=3,$AP11=98,$AP11=99,$DI11=98,$DI11=2,),"1845-01-01",IF($AP11=55,"1846-01-01"," ")) -> 1845-01-01 | DU11: =IF(OR($AP11=1,$AP11=3,$AP11=98,$AP11=99,$DI11=98,$DI11=2,$DT11="1845-01-01"),98,IF($AP11=55,55," ")) -> 98 | DV11: =IF(OR($AP11=1,$AP11=3,$AP11=98,$AP11=99,$DI11=98,$DI11=2,$DT11="1845-01-01"),98,IF($AP11=55,55," ")) -> 98 | DW11: =IF(OR($AP11=1,$AP11=3,$AP11=98,$AP11=99,$DI11=98,$DI11=2,$DT11="1845-01-01"),98,IF($AP11=55,55," ")) -> 98 | DX11: =IF(OR($AP11=1,$AP11=3,$AP11=98,$AP11=99,$DI11=98,$DI11=2,$DT11="1845-01-01"),98,IF($AP11=55,55," ")) -> 98 | DY11: =IF(OR($AP11=1,$AP11=3,$AP11=98,$AP11=99,$DI11=98,$DI11=2,$DT11="1845-01-01"),98,IF($AP11=55,55," ")) -> 98 | DZ11: =IF(OR($AP11=1,$AP11=3,$AP11=99,$AP11=98,$DI11=98,$DI11=2,$DT11="1845-01-01"),"1845-01-01",IF($AP11=55,"1846-01-01"," ")) -> 1845-01-01 | EA11: =IF(OR($AP11=1,$AP11=3,$AP11=98,$AP11=99,$DI11=98,$DI11=2,$DT11="1845-01-01"),98,IF($AP11=55,55," ")) -> 98 | EB11: =IF(OR($AP11=1,$AP11=3,$AP11=98,$AP11=99,$DI11=98,$DI11=2,$DT11="1845-01-01",$EA11<>2),98,IF($AP11=55,55," ")) -> 98 | EC11: =IF(OR($AP11=1,$AP11=3,$AP11=99),98,IF($AP11=55,55," ")) -> 98 | ED11: =IF(OR($AP11=1,$AP11=3,$EC11=98),98,IF($AP11=55,55," ")) -> 98 | EE11: =IF(OR($AP11=1,$AP11=3,$EC11=98),98,IF($AP11=55,55," ")) -> 98 | EF11: =IF(OR($AP11=1,$AP11=3,$EC11=98),"1845-01-01",IF($AP11=55,"1846-01-01"," ")) -> 1845-01-01 | EG11: =IF(OR($AP11=1,$AP11=3,$EC11=98),98,IF($AP11=55,55,"230010094901")) -> 98 | EH11: =IF(OR($AP11=1,$AP11=3,$AP11=99),98,IF($AP11=55,55," ")) -> 98 | EI11: =IF(OR($AP11=1,$AP11=3,,$AP11=99,$EH11=98),"1845-01-01",IF($AP11=55,"1846-01-01"," ")) -> 1845-01-01 | EJ11: =IF(OR($AP11=1,$AP11=3,,$AP11=99,$EH11=98),98,IF($AP11=55,55," ")) -> 98 | EK11: =IF(OR($AP11=1,$AP11=3,$AP11=99),2,IF($AP11=55,55," ")) -> 2 | EL11: =IF(OR($AP11=1,$AP11=3,$AP11=99,$EK11=2),2,IF($AP11=55,55," ")) -> 2 | EM11: =IF(OR($AP11=1,$AP11=3,$AP11=99,$EK11=2),2,IF($AP11=55,55," ")) -> 2 | EN11: =IF(OR($AP11=1,$AP11=3,$AP11=99,$EK11=2),2,IF($AP11=55,55," ")) -> 2 | EO11: =IF(OR($AP11=1,$AP11=3,$AP11=99,$EK11=2),2,IF($AP11=55,55," ")) -> 2 | EP11: =IF(OR($AP11=1,$AP11=3,$AP11=99,$EK11=2),2,IF($AP11=55,55," ")) -> 2 | EQ11: =IF(OR($AP11=1,$AP11=3,$AP11=99,$EK11=2),2,IF($AP11=55,55," ")) -> 2 | ER11: =IF(OR($AP11=1,$AP11=3,$AP11=99,$EK11=2),"1845-01-01",IF($AP11=55,"1846-01-01"," ")) -> 1845-01-01 | ES11: =IF(OR($AP11=1,$AP11=3,$AP11=99,$EK11=2),98,IF($AP11=55,55," ")) -> 98 | ET11: =IF(OR($AP11=1,$AP11=3,$AP11=99,$EK11=2),98,IF($AP11=55,55," ")) -> 98 | EU11: =IF($AP11=55,"1846-01-01",IF(OR($ET11=2,$ET11=98),"1845-01-01"," ")) -> 1845-01-01 | EV11: =IF($AP11=55,55,IF(OR($ET11=2,$ET11=98),98," ")) -> 98 | EW11: =IF(OR($AP11=1,$AP11=3,$AP11=99),98,IF($AP11=55,55," ")) -> 98 | EX11: =IF($AP11=55,55,IF(OR($EW11=98,$EW11=2),"1845-01-01"," ")) -> 1845-01-01 | EY11: =IF($AP11=55,55,IF(OR($EW11=98,$EW11=2),98,IF($EW11<>" ","230010094901",""))) -> 98 | EZ11: =IF($AP11=55,55,IF(OR($EW11=98,$EW11=2),4," ")) -> 4 | FA11: =IF($AP11=55,55,IF(OR($AP11=1,$AP11=3),98," ")) -> 98 | FB11: =IF($AP11=55,55,IF(OR($AP11=99,$FD11=2),98,IF($AP11=1,7,IF($AP11=3,9,IF(OR($AP11=5,$AP11=6),8," "))))) -> 9 | FC11: =IF($AP11=1,5,IF($AP11=3,7,IF($AP11=99,6,IF($FB11=98,99,IF($AP11=55,55,""))))) -> 7 | FD11: =IF($AP11=55,55,IF($AP11=99,99,"")) | FE11: =IF($FD11=2,4,IF($FD11=55,14,IF(YEAR($S11)=2023,2,IF(AP11=3,0,"")))) -> 0 | FF11: =IF($AP11=1,10,IF($AP11=99,8, IF($FD11=2,12,IF($AP11=3,7,"")))) -> 7 | FH11: =IF(OR($FD11=1,$FD11=99),"1845-01-01"," ") | FI11: =IF(OR($FD11=1,$FD11=99),98," ") | FL11: =COUNTIF(R11:FI11,"<>""")-COUNTBLANK(R11:FI11) -> 143 | FM11: =+FL11/147 -> 0.97278912 | FN11: =+VLOOKUP(R11,'CIE-10'!$A$3:$C$558,3,FALSE) -> 16= Otros tumores de la piel | FT11: 1 | FU11: =SUM(FP11:FS11) -> 0
A12: Revisar sí es abandono o segumiento | B12: JULIA | C12: ROSA | D12: OROZCO | E12: GOMEZ | F12: CC | G12: 34967471 | H12: 20261 | I12: F | R12: C509 | S12: 37897 | T12: 37889 | U12: 37897 | V12: 10 | W12: 98 | X12: 37889 | Y12: 37897 | Z12: 230010144701 | AA12: 38008 | AB12: 4 | AC12: 99 | AD12: 18 | AE12: 38890 | AF12: 1 | AG12: 38890 | AH12: 1 | AI12: 98 | AJ12: 1845-01-01 | AK12: 98 | AL12: 98 | AM12: 98 | AN12: 1845-01-01 | AO12: 1 | AR12: =+IF(AQ12=2,"1845-01-01","") | AS12: =+IF(AQ12=2,"99","") | AT12: =IF(OR($AP12=1,$AP12=3,$AP12=99),98,"") | AU12: =IF(AND(OR($R12="C835",$R12="C910",$R12="C920",$R12="C924",$R12="C925"),OR($AT12=98)),0,IF($AT12=55,55,IF(OR($R12="C835",$R12="C910",$R12="C920",$R12="C924",$R12="C925"),SUMIF($AV12:$BC12,1),98))) -> 98 | AV12: =IF($AT12=98,97,IF(AND(OR($R12="C835",$R12="C910",$R12="C920",$R12="C924",$R12="C925"),$AT12=98),97,"")) | AW12: =IF($AT12=98,97,IF(AND(OR($R12="C835",$R12="C910",$R12="C920",$R12="C924",$R12="C925"),$AT12=98),97,"")) | AX12: =IF($AT12=98,97,IF(AND(OR($R12="C835",$R12="C910",$R12="C920",$R12="C924",$R12="C925"),$AT12=98),97,"")) | AY12: =IF($AT12=98,97,IF(AND(OR($R12="C835",$R12="C910",$R12="C920",$R12="C924",$R12="C925"),$AT12=98),97,"")) | AZ12: =IF($AT12=98,97,IF(AND(OR($R12="C835",$R12="C910",$R12="C920",$R12="C924",$R12="C925"),$AT12=98),97,"")) | BA12: =IF($AT12=98,97,IF(AND(OR($R12="C835",$R12="C910",$R12="C920",$R12="C924",$R12="C925"),$AT12=98),97,"")) | BB12: =IF($AT12=98,97,IF(AND(OR($R12="C835",$R12="C910",$R12="C920",$R12="C924",$R12="C925"),$AT12=98),97,"")) | BC12: =IF($AT12=98,97,IF(AND(OR($R12="C835",$R12="C910",$R12="C920",$R12="C924",$R12="C925"),$AT12=98),97,"")) | BD12: =IF($AT12=98,98,"") | BE12: =IF($AT12=98,98,"") | BF12: =IF($AT12=98,"1845-01-01","") | BG12: =IF($AT12=98,98,"") | BH12: =IF($AT12=98,98,IF(AT12=1,230010094901,"")) | BI12: =IF(OR($AT12=98,$BG12=1),98,"") | BJ12: =IF(OR($AT12=98),98,IF($AT12=55,55,"")) | BK12: =IF(OR($AT12=98),98,IF($AT12=55,55,"")) | BL12: =IF(OR($AT12=98),98,IF($AT12=55,55,"")) | BM12: =IF(OR($AT12=98),98,IF($AT12=55,55,"")) | BN12: =IF(OR($AT12=98),98,IF($AT12=55,55,"")) | BO12: =IF(OR($AT12=98),98,IF($AT12=55,55,"")) | BP12: =IF(OR($AT12=98),98,IF($AT12=55,55,"")) | BQ12: =IF(OR($AT12=98),98,IF($AT12=55,55,"")) | ... BW12: =IF(OR($AT12=98),98,IF($AT12=55,55,"")) | BX12: =IF($AT12=98,"1845-01-01","") | BY12: =IF(OR($AT12=98),98,IF($AT12=55,55,"")) | BZ12: =IF(OR($AT12=98,BY12<>2),98,IF($AT12=55,55,"")) -> 98 | CA12: =IF(OR($AT12=98,$AP12=1,$AP12=3,$AP12=99),98,IF($AT12=55,55," ")) | CB12: =IF(OR($AT12=98,$CA12=97,$AP12=1,$AP12=3,$AP12=99),"1845-01-01",IF($AT12=55,"1846-01-01"," ")) | CC12: =IF(OR($AT12=2,$AT12=98,$CA12=97,$AP12=1,$AP12=3,$AP12=99),98,IF($AT12=55,55," ")) | CD12: =IF(OR($AT12=2,$AT12=98,$CA12=97,$AP12=1,$AP12=3,$AP12=99),98,IF($AT12=55,55," ")) | CE12: =IF(OR($AT12=2,$AT12=98,$CA12=97,$AP12=1,$AP12=3,$AP12=99,$CC12=1),98,IF($AT12=55,55," ")) | CF12: =IF(OR($AT12=2,$AT12=98,$CA12=97,$AP12=1,$AP12=3,$AP12=99),98,IF($AT12=55,55,"")) | CG12: =IF(OR($AT12=98,$CA12=97,$AP12=1,$AP12=3,$AP12=99),98,IF($AT12=55,55,"")) | CH12: =IF(OR($AT12=2,$AT12=98,$CA12=97,$AP12=1,$AP12=3,$AP12=99),98,IF($AT12=55,55,97)) -> 97 | CI12: =IF(OR($AT12=2,$AT12=98,$CA12=97,$AP12=1,$AP12=3,$AP12=99),98,IF($AT12=55,55,97)) -> 97 | CJ12: =IF(OR($AT12=2,$AT12=98,$CA12=97,$AP12=1,$AP12=3,$AP12=99),98,IF($AT12=55,55,97)) -> 97 | CK12: =IF(OR($AT12=2,$AT12=98,$CA12=97,$AP12=1,$AP12=3,$AP12=99),98,IF($AT12=55,55,97)) -> 97 | CL12: =IF(OR($AT12=2,$AT12=98,$CA12=97,$AP12=1,$AP12=3,$AP12=99),98,IF($AT12=55,55,97)) -> 97 | CM12: =IF(OR($AT12=2,$AT12=98,$CA12=97,$AP12=1,$AP12=3,$AP12=99),98,IF($AT12=55,55,97)) -> 97 | CN12: =IF(OR($AT12=2,$AT12=98,$CA12=97,$AP12=1,$AP12=3,$AP12=99),98,IF($AT12=55,55,97)) -> 97 | CO12: =IF(OR($AT12=2,$AT12=98,$CA12=97,$AP12=1,$AP12=3,$AP12=99),98,IF($AT12=55,55,97)) -> 97 | ... CR12: =IF(OR($AT12=2,$AT12=98,$CA12=97,$AP12=1,$AP12=3,$AP12=99),98,IF($AT12=55,55,97)) -> 97 | CS12: =IF($CA12<=10,"",IF(OR($AT12=98,$AT12=2,$CA12=97,$CA12=98,$AP12=1,$AP12=3,$AP12=99),98,IF($AT12=55,55," "))) | CT12: =IF($CA12<=10,"",IF(OR($AT12=98,$AT12=2,$CA12=97,$CA12=98,$AP12=1,$AP12=3,$AP12=99),"1845-01-01",IF($AT12=55,"1846-01-01"," "))) | CU12: =IF($CA12<=10,"",IF(OR($AT12=98,$AT12=2,$CA12=97,$CA12=98,$AP12=1,$AP12=3,$AP12=99),98,IF($AT12=55,55," "))) | CV12: =IF($CA12<=10,"",IF(OR($AT12=98,$AT12=2,$CA12=97,$CA12=98,$AP12=1,$AP12=3,$AP12=99),98,IF($AT12=55,55," "))) | CW12: =IF(OR($AP12=1,$AP12=3,$AP12=99),2,IF($AP12=55,55," ")) | CX12: =IF(OR($AP12=1,$AP12=3,$AP12=99,$CW12=2,$CW12=3),98,IF($AP12=55,55," ")) | CY12: =IF(OR($AP12=1,$AP12=3,$AP12=99,$CW12=2,$CW12=3),"1845-01-01",IF($AP12=55,"1846-01-01"," ")) | CZ12: =IF(OR($AP12=1,$AP12=3,$AP12=99,$CW12=2,$CW12=3),98,IF($AP12=55,55,"230010094901")) -> 230010094901 | DA12: =IF(OR($AP12=1,$AP12=3,$AP12=99,$CW12=2,$CW12=3),98,IF($AP12=55,55," ")) | DB12: =IF(OR($AP12=1,$AP12=3,$AP12=99,$CW12=2,$CW12=3),98,IF($AP12=55,55," ")) | DC12: =IF(OR($AP12=1,$AP12=3,$AP12=99,$CX12<=1,$CW12=2,$CW12=3),"1845-01-01",IF($AP12=55,"1846-01-01"," ")) | DD12: =IF(OR($AP12=1,$AP12=3,$AP12=99,$CX12<=1,$CW12=2,$CW12=3),98,IF($AP12=55,55," ")) | DE12: =IF(OR($AP12=1,$AP12=3,$AP12=99,$CX12<=1,$CW12=2,$CW12=3),98,IF($AP12=55,55," ")) | DF12: =IF(OR($AP12=1,$AP12=3,$AP12=99,$CX12<=1,$CW12=2,$CW12=3),98,IF($AP12=55,55," ")) | DG12: =IF(OR($AP12=1,$AP12=3,$AP12=99,$CX12<=1,$CW12=2,$CW12=3),98,IF($AP12=55,55," ")) | DH12: =IF(OR($AP12=1,$AP12=3,$AP12=99,$CW12=2,$CW12=3),98,IF($AP12=55,55," ")) | DI12: =IF(OR($AP12=1,$AP12=3,$AP12=99),98,IF($AP12=55,55," ")) | DJ12: =IF(OR($AP12=1,$AP12=3,$AP12=98,$DI12=98,$DI12=2,$AP12=99),98,IF($AP12=55,55," ")) | DK12: =IF(OR($AP12=1,$AP12=3,$AP12=98,$DI12=98,$DI12=2,$AP12=99),"1845-01-01",IF($AP12=55,"1846-01-01"," ")) | DL12: =IF(OR($AP12=1,$AP12=3,$AP12=98,$DI12=98,$DI12=2,$AP12=99),98,IF($AP12=55,55," ")) | DM12: =IF(OR($AP12=1,$AP12=3,$AP12=98,$DI12=98,$DI12=2,$AP12=99),98,IF($AP12=55,55," ")) | DN12: =IF(OR($AP12=1,$AP12=3,$AP12=98,$DI12=98,$DI12=2,$AP12=99),98,IF($AP12=55,55," ")) | DO12: =IF(OR($AP12=1,$AP12=3,$AP12=98,$DI12=98,$DI12=2,$AP12=99),98,IF($AP12=55,55,"230010094901")) -> 230010094901 | DP12: =IF(OR($AP12=1,$AP12=3,$AP12=98,$DI12=98,$DI12=2,$AP12=99,DN12<=1),98,IF($AP12=55,55," ")) | DQ12: =IF(OR($AP12=1,$AP12=3,$AP12=98,$DI12=98,$DI12=2,$AP12=99),"1845-01-01",IF($AP12=55,"1846-01-01"," ")) | DR12: =IF(OR($AP12=1,$AP12=3,$AP12=98,$DI12=98,$DI12=2,$AP12=99),98,IF($AP12=55,55," ")) | DS12: =IF(OR($AP12=1,$AP12=3,$AP12=98,$AP12=99,$DI12=98,$DI12=2,$DR12<>2),98,IF($AP12=55,55," ")) -> 98 | DT12: =IF(OR($AP12=1,$AP12=3,$AP12=98,$AP12=99,$DI12=98,$DI12=2,),"1845-01-01",IF($AP12=55,"1846-01-01"," ")) | DU12: =IF(OR($AP12=1,$AP12=3,$AP12=98,$AP12=99,$DI12=98,$DI12=2,$DT12="1845-01-01"),98,IF($AP12=55,55," ")) | DV12: =IF(OR($AP12=1,$AP12=3,$AP12=98,$AP12=99,$DI12=98,$DI12=2,$DT12="1845-01-01"),98,IF($AP12=55,55," ")) | DW12: =IF(OR($AP12=1,$AP12=3,$AP12=98,$AP12=99,$DI12=98,$DI12=2,$DT12="1845-01-01"),98,IF($AP12=55,55," ")) | DX12: =IF(OR($AP12=1,$AP12=3,$AP12=98,$AP12=99,$DI12=98,$DI12=2,$DT12="1845-01-01"),98,IF($AP12=55,55," ")) | DY12: =IF(OR($AP12=1,$AP12=3,$AP12=98,$AP12=99,$DI12=98,$DI12=2,$DT12="1845-01-01"),98,IF($AP12=55,55," ")) | DZ12: =IF(OR($AP12=1,$AP12=3,$AP12=99,$AP12=98,$DI12=98,$DI12=2,$DT12="1845-01-01"),"1845-01-01",IF($AP12=55,"1846-01-01"," ")) | EA12: =IF(OR($AP12=1,$AP12=3,$AP12=98,$AP12=99,$DI12=98,$DI12=2,$DT12="1845-01-01"),98,IF($AP12=55,55," ")) | EB12: =IF(OR($AP12=1,$AP12=3,$AP12=98,$AP12=99,$DI12=98,$DI12=2,$DT12="1845-01-01",$EA12<>2),98,IF($AP12=55,55," ")) -> 98 | EC12: =IF(OR($AP12=1,$AP12=3,$AP12=99),98,IF($AP12=55,55," ")) | ED12: =IF(OR($AP12=1,$AP12=3,$EC12=98),98,IF($AP12=55,55," ")) | EE12: =IF(OR($AP12=1,$AP12=3,$EC12=98),98,IF($AP12=55,55," ")) | EF12: =IF(OR($AP12=1,$AP12=3,$EC12=98),"1845-01-01",IF($AP12=55,"1846-01-01"," ")) | EG12: =IF(OR($AP12=1,$AP12=3,$EC12=98),98,IF($AP12=55,55,"230010094901")) -> 230010094901 | EH12: =IF(OR($AP12=1,$AP12=3,$AP12=99),98,IF($AP12=55,55," ")) | EI12: =IF(OR($AP12=1,$AP12=3,,$AP12=99,$EH12=98),"1845-01-01",IF($AP12=55,"1846-01-01"," ")) | EJ12: =IF(OR($AP12=1,$AP12=3,,$AP12=99,$EH12=98),98,IF($AP12=55,55," ")) | EK12: =IF(OR($AP12=1,$AP12=3,$AP12=99),2,IF($AP12=55,55," ")) | EL12: =IF(OR($AP12=1,$AP12=3,$AP12=99,$EK12=2),2,IF($AP12=55,55," ")) | EM12: =IF(OR($AP12=1,$AP12=3,$AP12=99,$EK12=2),2,IF($AP12=55,55," ")) | EN12: =IF(OR($AP12=1,$AP12=3,$AP12=99,$EK12=2),2,IF($AP12=55,55," ")) | EO12: =IF(OR($AP12=1,$AP12=3,$AP12=99,$EK12=2),2,IF($AP12=55,55," ")) | EP12: =IF(OR($AP12=1,$AP12=3,$AP12=99,$EK12=2),2,IF($AP12=55,55," ")) | EQ12: =IF(OR($AP12=1,$AP12=3,$AP12=99,$EK12=2),2,IF($AP12=55,55," ")) | ER12: =IF(OR($AP12=1,$AP12=3,$AP12=99,$EK12=2),"1845-01-01",IF($AP12=55,"1846-01-01"," ")) | ES12: =IF(OR($AP12=1,$AP12=3,$AP12=99,$EK12=2),98,IF($AP12=55,55," ")) | ET12: =IF(OR($AP12=1,$AP12=3,$AP12=99,$EK12=2),98,IF($AP12=55,55," ")) | EU12: =IF($AP12=55,"1846-01-01",IF(OR($ET12=2,$ET12=98),"1845-01-01"," ")) | EV12: =IF($AP12=55,55,IF(OR($ET12=2,$ET12=98),98," ")) | EW12: =IF(OR($AP12=1,$AP12=3,$AP12=99),98,IF($AP12=55,55," ")) | EX12: =IF($AP12=55,55,IF(OR($EW12=98,$EW12=2),"1845-01-01"," ")) | EY12: =IF($AP12=55,55,IF(OR($EW12=98,$EW12=2),98,IF($EW12<>" ","230010094901",""))) | EZ12: =IF($AP12=55,55,IF(OR($EW12=98,$EW12=2),4," ")) | FA12: =IF($AP12=55,55,IF(OR($AP12=1,$AP12=3),98," ")) | FB12: =IF($AP12=55,55,IF(OR($AP12=99,$FD12=2),98,IF($AP12=1,7,IF($AP12=3,9,IF(OR($AP12=5,$AP12=6),8," "))))) | FC12: =IF($AP12=1,5,IF($AP12=3,7,IF($AP12=99,6,IF($FB12=98,99,IF($AP12=55,55,""))))) | FD12: =IF($AP12=55,55,IF($AP12=99,99,"")) | FE12: =IF($FD12=2,4,IF($FD12=55,14,IF(YEAR($S12)=2023,2,IF(AP12=3,0,"")))) | FF12: =IF($AP12=1,10,IF($AP12=99,8, IF($FD12=2,12,IF($AP12=3,7,"")))) | FH12: =IF(OR($FD12=1,$FD12=99),"1845-01-01"," ") | FI12: =IF(OR($FD12=1,$FD12=99),98," ") | FL12: =COUNTIF(R12:FI12,"<>""")-COUNTBLANK(R12:FI12) -> 105 | FM12: =+FL12/147 -> 0.71428571 | FN12: =+VLOOKUP(R12,'CIE-10'!$A$3:$C$558,3,FALSE) -> 1= CAC Mama | FU12: =SUM(FP12:FS12) -> 0
A13: Posible segumiento | B13: OLGA | C13: LUCIA | D13: MADRONERO | E13: CERON | F13: CC | G13: 25913302 | H13: 25148 | I13: F | R13: C820 | S13: 37898 | T13: 36144 | U13: 37898 | V13: 10 | W13: 98 | X13: 37898 | Y13: 37898 | Z13: 230010144701 | AA13: 1800-01-01 | AB13: 20 | AC13: 95 | AD13: 98 | AE13: 36144 | AF13: 98 | AG13: 1845-01-01 | AH13: 98 | AI13: 98 | AJ13: 1845-01-01 | AK13: 1 | AL13: 98 | AM13: 1 | AN13: 1800-01-01 | AO13: 1 | AP13: 3 | AR13: =+IF(AQ13=2,"1845-01-01","") | AS13: =+IF(AQ13=2,"99","") | AT13: =IF(OR($AP13=1,$AP13=3,$AP13=99),98,"") -> 98 | AU13: =IF(AND(OR($R13="C835",$R13="C910",$R13="C920",$R13="C924",$R13="C925"),OR($AT13=98)),0,IF($AT13=55,55,IF(OR($R13="C835",$R13="C910",$R13="C920",$R13="C924",$R13="C925"),SUMIF($AV13:$BC13,1),98))) -> 98 | AV13: =IF($AT13=98,97,IF(AND(OR($R13="C835",$R13="C910",$R13="C920",$R13="C924",$R13="C925"),$AT13=98),97,"")) -> 97 | AW13: =IF($AT13=98,97,IF(AND(OR($R13="C835",$R13="C910",$R13="C920",$R13="C924",$R13="C925"),$AT13=98),97,"")) -> 97 | AX13: =IF($AT13=98,97,IF(AND(OR($R13="C835",$R13="C910",$R13="C920",$R13="C924",$R13="C925"),$AT13=98),97,"")) -> 97 | AY13: =IF($AT13=98,97,IF(AND(OR($R13="C835",$R13="C910",$R13="C920",$R13="C924",$R13="C925"),$AT13=98),97,"")) -> 97 | AZ13: =IF($AT13=98,97,IF(AND(OR($R13="C835",$R13="C910",$R13="C920",$R13="C924",$R13="C925"),$AT13=98),97,"")) -> 97 | BA13: =IF($AT13=98,97,IF(AND(OR($R13="C835",$R13="C910",$R13="C920",$R13="C924",$R13="C925"),$AT13=98),97,"")) -> 97 | BB13: =IF($AT13=98,97,IF(AND(OR($R13="C835",$R13="C910",$R13="C920",$R13="C924",$R13="C925"),$AT13=98),97,"")) -> 97 | BC13: =IF($AT13=98,97,IF(AND(OR($R13="C835",$R13="C910",$R13="C920",$R13="C924",$R13="C925"),$AT13=98),97,"")) -> 97 | BD13: =IF($AT13=98,98,"") -> 98 | BE13: =IF($AT13=98,98,"") -> 98 | BF13: =IF($AT13=98,"1845-01-01","") -> 1845-01-01 | BG13: =IF($AT13=98,98,"") -> 98 | BH13: =IF($AT13=98,98,IF(AT13=1,230010094901,"")) -> 98 | BI13: =IF(OR($AT13=98,$BG13=1),98,"") -> 98 | BJ13: =IF(OR($AT13=98),98,IF($AT13=55,55,"")) -> 98 | BK13: =IF(OR($AT13=98),98,IF($AT13=55,55,"")) -> 98 | BL13: =IF(OR($AT13=98),98,IF($AT13=55,55,"")) -> 98 | BM13: =IF(OR($AT13=98),98,IF($AT13=55,55,"")) -> 98 | BN13: =IF(OR($AT13=98),98,IF($AT13=55,55,"")) -> 98 | BO13: =IF(OR($AT13=98),98,IF($AT13=55,55,"")) -> 98 | BP13: =IF(OR($AT13=98),98,IF($AT13=55,55,"")) -> 98 | BQ13: =IF(OR($AT13=98),98,IF($AT13=55,55,"")) -> 98 | ... BW13: =IF(OR($AT13=98),98,IF($AT13=55,55,"")) -> 98 | BX13: =IF($AT13=98,"1845-01-01","") -> 1845-01-01 | BY13: =IF(OR($AT13=98),98,IF($AT13=55,55,"")) -> 98 | BZ13: =IF(OR($AT13=98,BY13<>2),98,IF($AT13=55,55,"")) -> 98 | CA13: =IF(OR($AT13=98,$AP13=1,$AP13=3,$AP13=99),98,IF($AT13=55,55," ")) -> 98 | CB13: =IF(OR($AT13=98,$CA13=97,$AP13=1,$AP13=3,$AP13=99),"1845-01-01",IF($AT13=55,"1846-01-01"," ")) -> 1845-01-01 | CC13: =IF(OR($AT13=2,$AT13=98,$CA13=97,$AP13=1,$AP13=3,$AP13=99),98,IF($AT13=55,55," ")) -> 98 | CD13: =IF(OR($AT13=2,$AT13=98,$CA13=97,$AP13=1,$AP13=3,$AP13=99),98,IF($AT13=55,55," ")) -> 98 | CE13: =IF(OR($AT13=2,$AT13=98,$CA13=97,$AP13=1,$AP13=3,$AP13=99,$CC13=1),98,IF($AT13=55,55," ")) -> 98 | CF13: =IF(OR($AT13=2,$AT13=98,$CA13=97,$AP13=1,$AP13=3,$AP13=99),98,IF($AT13=55,55,"")) -> 98 | CG13: =IF(OR($AT13=98,$CA13=97,$AP13=1,$AP13=3,$AP13=99),98,IF($AT13=55,55,"")) -> 98 | CH13: =IF(OR($AT13=2,$AT13=98,$CA13=97,$AP13=1,$AP13=3,$AP13=99),98,IF($AT13=55,55,97)) -> 98 | CI13: =IF(OR($AT13=2,$AT13=98,$CA13=97,$AP13=1,$AP13=3,$AP13=99),98,IF($AT13=55,55,97)) -> 98 | CJ13: =IF(OR($AT13=2,$AT13=98,$CA13=97,$AP13=1,$AP13=3,$AP13=99),98,IF($AT13=55,55,97)) -> 98 | CK13: =IF(OR($AT13=2,$AT13=98,$CA13=97,$AP13=1,$AP13=3,$AP13=99),98,IF($AT13=55,55,97)) -> 98 | CL13: =IF(OR($AT13=2,$AT13=98,$CA13=97,$AP13=1,$AP13=3,$AP13=99),98,IF($AT13=55,55,97)) -> 98 | CM13: =IF(OR($AT13=2,$AT13=98,$CA13=97,$AP13=1,$AP13=3,$AP13=99),98,IF($AT13=55,55,97)) -> 98 | CN13: =IF(OR($AT13=2,$AT13=98,$CA13=97,$AP13=1,$AP13=3,$AP13=99),98,IF($AT13=55,55,97)) -> 98 | CO13: =IF(OR($AT13=2,$AT13=98,$CA13=97,$AP13=1,$AP13=3,$AP13=99),98,IF($AT13=55,55,97)) -> 98 | ... CR13: =IF(OR($AT13=2,$AT13=98,$CA13=97,$AP13=1,$AP13=3,$AP13=99),98,IF($AT13=55,55,97)) -> 98 | CS13: =IF($CA13<=10,"",IF(OR($AT13=98,$AT13=2,$CA13=97,$CA13=98,$AP13=1,$AP13=3,$AP13=99),98,IF($AT13=55,55," "))) -> 98 | CT13: =IF($CA13<=10,"",IF(OR($AT13=98,$AT13=2,$CA13=97,$CA13=98,$AP13=1,$AP13=3,$AP13=99),"1845-01-01",IF($AT13=55,"1846-01-01"," "))) -> 1845-01-01 | CU13: =IF($CA13<=10,"",IF(OR($AT13=98,$AT13=2,$CA13=97,$CA13=98,$AP13=1,$AP13=3,$AP13=99),98,IF($AT13=55,55," "))) -> 98 | CV13: =IF($CA13<=10,"",IF(OR($AT13=98,$AT13=2,$CA13=97,$CA13=98,$AP13=1,$AP13=3,$AP13=99),98,IF($AT13=55,55," "))) -> 98 | CW13: =IF(OR($AP13=1,$AP13=3,$AP13=99),2,IF($AP13=55,55," ")) -> 2 | CX13: =IF(OR($AP13=1,$AP13=3,$AP13=99,$CW13=2,$CW13=3),98,IF($AP13=55,55," ")) -> 98 | CY13: =IF(OR($AP13=1,$AP13=3,$AP13=99,$CW13=2,$CW13=3),"1845-01-01",IF($AP13=55,"1846-01-01"," ")) -> 1845-01-01 | CZ13: =IF(OR($AP13=1,$AP13=3,$AP13=99,$CW13=2,$CW13=3),98,IF($AP13=55,55,"230010094901")) -> 98 | DA13: =IF(OR($AP13=1,$AP13=3,$AP13=99,$CW13=2,$CW13=3),98,IF($AP13=55,55," ")) -> 98 | DB13: =IF(OR($AP13=1,$AP13=3,$AP13=99,$CW13=2,$CW13=3),98,IF($AP13=55,55," ")) -> 98 | DC13: =IF(OR($AP13=1,$AP13=3,$AP13=99,$CX13<=1,$CW13=2,$CW13=3),"1845-01-01",IF($AP13=55,"1846-01-01"," ")) -> 1845-01-01 | DD13: =IF(OR($AP13=1,$AP13=3,$AP13=99,$CX13<=1,$CW13=2,$CW13=3),98,IF($AP13=55,55," ")) -> 98 | DE13: =IF(OR($AP13=1,$AP13=3,$AP13=99,$CX13<=1,$CW13=2,$CW13=3),98,IF($AP13=55,55," ")) -> 98 | DF13: =IF(OR($AP13=1,$AP13=3,$AP13=99,$CX13<=1,$CW13=2,$CW13=3),98,IF($AP13=55,55," ")) -> 98 | DG13: =IF(OR($AP13=1,$AP13=3,$AP13=99,$CX13<=1,$CW13=2,$CW13=3),98,IF($AP13=55,55," ")) -> 98 | DH13: =IF(OR($AP13=1,$AP13=3,$AP13=99,$CW13=2,$CW13=3),98,IF($AP13=55,55," ")) -> 98 | DI13: =IF(OR($AP13=1,$AP13=3,$AP13=99),98,IF($AP13=55,55," ")) -> 98 | DJ13: =IF(OR($AP13=1,$AP13=3,$AP13=98,$DI13=98,$DI13=2,$AP13=99),98,IF($AP13=55,55," ")) -> 98 | DK13: =IF(OR($AP13=1,$AP13=3,$AP13=98,$DI13=98,$DI13=2,$AP13=99),"1845-01-01",IF($AP13=55,"1846-01-01"," ")) -> 1845-01-01 | DL13: =IF(OR($AP13=1,$AP13=3,$AP13=98,$DI13=98,$DI13=2,$AP13=99),98,IF($AP13=55,55," ")) -> 98 | DM13: =IF(OR($AP13=1,$AP13=3,$AP13=98,$DI13=98,$DI13=2,$AP13=99),98,IF($AP13=55,55," ")) -> 98 | DN13: =IF(OR($AP13=1,$AP13=3,$AP13=98,$DI13=98,$DI13=2,$AP13=99),98,IF($AP13=55,55," ")) -> 98 | DO13: =IF(OR($AP13=1,$AP13=3,$AP13=98,$DI13=98,$DI13=2,$AP13=99),98,IF($AP13=55,55,"230010094901")) -> 98 | DP13: =IF(OR($AP13=1,$AP13=3,$AP13=98,$DI13=98,$DI13=2,$AP13=99,DN13<=1),98,IF($AP13=55,55," ")) -> 98 | DQ13: =IF(OR($AP13=1,$AP13=3,$AP13=98,$DI13=98,$DI13=2,$AP13=99),"1845-01-01",IF($AP13=55,"1846-01-01"," ")) -> 1845-01-01 | DR13: =IF(OR($AP13=1,$AP13=3,$AP13=98,$DI13=98,$DI13=2,$AP13=99),98,IF($AP13=55,55," ")) -> 98 | DS13: =IF(OR($AP13=1,$AP13=3,$AP13=98,$AP13=99,$DI13=98,$DI13=2,$DR13<>2),98,IF($AP13=55,55," ")) -> 98 | DT13: =IF(OR($AP13=1,$AP13=3,$AP13=98,$AP13=99,$DI13=98,$DI13=2,),"1845-01-01",IF($AP13=55,"1846-01-01"," ")) -> 1845-01-01 | DU13: =IF(OR($AP13=1,$AP13=3,$AP13=98,$AP13=99,$DI13=98,$DI13=2,$DT13="1845-01-01"),98,IF($AP13=55,55," ")) -> 98 | DV13: =IF(OR($AP13=1,$AP13=3,$AP13=98,$AP13=99,$DI13=98,$DI13=2,$DT13="1845-01-01"),98,IF($AP13=55,55," ")) -> 98 | DW13: =IF(OR($AP13=1,$AP13=3,$AP13=98,$AP13=99,$DI13=98,$DI13=2,$DT13="1845-01-01"),98,IF($AP13=55,55," ")) -> 98 | DX13: =IF(OR($AP13=1,$AP13=3,$AP13=98,$AP13=99,$DI13=98,$DI13=2,$DT13="1845-01-01"),98,IF($AP13=55,55," ")) -> 98 | DY13: =IF(OR($AP13=1,$AP13=3,$AP13=98,$AP13=99,$DI13=98,$DI13=2,$DT13="1845-01-01"),98,IF($AP13=55,55," ")) -> 98 | DZ13: =IF(OR($AP13=1,$AP13=3,$AP13=99,$AP13=98,$DI13=98,$DI13=2,$DT13="1845-01-01"),"1845-01-01",IF($AP13=55,"1846-01-01"," ")) -> 1845-01-01 | EA13: =IF(OR($AP13=1,$AP13=3,$AP13=98,$AP13=99,$DI13=98,$DI13=2,$DT13="1845-01-01"),98,IF($AP13=55,55," ")) -> 98 | EB13: =IF(OR($AP13=1,$AP13=3,$AP13=98,$AP13=99,$DI13=98,$DI13=2,$DT13="1845-01-01",$EA13<>2),98,IF($AP13=55,55," ")) -> 98 | EC13: =IF(OR($AP13=1,$AP13=3,$AP13=99),98,IF($AP13=55,55," ")) -> 98 | ED13: =IF(OR($AP13=1,$AP13=3,$EC13=98),98,IF($AP13=55,55," ")) -> 98 | EE13: =IF(OR($AP13=1,$AP13=3,$EC13=98),98,IF($AP13=55,55," ")) -> 98 | EF13: =IF(OR($AP13=1,$AP13=3,$EC13=98),"1845-01-01",IF($AP13=55,"1846-01-01"," ")) -> 1845-01-01 | EG13: =IF(OR($AP13=1,$AP13=3,$EC13=98),98,IF($AP13=55,55,"230010094901")) -> 98 | EH13: =IF(OR($AP13=1,$AP13=3,$AP13=99),98,IF($AP13=55,55," ")) -> 98 | EI13: =IF(OR($AP13=1,$AP13=3,,$AP13=99,$EH13=98),"1845-01-01",IF($AP13=55,"1846-01-01"," ")) -> 1845-01-01 | EJ13: =IF(OR($AP13=1,$AP13=3,,$AP13=99,$EH13=98),98,IF($AP13=55,55," ")) -> 98 | EK13: =IF(OR($AP13=1,$AP13=3,$AP13=99),2,IF($AP13=55,55," ")) -> 2 | EL13: =IF(OR($AP13=1,$AP13=3,$AP13=99,$EK13=2),2,IF($AP13=55,55," ")) -> 2 | EM13: =IF(OR($AP13=1,$AP13=3,$AP13=99,$EK13=2),2,IF($AP13=55,55," ")) -> 2 | EN13: =IF(OR($AP13=1,$AP13=3,$AP13=99,$EK13=2),2,IF($AP13=55,55," ")) -> 2 | EO13: =IF(OR($AP13=1,$AP13=3,$AP13=99,$EK13=2),2,IF($AP13=55,55," ")) -> 2 | EP13: =IF(OR($AP13=1,$AP13=3,$AP13=99,$EK13=2),2,IF($AP13=55,55," ")) -> 2 | EQ13: =IF(OR($AP13=1,$AP13=3,$AP13=99,$EK13=2),2,IF($AP13=55,55," ")) -> 2 | ER13: =IF(OR($AP13=1,$AP13=3,$AP13=99,$EK13=2),"1845-01-01",IF($AP13=55,"1846-01-01"," ")) -> 1845-01-01 | ES13: =IF(OR($AP13=1,$AP13=3,$AP13=99,$EK13=2),98,IF($AP13=55,55," ")) -> 98 | ET13: =IF(OR($AP13=1,$AP13=3,$AP13=99,$EK13=2),98,IF($AP13=55,55," ")) -> 98 | EU13: =IF($AP13=55,"1846-01-01",IF(OR($ET13=2,$ET13=98),"1845-01-01"," ")) -> 1845-01-01 | EV13: =IF($AP13=55,55,IF(OR($ET13=2,$ET13=98),98," ")) -> 98 | EW13: =IF(OR($AP13=1,$AP13=3,$AP13=99),98,IF($AP13=55,55," ")) -> 98 | EX13: =IF($AP13=55,55,IF(OR($EW13=98,$EW13=2),"1845-01-01"," ")) -> 1845-01-01 | EY13: =IF($AP13=55,55,IF(OR($EW13=98,$EW13=2),98,IF($EW13<>" ","230010094901",""))) -> 98 | EZ13: =IF($AP13=55,55,IF(OR($EW13=98,$EW13=2),4," ")) -> 4 | FA13: =IF($AP13=55,55,IF(OR($AP13=1,$AP13=3),98," ")) -> 98 | FB13: =IF($AP13=55,55,IF(OR($AP13=99,$FD13=2),98,IF($AP13=1,7,IF($AP13=3,9,IF(OR($AP13=5,$AP13=6),8," "))))) -> 9 | FC13: =IF($AP13=1,5,IF($AP13=3,7,IF($AP13=99,6,IF($FB13=98,99,IF($AP13=55,55,""))))) -> 7 | FD13: =IF($AP13=55,55,IF($AP13=99,99,"")) | FE13: =IF($FD13=2,4,IF($FD13=55,14,IF(YEAR($S13)=2023,2,IF(AP13=3,0,"")))) -> 0 | FF13: =IF($AP13=1,10,IF($AP13=99,8, IF($FD13=2,12,IF($AP13=3,7,"")))) -> 7 | FH13: =IF(OR($FD13=1,$FD13=99),"1845-01-01"," ") | FI13: =IF(OR($FD13=1,$FD13=99),98," ") | FL13: =COUNTIF(R13:FI13,"<>""")-COUNTBLANK(R13:FI13) -> 143 | FM13: =+FL13/147 -> 0.97278912 | FN13: =+VLOOKUP(R13,'CIE-10'!$A$3:$C$558,3,FALSE) -> 9= CAC Linfoma No Hodgkin | FT13: 1 | FU13: =SUM(FP13:FS13) -> 0
A14: Abandono confirmado | B14: OTONIEL | C14: VINICIO | D14: MARTINEZ | E14: PETRO | F14: CC | G14: 7376942 | H14: 22715 | I14: M | R14: C323 | S14: 37914 | T14: 37914 | U14: 37914 | V14: 10 | W14: 98 | X14: 37914 | Y14: 37914 | Z14: 230010144701 | AA14: 38338 | AB14: 1 | AC14: 2 | AD14: 11 | AE14: 38338 | AF14: 98 | AG14: 1845-01-01 | AH14: 98 | AI14: 98 | AJ14: 1845-01-01 | AK14: 98 | AL14: 98 | AM14: 98 | AN14: 1845-01-01 | AO14: 1 | AP14: 99 | AR14: =+IF(AQ14=2,"1845-01-01","") | AS14: =+IF(AQ14=2,"99","") | AT14: =IF(OR($AP14=1,$AP14=3,$AP14=99),98,"") -> 98 | AU14: =IF(AND(OR($R14="C835",$R14="C910",$R14="C920",$R14="C924",$R14="C925"),OR($AT14=98)),0,IF($AT14=55,55,IF(OR($R14="C835",$R14="C910",$R14="C920",$R14="C924",$R14="C925"),SUMIF($AV14:$BC14,1),98))) -> 98 | AV14: =IF($AT14=98,97,IF(AND(OR($R14="C835",$R14="C910",$R14="C920",$R14="C924",$R14="C925"),$AT14=98),97,"")) -> 97 | AW14: =IF($AT14=98,97,IF(AND(OR($R14="C835",$R14="C910",$R14="C920",$R14="C924",$R14="C925"),$AT14=98),97,"")) -> 97 | AX14: =IF($AT14=98,97,IF(AND(OR($R14="C835",$R14="C910",$R14="C920",$R14="C924",$R14="C925"),$AT14=98),97,"")) -> 97 | AY14: =IF($AT14=98,97,IF(AND(OR($R14="C835",$R14="C910",$R14="C920",$R14="C924",$R14="C925"),$AT14=98),97,"")) -> 97 | AZ14: =IF($AT14=98,97,IF(AND(OR($R14="C835",$R14="C910",$R14="C920",$R14="C924",$R14="C925"),$AT14=98),97,"")) -> 97 | BA14: =IF($AT14=98,97,IF(AND(OR($R14="C835",$R14="C910",$R14="C920",$R14="C924",$R14="C925"),$AT14=98),97,"")) -> 97 | BB14: =IF($AT14=98,97,IF(AND(OR($R14="C835",$R14="C910",$R14="C920",$R14="C924",$R14="C925"),$AT14=98),97,"")) -> 97 | BC14: =IF($AT14=98,97,IF(AND(OR($R14="C835",$R14="C910",$R14="C920",$R14="C924",$R14="C925"),$AT14=98),97,"")) -> 97 | BD14: =IF($AT14=98,98,"") -> 98 | BE14: =IF($AT14=98,98,"") -> 98 | BF14: =IF($AT14=98,"1845-01-01","") -> 1845-01-01 | BG14: =IF($AT14=98,98,"") -> 98 | BH14: =IF($AT14=98,98,IF(AT14=1,230010094901,"")) -> 98 | BI14: =IF(OR($AT14=98,$BG14=1),98,"") -> 98 | BJ14: =IF(OR($AT14=98),98,IF($AT14=55,55,"")) -> 98 | BK14: =IF(OR($AT14=98),98,IF($AT14=55,55,"")) -> 98 | BL14: =IF(OR($AT14=98),98,IF($AT14=55,55,"")) -> 98 | BM14: =IF(OR($AT14=98),98,IF($AT14=55,55,"")) -> 98 | BN14: =IF(OR($AT14=98),98,IF($AT14=55,55,"")) -> 98 | BO14: =IF(OR($AT14=98),98,IF($AT14=55,55,"")) -> 98 | BP14: =IF(OR($AT14=98),98,IF($AT14=55,55,"")) -> 98 | BQ14: =IF(OR($AT14=98),98,IF($AT14=55,55,"")) -> 98 | ... BW14: =IF(OR($AT14=98),98,IF($AT14=55,55,"")) -> 98 | BX14: =IF($AT14=98,"1845-01-01","") -> 1845-01-01 | BY14: =IF(OR($AT14=98),98,IF($AT14=55,55,"")) -> 98 | BZ14: =IF(OR($AT14=98,BY14<>2),98,IF($AT14=55,55,"")) -> 98 | CA14: =IF(OR($AT14=98,$AP14=1,$AP14=3,$AP14=99),98,IF($AT14=55,55," ")) -> 98 | CB14: =IF(OR($AT14=98,$CA14=97,$AP14=1,$AP14=3,$AP14=99),"1845-01-01",IF($AT14=55,"1846-01-01"," ")) -> 1845-01-01 | CC14: =IF(OR($AT14=2,$AT14=98,$CA14=97,$AP14=1,$AP14=3,$AP14=99),98,IF($AT14=55,55," ")) -> 98 | CD14: =IF(OR($AT14=2,$AT14=98,$CA14=97,$AP14=1,$AP14=3,$AP14=99),98,IF($AT14=55,55," ")) -> 98 | CE14: =IF(OR($AT14=2,$AT14=98,$CA14=97,$AP14=1,$AP14=3,$AP14=99,$CC14=1),98,IF($AT14=55,55," ")) -> 98 | CF14: =IF(OR($AT14=2,$AT14=98,$CA14=97,$AP14=1,$AP14=3,$AP14=99),98,IF($AT14=55,55,"")) -> 98 | CG14: =IF(OR($AT14=98,$CA14=97,$AP14=1,$AP14=3,$AP14=99),98,IF($AT14=55,55,"")) -> 98 | CH14: =IF(OR($AT14=2,$AT14=98,$CA14=97,$AP14=1,$AP14=3,$AP14=99),98,IF($AT14=55,55,97)) -> 98 | CI14: =IF(OR($AT14=2,$AT14=98,$CA14=97,$AP14=1,$AP14=3,$AP14=99),98,IF($AT14=55,55,97)) -> 98 | CJ14: =IF(OR($AT14=2,$AT14=98,$CA14=97,$AP14=1,$AP14=3,$AP14=99),98,IF($AT14=55,55,97)) -> 98 | CK14: =IF(OR($AT14=2,$AT14=98,$CA14=97,$AP14=1,$AP14=3,$AP14=99),98,IF($AT14=55,55,97)) -> 98 | CL14: =IF(OR($AT14=2,$AT14=98,$CA14=97,$AP14=1,$AP14=3,$AP14=99),98,IF($AT14=55,55,97)) -> 98 | CM14: =IF(OR($AT14=2,$AT14=98,$CA14=97,$AP14=1,$AP14=3,$AP14=99),98,IF($AT14=55,55,97)) -> 98 | CN14: =IF(OR($AT14=2,$AT14=98,$CA14=97,$AP14=1,$AP14=3,$AP14=99),98,IF($AT14=55,55,97)) -> 98 | CO14: =IF(OR($AT14=2,$AT14=98,$CA14=97,$AP14=1,$AP14=3,$AP14=99),98,IF($AT14=55,55,97)) -> 98 | ... CR14: =IF(OR($AT14=2,$AT14=98,$CA14=97,$AP14=1,$AP14=3,$AP14=99),98,IF($AT14=55,55,97)) -> 98 | CS14: =IF($CA14<=10,"",IF(OR($AT14=98,$AT14=2,$CA14=97,$CA14=98,$AP14=1,$AP14=3,$AP14=99),98,IF($AT14=55,55," "))) -> 98 | CT14: =IF($CA14<=10,"",IF(OR($AT14=98,$AT14=2,$CA14=97,$CA14=98,$AP14=1,$AP14=3,$AP14=99),"1845-01-01",IF($AT14=55,"1846-01-01"," "))) -> 1845-01-01 | CU14: =IF($CA14<=10,"",IF(OR($AT14=98,$AT14=2,$CA14=97,$CA14=98,$AP14=1,$AP14=3,$AP14=99),98,IF($AT14=55,55," "))) -> 98 | CV14: =IF($CA14<=10,"",IF(OR($AT14=98,$AT14=2,$CA14=97,$CA14=98,$AP14=1,$AP14=3,$AP14=99),98,IF($AT14=55,55," "))) -> 98 | CW14: =IF(OR($AP14=1,$AP14=3,$AP14=99),2,IF($AP14=55,55," ")) -> 2 | CX14: =IF(OR($AP14=1,$AP14=3,$AP14=99,$CW14=2,$CW14=3),98,IF($AP14=55,55," ")) -> 98 | CY14: =IF(OR($AP14=1,$AP14=3,$AP14=99,$CW14=2,$CW14=3),"1845-01-01",IF($AP14=55,"1846-01-01"," ")) -> 1845-01-01 | CZ14: =IF(OR($AP14=1,$AP14=3,$AP14=99,$CW14=2,$CW14=3),98,IF($AP14=55,55,"230010094901")) -> 98 | DA14: =IF(OR($AP14=1,$AP14=3,$AP14=99,$CW14=2,$CW14=3),98,IF($AP14=55,55," ")) -> 98 | DB14: =IF(OR($AP14=1,$AP14=3,$AP14=99,$CW14=2,$CW14=3),98,IF($AP14=55,55," ")) -> 98 | DC14: =IF(OR($AP14=1,$AP14=3,$AP14=99,$CX14<=1,$CW14=2,$CW14=3),"1845-01-01",IF($AP14=55,"1846-01-01"," ")) -> 1845-01-01 | DD14: =IF(OR($AP14=1,$AP14=3,$AP14=99,$CX14<=1,$CW14=2,$CW14=3),98,IF($AP14=55,55," ")) -> 98 | DE14: =IF(OR($AP14=1,$AP14=3,$AP14=99,$CX14<=1,$CW14=2,$CW14=3),98,IF($AP14=55,55," ")) -> 98 | DF14: =IF(OR($AP14=1,$AP14=3,$AP14=99,$CX14<=1,$CW14=2,$CW14=3),98,IF($AP14=55,55," ")) -> 98 | DG14: =IF(OR($AP14=1,$AP14=3,$AP14=99,$CX14<=1,$CW14=2,$CW14=3),98,IF($AP14=55,55," ")) -> 98 | DH14: =IF(OR($AP14=1,$AP14=3,$AP14=99,$CW14=2,$CW14=3),98,IF($AP14=55,55," ")) -> 98 | DI14: =IF(OR($AP14=1,$AP14=3,$AP14=99),98,IF($AP14=55,55," ")) -> 98 | DJ14: =IF(OR($AP14=1,$AP14=3,$AP14=98,$DI14=98,$DI14=2,$AP14=99),98,IF($AP14=55,55," ")) -> 98 | DK14: =IF(OR($AP14=1,$AP14=3,$AP14=98,$DI14=98,$DI14=2,$AP14=99),"1845-01-01",IF($AP14=55,"1846-01-01"," ")) -> 1845-01-01 | DL14: =IF(OR($AP14=1,$AP14=3,$AP14=98,$DI14=98,$DI14=2,$AP14=99),98,IF($AP14=55,55," ")) -> 98 | DM14: =IF(OR($AP14=1,$AP14=3,$AP14=98,$DI14=98,$DI14=2,$AP14=99),98,IF($AP14=55,55," ")) -> 98 | DN14: =IF(OR($AP14=1,$AP14=3,$AP14=98,$DI14=98,$DI14=2,$AP14=99),98,IF($AP14=55,55," ")) -> 98 | DO14: =IF(OR($AP14=1,$AP14=3,$AP14=98,$DI14=98,$DI14=2,$AP14=99),98,IF($AP14=55,55,"230010094901")) -> 98 | DP14: =IF(OR($AP14=1,$AP14=3,$AP14=98,$DI14=98,$DI14=2,$AP14=99,DN14<=1),98,IF($AP14=55,55," ")) -> 98 | DQ14: =IF(OR($AP14=1,$AP14=3,$AP14=98,$DI14=98,$DI14=2,$AP14=99),"1845-01-01",IF($AP14=55,"1846-01-01"," ")) -> 1845-01-01 | DR14: =IF(OR($AP14=1,$AP14=3,$AP14=98,$DI14=98,$DI14=2,$AP14=99),98,IF($AP14=55,55," ")) -> 98 | DS14: =IF(OR($AP14=1,$AP14=3,$AP14=98,$AP14=99,$DI14=98,$DI14=2,$DR14<>2),98,IF($AP14=55,55," ")) -> 98 | DT14: =IF(OR($AP14=1,$AP14=3,$AP14=98,$AP14=99,$DI14=98,$DI14=2,),"1845-01-01",IF($AP14=55,"1846-01-01"," ")) -> 1845-01-01 | DU14: =IF(OR($AP14=1,$AP14=3,$AP14=98,$AP14=99,$DI14=98,$DI14=2,$DT14="1845-01-01"),98,IF($AP14=55,55," ")) -> 98 | DV14: =IF(OR($AP14=1,$AP14=3,$AP14=98,$AP14=99,$DI14=98,$DI14=2,$DT14="1845-01-01"),98,IF($AP14=55,55," ")) -> 98 | DW14: =IF(OR($AP14=1,$AP14=3,$AP14=98,$AP14=99,$DI14=98,$DI14=2,$DT14="1845-01-01"),98,IF($AP14=55,55," ")) -> 98 | DX14: =IF(OR($AP14=1,$AP14=3,$AP14=98,$AP14=99,$DI14=98,$DI14=2,$DT14="1845-01-01"),98,IF($AP14=55,55," ")) -> 98 | DY14: =IF(OR($AP14=1,$AP14=3,$AP14=98,$AP14=99,$DI14=98,$DI14=2,$DT14="1845-01-01"),98,IF($AP14=55,55," ")) -> 98 | DZ14: =IF(OR($AP14=1,$AP14=3,$AP14=99,$AP14=98,$DI14=98,$DI14=2,$DT14="1845-01-01"),"1845-01-01",IF($AP14=55,"1846-01-01"," ")) -> 1845-01-01 | EA14: =IF(OR($AP14=1,$AP14=3,$AP14=98,$AP14=99,$DI14=98,$DI14=2,$DT14="1845-01-01"),98,IF($AP14=55,55," ")) -> 98 | EB14: =IF(OR($AP14=1,$AP14=3,$AP14=98,$AP14=99,$DI14=98,$DI14=2,$DT14="1845-01-01",$EA14<>2),98,IF($AP14=55,55," ")) -> 98 | EC14: =IF(OR($AP14=1,$AP14=3,$AP14=99),98,IF($AP14=55,55," ")) -> 98 | ED14: =IF(OR($AP14=1,$AP14=3,$EC14=98),98,IF($AP14=55,55," ")) -> 98 | EE14: =IF(OR($AP14=1,$AP14=3,$EC14=98),98,IF($AP14=55,55," ")) -> 98 | EF14: =IF(OR($AP14=1,$AP14=3,$EC14=98),"1845-01-01",IF($AP14=55,"1846-01-01"," ")) -> 1845-01-01 | EG14: =IF(OR($AP14=1,$AP14=3,$EC14=98),98,IF($AP14=55,55,"230010094901")) -> 98 | EH14: =IF(OR($AP14=1,$AP14=3,$AP14=99),98,IF($AP14=55,55," ")) -> 98 | EI14: =IF(OR($AP14=1,$AP14=3,,$AP14=99,$EH14=98),"1845-01-01",IF($AP14=55,"1846-01-01"," ")) -> 1845-01-01 | EJ14: =IF(OR($AP14=1,$AP14=3,,$AP14=99,$EH14=98),98,IF($AP14=55,55," ")) -> 98 | EK14: =IF(OR($AP14=1,$AP14=3,$AP14=99),2,IF($AP14=55,55," ")) -> 2 | EL14: =IF(OR($AP14=1,$AP14=3,$AP14=99,$EK14=2),2,IF($AP14=55,55," ")) -> 2 | EM14: =IF(OR($AP14=1,$AP14=3,$AP14=99,$EK14=2),2,IF($AP14=55,55," ")) -> 2 | EN14: =IF(OR($AP14=1,$AP14=3,$AP14=99,$EK14=2),2,IF($AP14=55,55," ")) -> 2 | EO14: =IF(OR($AP14=1,$AP14=3,$AP14=99,$EK14=2),2,IF($AP14=55,55," ")) -> 2 | EP14: =IF(OR($AP14=1,$AP14=3,$AP14=99,$EK14=2),2,IF($AP14=55,55," ")) -> 2 | EQ14: =IF(OR($AP14=1,$AP14=3,$AP14=99,$EK14=2),2,IF($AP14=55,55," ")) -> 2 | ER14: =IF(OR($AP14=1,$AP14=3,$AP14=99,$EK14=2),"1845-01-01",IF($AP14=55,"1846-01-01"," ")) -> 1845-01-01 | ES14: =IF(OR($AP14=1,$AP14=3,$AP14=99,$EK14=2),98,IF($AP14=55,55," ")) -> 98 | ET14: =IF(OR($AP14=1,$AP14=3,$AP14=99,$EK14=2),98,IF($AP14=55,55," ")) -> 98 | EU14: =IF($AP14=55,"1846-01-01",IF(OR($ET14=2,$ET14=98),"1845-01-01"," ")) -> 1845-01-01 | EV14: =IF($AP14=55,55,IF(OR($ET14=2,$ET14=98),98," ")) -> 98 | EW14: =IF(OR($AP14=1,$AP14=3,$AP14=99),98,IF($AP14=55,55," ")) -> 98 | EX14: =IF($AP14=55,55,IF(OR($EW14=98,$EW14=2),"1845-01-01"," ")) -> 1845-01-01 | EY14: =IF($AP14=55,55,IF(OR($EW14=98,$EW14=2),98,IF($EW14<>" ","230010094901",""))) -> 98 | EZ14: =IF($AP14=55,55,IF(OR($EW14=98,$EW14=2),4," ")) -> 4 | FA14: =IF($AP14=55,55,IF(OR($AP14=1,$AP14=3),98," ")) | FB14: =IF($AP14=55,55,IF(OR($AP14=99,$FD14=2),98,IF($AP14=1,7,IF($AP14=3,9,IF(OR($AP14=5,$AP14=6),8," "))))) -> 98 | FC14: =IF($AP14=1,5,IF($AP14=3,7,IF($AP14=99,6,IF($FB14=98,99,IF($AP14=55,55,""))))) -> 6 | FD14: =IF($AP14=55,55,IF($AP14=99,99,"")) -> 99 | FE14: =IF($FD14=2,4,IF($FD14=55,14,IF(YEAR($S14)=2023,2,IF(AP14=3,0,"")))) | FF14: =IF($AP14=1,10,IF($AP14=99,8, IF($FD14=2,12,IF($AP14=3,7,"")))) -> 8 | FH14: =IF(OR($FD14=1,$FD14=99),"1845-01-01"," ") -> 1845-01-01 | FI14: =IF(OR($FD14=1,$FD14=99),98," ") -> 98 | FL14: =COUNTIF(R14:FI14,"<>""")-COUNTBLANK(R14:FI14) -> 143 | FM14: =+FL14/147 -> 0.97278912 | FN14: =+VLOOKUP(R14,'CIE-10'!$A$3:$C$558,3,FALSE) -> 14= Otros órganos respiratorios e intratorácicos | FU14: =SUM(FP14:FS14) -> 0
